{
  "updated": "2026-06-05",
  "total": 143,
  "scores": [
    {
      "code": "2002",
      "name": "中鋼",
      "sector": "鋼鐵",
      "price": 19.3,
      "chg_pct": 0.26,
      "k": 30.9,
      "d": 34.0,
      "j": 24.7,
      "ma5": 19.2,
      "ma20": 18.77,
      "ma_gap": 2.3,
      "volume": 52448,
      "avg_vol5": 80808.2,
      "vol_ratio": 0.65,
      "buy_days": 6,
      "net_buy_ratio": 0.54,
      "foreign_buy_days": 3,
      "dif": 0.0763,
      "score": 4,
      "criteria": {
        "s1": true,
        "s2": false,
        "s3": true,
        "s4": false,
        "s5": true,
        "s6": true
      },
      "updated": "2026-06-05"
    },
    {
      "code": "2330",
      "name": "台積電",
      "sector": "半導體",
      "price": 2365.0,
      "chg_pct": -0.84,
      "k": 69.8,
      "d": 72.5,
      "j": 64.4,
      "ma5": 2382.0,
      "ma20": 2290.0,
      "ma_gap": 4.0,
      "volume": 43404,
      "avg_vol5": 53804.4,
      "vol_ratio": 0.81,
      "buy_days": 3,
      "net_buy_ratio": 6.71,
      "foreign_buy_days": 0,
      "dif": 64.3059,
      "score": 3,
      "criteria": {
        "s1": true,
        "s2": true,
        "s3": true,
        "s4": false,
        "s5": false,
        "s6": false
      },
      "updated": "2026-06-05"
    },
    {
      "code": "2884",
      "name": "玉山金",
      "sector": "金融保險",
      "price": 33.35,
      "chg_pct": -0.3,
      "k": 78.3,
      "d": 60.5,
      "j": 113.9,
      "ma5": 32.69,
      "ma20": 31.82,
      "ma_gap": 2.7,
      "volume": 49409,
      "avg_vol5": 81606.3,
      "vol_ratio": 0.61,
      "buy_days": 4,
      "net_buy_ratio": 0.96,
      "foreign_buy_days": 6,
      "dif": 0.1523,
      "score": 3,
      "criteria": {
        "s1": true,
        "s2": false,
        "s3": false,
        "s4": false,
        "s5": true,
        "s6": true
      },
      "updated": "2026-06-05"
    },
    {
      "code": "5880",
      "name": "合庫金",
      "sector": "金融保險",
      "price": 23.45,
      "chg_pct": -1.05,
      "k": 69.3,
      "d": 62.8,
      "j": 82.5,
      "ma5": 23.29,
      "ma20": 22.9,
      "ma_gap": 1.7,
      "volume": 28748,
      "avg_vol5": 41651.8,
      "vol_ratio": 0.69,
      "buy_days": 10,
      "net_buy_ratio": 0.17,
      "foreign_buy_days": 0,
      "dif": 0.0587,
      "score": 3,
      "criteria": {
        "s1": true,
        "s2": false,
        "s3": true,
        "s4": false,
        "s5": true,
        "s6": false
      },
      "updated": "2026-06-05"
    },
    {
      "code": "2379",
      "name": "瑞昱",
      "sector": "半導體",
      "price": 643.0,
      "chg_pct": 3.04,
      "k": 61.2,
      "d": 65.9,
      "j": 51.8,
      "ma5": 635.0,
      "ma20": 588.15,
      "ma_gap": 8.0,
      "volume": 8953,
      "avg_vol5": 8341.7,
      "vol_ratio": 1.07,
      "buy_days": 10,
      "net_buy_ratio": 31.47,
      "foreign_buy_days": 0,
      "dif": 24.903,
      "score": 3,
      "criteria": {
        "s1": true,
        "s2": true,
        "s3": true,
        "s4": false,
        "s5": false,
        "s6": false
      },
      "updated": "2026-06-05"
    },
    {
      "code": "1402",
      "name": "遠東新",
      "sector": "紡織",
      "price": 27.55,
      "chg_pct": 0.0,
      "k": 78.3,
      "d": 68.1,
      "j": 98.7,
      "ma5": 26.74,
      "ma20": 26.35,
      "ma_gap": 1.5,
      "volume": 71494,
      "avg_vol5": 139031.7,
      "vol_ratio": 0.51,
      "buy_days": 3,
      "net_buy_ratio": 37.21,
      "foreign_buy_days": 0,
      "dif": 0.1252,
      "score": 3,
      "criteria": {
        "s1": true,
        "s2": true,
        "s3": false,
        "s4": false,
        "s5": true,
        "s6": false
      },
      "updated": "2026-06-05"
    },
    {
      "code": "9910",
      "name": "豐泰",
      "sector": "其他",
      "price": 76.9,
      "chg_pct": -4.47,
      "k": 65.8,
      "d": 63.5,
      "j": 70.4,
      "ma5": 78.16,
      "ma20": 71.98,
      "ma_gap": 8.6,
      "volume": 12287,
      "avg_vol5": 9171.6,
      "vol_ratio": 1.34,
      "buy_days": 4,
      "net_buy_ratio": 33.0,
      "foreign_buy_days": 0,
      "dif": 0.9846,
      "score": 3,
      "criteria": {
        "s1": true,
        "s2": true,
        "s3": true,
        "s4": false,
        "s5": false,
        "s6": false
      },
      "updated": "2026-06-05"
    },
    {
      "code": "2360",
      "name": "致茂",
      "sector": "其他電子",
      "price": 2565.0,
      "chg_pct": -2.1,
      "k": 54.8,
      "d": 60.3,
      "j": 43.7,
      "ma5": 2546.0,
      "ma20": 2397.75,
      "ma_gap": 6.2,
      "volume": 2348,
      "avg_vol5": 3281.5,
      "vol_ratio": 0.72,
      "buy_days": 2,
      "net_buy_ratio": 6.79,
      "foreign_buy_days": 4,
      "dif": 135.1675,
      "score": 3,
      "criteria": {
        "s1": false,
        "s2": true,
        "s3": true,
        "s4": false,
        "s5": false,
        "s6": true
      },
      "updated": "2026-06-05"
    },
    {
      "code": "2317",
      "name": "鴻海",
      "sector": "其他電子",
      "price": 284.5,
      "chg_pct": -2.9,
      "k": 69.8,
      "d": 77.6,
      "j": 54.3,
      "ma5": 296.3,
      "ma20": 264.73,
      "ma_gap": 11.9,
      "volume": 93159,
      "avg_vol5": 173747.2,
      "vol_ratio": 0.54,
      "buy_days": 8,
      "net_buy_ratio": 0.28,
      "foreign_buy_days": 0,
      "dif": 17.1344,
      "score": 2,
      "criteria": {
        "s1": true,
        "s2": false,
        "s3": true,
        "s4": false,
        "s5": false,
        "s6": false
      },
      "updated": "2026-06-05"
    },
    {
      "code": "2454",
      "name": "聯發科",
      "sector": "半導體",
      "price": 4300.0,
      "chg_pct": -2.93,
      "k": 47.3,
      "d": 63.7,
      "j": 14.5,
      "ma5": 4471.0,
      "ma20": 3958.0,
      "ma_gap": 13.0,
      "volume": 11919,
      "avg_vol5": 16100.9,
      "vol_ratio": 0.74,
      "buy_days": 0,
      "net_buy_ratio": 0.0,
      "foreign_buy_days": 3,
      "dif": 461.9682,
      "score": 2,
      "criteria": {
        "s1": false,
        "s2": false,
        "s3": true,
        "s4": false,
        "s5": false,
        "s6": true
      },
      "updated": "2026-06-05"
    },
    {
      "code": "2303",
      "name": "聯電",
      "sector": "半導體",
      "price": 131.5,
      "chg_pct": 5.2,
      "k": 44.9,
      "d": 61.6,
      "j": 11.7,
      "ma5": 134.9,
      "ma20": 121.9,
      "ma_gap": 10.7,
      "volume": 377903,
      "avg_vol5": 359415.3,
      "vol_ratio": 1.05,
      "buy_days": 0,
      "net_buy_ratio": 0.0,
      "foreign_buy_days": 5,
      "dif": 13.3402,
      "score": 2,
      "criteria": {
        "s1": false,
        "s2": false,
        "s3": true,
        "s4": false,
        "s5": false,
        "s6": true
      },
      "updated": "2026-06-05"
    },
    {
      "code": "2412",
      "name": "中華電",
      "sector": "通信網路",
      "price": 141.0,
      "chg_pct": -0.35,
      "k": 66.7,
      "d": 54.6,
      "j": 90.8,
      "ma5": 141.2,
      "ma20": 138.3,
      "ma_gap": 2.1,
      "volume": 11586,
      "avg_vol5": 20619.1,
      "vol_ratio": 0.56,
      "buy_days": 10,
      "net_buy_ratio": 1.71,
      "foreign_buy_days": 0,
      "dif": 1.1925,
      "score": 2,
      "criteria": {
        "s1": true,
        "s2": false,
        "s3": true,
        "s4": false,
        "s5": false,
        "s6": false
      },
      "updated": "2026-06-05"
    },
    {
      "code": "2382",
      "name": "廣達",
      "sector": "電腦週邊",
      "price": 390.5,
      "chg_pct": -3.34,
      "k": 74.2,
      "d": 74.1,
      "j": 74.3,
      "ma5": 396.9,
      "ma20": 337.27,
      "ma_gap": 17.7,
      "volume": 69276,
      "avg_vol5": 100164.1,
      "vol_ratio": 0.69,
      "buy_days": 12,
      "net_buy_ratio": 28.65,
      "foreign_buy_days": 0,
      "dif": 20.1201,
      "score": 2,
      "criteria": {
        "s1": true,
        "s2": true,
        "s3": false,
        "s4": false,
        "s5": false,
        "s6": false
      },
      "updated": "2026-06-05"
    },
    {
      "code": "1216",
      "name": "統一",
      "sector": "食品",
      "price": 73.8,
      "chg_pct": 0.27,
      "k": 73.9,
      "d": 60.2,
      "j": 101.4,
      "ma5": 73.72,
      "ma20": 73.18,
      "ma_gap": 0.7,
      "volume": 9454,
      "avg_vol5": 24275.8,
      "vol_ratio": 0.39,
      "buy_days": 14,
      "net_buy_ratio": 0.44,
      "foreign_buy_days": 2,
      "dif": 0.3415,
      "score": 2,
      "criteria": {
        "s1": true,
        "s2": false,
        "s3": false,
        "s4": false,
        "s5": true,
        "s6": false
      },
      "updated": "2026-06-05"
    },
    {
      "code": "2892",
      "name": "第一金",
      "sector": "金融保險",
      "price": 29.3,
      "chg_pct": -0.85,
      "k": 76.6,
      "d": 58.8,
      "j": 112.0,
      "ma5": 28.75,
      "ma20": 28.47,
      "ma_gap": 1.0,
      "volume": 57303,
      "avg_vol5": 78201.4,
      "vol_ratio": 0.73,
      "buy_days": 6,
      "net_buy_ratio": 0.09,
      "foreign_buy_days": 0,
      "dif": 0.0131,
      "score": 2,
      "criteria": {
        "s1": true,
        "s2": false,
        "s3": false,
        "s4": false,
        "s5": true,
        "s6": false
      },
      "updated": "2026-06-05"
    },
    {
      "code": "2609",
      "name": "陽明",
      "sector": "航運",
      "price": 54.5,
      "chg_pct": 2.44,
      "k": 65.4,
      "d": 67.8,
      "j": 60.7,
      "ma5": 53.98,
      "ma20": 51.53,
      "ma_gap": 4.8,
      "volume": 78583,
      "avg_vol5": 53931.8,
      "vol_ratio": 1.46,
      "buy_days": 0,
      "net_buy_ratio": 0.0,
      "foreign_buy_days": 9,
      "dif": 0.8482,
      "score": 2,
      "criteria": {
        "s1": false,
        "s2": false,
        "s3": true,
        "s4": false,
        "s5": false,
        "s6": true
      },
      "updated": "2026-06-05"
    },
    {
      "code": "2301",
      "name": "光寶科",
      "sector": "電腦週邊",
      "price": 230.0,
      "chg_pct": -7.44,
      "k": 49.7,
      "d": 57.3,
      "j": 34.7,
      "ma5": 238.1,
      "ma20": 223.97,
      "ma_gap": 6.3,
      "volume": 45960,
      "avg_vol5": 49650.9,
      "vol_ratio": 0.93,
      "buy_days": 1,
      "net_buy_ratio": 0.16,
      "foreign_buy_days": 6,
      "dif": 14.7576,
      "score": 2,
      "criteria": {
        "s1": false,
        "s2": false,
        "s3": true,
        "s4": false,
        "s5": false,
        "s6": true
      },
      "updated": "2026-06-05"
    },
    {
      "code": "2395",
      "name": "研華",
      "sector": "電腦週邊",
      "price": 496.0,
      "chg_pct": -4.98,
      "k": 54.5,
      "d": 65.6,
      "j": 32.4,
      "ma5": 512.6,
      "ma20": 487.23,
      "ma_gap": 5.2,
      "volume": 5251,
      "avg_vol5": 6024.9,
      "vol_ratio": 0.87,
      "buy_days": 6,
      "net_buy_ratio": 0.1,
      "foreign_buy_days": 0,
      "dif": 28.7589,
      "score": 2,
      "criteria": {
        "s1": true,
        "s2": false,
        "s3": true,
        "s4": false,
        "s5": false,
        "s6": false
      },
      "updated": "2026-06-05"
    },
    {
      "code": "8046",
      "name": "南電",
      "sector": "電子零組件",
      "price": 845.0,
      "chg_pct": -3.76,
      "k": 37.3,
      "d": 45.1,
      "j": 21.6,
      "ma5": 878.8,
      "ma20": 867.4,
      "ma_gap": 1.3,
      "volume": 14137,
      "avg_vol5": 16021.9,
      "vol_ratio": 0.88,
      "buy_days": 0,
      "net_buy_ratio": 0.0,
      "foreign_buy_days": 3,
      "dif": 17.2991,
      "score": 2,
      "criteria": {
        "s1": false,
        "s2": false,
        "s3": true,
        "s4": false,
        "s5": false,
        "s6": true
      },
      "updated": "2026-06-05"
    },
    {
      "code": "2883",
      "name": "開發金",
      "sector": "金融保險",
      "price": 27.6,
      "chg_pct": 0.73,
      "k": 86.1,
      "d": 77.1,
      "j": 103.9,
      "ma5": 25.35,
      "ma20": 22.74,
      "ma_gap": 11.5,
      "volume": 312820,
      "avg_vol5": 210363.7,
      "vol_ratio": 1.49,
      "buy_days": 4,
      "net_buy_ratio": 32.72,
      "foreign_buy_days": 0,
      "dif": 1.2133,
      "score": 2,
      "criteria": {
        "s1": true,
        "s2": true,
        "s3": false,
        "s4": false,
        "s5": false,
        "s6": false
      },
      "updated": "2026-06-05"
    },
    {
      "code": "2887",
      "name": "台新金",
      "sector": "金融保險",
      "price": 28.6,
      "chg_pct": 0.18,
      "k": 82.5,
      "d": 70.9,
      "j": 105.8,
      "ma5": 27.23,
      "ma20": 24.39,
      "ma_gap": 11.6,
      "volume": 143711,
      "avg_vol5": 242940.7,
      "vol_ratio": 0.59,
      "buy_days": 12,
      "net_buy_ratio": 10.91,
      "foreign_buy_days": 1,
      "dif": 0.9517,
      "score": 2,
      "criteria": {
        "s1": true,
        "s2": true,
        "s3": false,
        "s4": false,
        "s5": false,
        "s6": false
      },
      "updated": "2026-06-05"
    },
    {
      "code": "2890",
      "name": "永豐金",
      "sector": "金融保險",
      "price": 32.7,
      "chg_pct": -1.36,
      "k": 86.8,
      "d": 75.5,
      "j": 109.2,
      "ma5": 32.06,
      "ma20": 30.45,
      "ma_gap": 5.3,
      "volume": 43991,
      "avg_vol5": 61281.5,
      "vol_ratio": 0.72,
      "buy_days": 8,
      "net_buy_ratio": 0.91,
      "foreign_buy_days": 6,
      "dif": 0.2822,
      "score": 2,
      "criteria": {
        "s1": true,
        "s2": false,
        "s3": false,
        "s4": false,
        "s5": false,
        "s6": true
      },
      "updated": "2026-06-05"
    },
    {
      "code": "5871",
      "name": "中租-KY",
      "sector": "其他",
      "price": 118.0,
      "chg_pct": -0.84,
      "k": 73.1,
      "d": 57.9,
      "j": 103.5,
      "ma5": 115.5,
      "ma20": 110.6,
      "ma_gap": 4.4,
      "volume": 21924,
      "avg_vol5": 20359.5,
      "vol_ratio": 1.08,
      "buy_days": 13,
      "net_buy_ratio": 41.09,
      "foreign_buy_days": 0,
      "dif": 0.9214,
      "score": 2,
      "criteria": {
        "s1": true,
        "s2": true,
        "s3": false,
        "s4": false,
        "s5": false,
        "s6": false
      },
      "updated": "2026-06-05"
    },
    {
      "code": "5876",
      "name": "上海商銀",
      "sector": "金融保險",
      "price": 40.75,
      "chg_pct": 0.0,
      "k": 68.0,
      "d": 59.0,
      "j": 86.0,
      "ma5": 40.62,
      "ma20": 40.07,
      "ma_gap": 1.4,
      "volume": 10574,
      "avg_vol5": 17111.7,
      "vol_ratio": 0.62,
      "buy_days": 0,
      "net_buy_ratio": 0.0,
      "foreign_buy_days": 0,
      "dif": 0.2754,
      "score": 2,
      "criteria": {
        "s1": false,
        "s2": false,
        "s3": true,
        "s4": false,
        "s5": true,
        "s6": false
      },
      "updated": "2026-06-05"
    },
    {
      "code": "2105",
      "name": "正新",
      "sector": "橡膠",
      "price": 34.1,
      "chg_pct": -1.3,
      "k": 73.3,
      "d": 68.3,
      "j": 83.4,
      "ma5": 34.04,
      "ma20": 32.51,
      "ma_gap": 4.7,
      "volume": 39168,
      "avg_vol5": 29305.3,
      "vol_ratio": 1.34,
      "buy_days": 5,
      "net_buy_ratio": 39.4,
      "foreign_buy_days": 0,
      "dif": 0.6158,
      "score": 2,
      "criteria": {
        "s1": true,
        "s2": true,
        "s3": false,
        "s4": false,
        "s5": false,
        "s6": false
      },
      "updated": "2026-06-05"
    },
    {
      "code": "2345",
      "name": "智邦",
      "sector": "通信網路",
      "price": 2490.0,
      "chg_pct": -0.8,
      "k": 39.5,
      "d": 42.5,
      "j": 33.4,
      "ma5": 2504.0,
      "ma20": 2504.25,
      "ma_gap": 0.0,
      "volume": 2518,
      "avg_vol5": 4021.7,
      "vol_ratio": 0.63,
      "buy_days": 2,
      "net_buy_ratio": 7.58,
      "foreign_buy_days": 0,
      "dif": 76.9866,
      "score": 2,
      "criteria": {
        "s1": false,
        "s2": true,
        "s3": true,
        "s4": false,
        "s5": false,
        "s6": false
      },
      "updated": "2026-06-05"
    },
    {
      "code": "3045",
      "name": "台灣大",
      "sector": "通信網路",
      "price": 116.0,
      "chg_pct": 0.0,
      "k": 77.7,
      "d": 63.6,
      "j": 105.9,
      "ma5": 115.5,
      "ma20": 113.22,
      "ma_gap": 2.0,
      "volume": 7036,
      "avg_vol5": 15188.1,
      "vol_ratio": 0.46,
      "buy_days": 1,
      "net_buy_ratio": 4.05,
      "foreign_buy_days": 3,
      "dif": 1.0362,
      "score": 2,
      "criteria": {
        "s1": false,
        "s2": false,
        "s3": false,
        "s4": false,
        "s5": true,
        "s6": true
      },
      "updated": "2026-06-05"
    },
    {
      "code": "6176",
      "name": "瑞儀",
      "sector": "光電",
      "price": 101.0,
      "chg_pct": -0.49,
      "k": 24.8,
      "d": 33.6,
      "j": 7.3,
      "ma5": 102.7,
      "ma20": 103.25,
      "ma_gap": 0.5,
      "volume": 15181,
      "avg_vol5": 11046.7,
      "vol_ratio": 1.37,
      "buy_days": 0,
      "net_buy_ratio": 0.0,
      "foreign_buy_days": 7,
      "dif": 0.646,
      "score": 2,
      "criteria": {
        "s1": false,
        "s2": false,
        "s3": true,
        "s4": false,
        "s5": false,
        "s6": true
      },
      "updated": "2026-06-05"
    },
    {
      "code": "3231",
      "name": "緯創",
      "sector": "電腦週邊",
      "price": 171.0,
      "chg_pct": -2.84,
      "k": 68.7,
      "d": 77.0,
      "j": 52.0,
      "ma5": 181.2,
      "ma20": 151.43,
      "ma_gap": 19.7,
      "volume": 75786,
      "avg_vol5": 159008.3,
      "vol_ratio": 0.48,
      "buy_days": 8,
      "net_buy_ratio": 0.18,
      "foreign_buy_days": 1,
      "dif": 10.7088,
      "score": 2,
      "criteria": {
        "s1": true,
        "s2": false,
        "s3": true,
        "s4": false,
        "s5": false,
        "s6": false
      },
      "updated": "2026-06-05"
    },
    {
      "code": "6505",
      "name": "台塑化",
      "sector": "油電燃氣",
      "price": 55.3,
      "chg_pct": -3.83,
      "k": 77.7,
      "d": 69.0,
      "j": 95.0,
      "ma5": 55.3,
      "ma20": 52.32,
      "ma_gap": 5.7,
      "volume": 10995,
      "avg_vol5": 13335.6,
      "vol_ratio": 0.82,
      "buy_days": 3,
      "net_buy_ratio": 0.17,
      "foreign_buy_days": 6,
      "dif": 0.4677,
      "score": 2,
      "criteria": {
        "s1": true,
        "s2": false,
        "s3": false,
        "s4": false,
        "s5": false,
        "s6": true
      },
      "updated": "2026-06-05"
    },
    {
      "code": "1722",
      "name": "台肥",
      "sector": "化學",
      "price": 48.25,
      "chg_pct": 0.42,
      "k": 83.4,
      "d": 74.1,
      "j": 102.0,
      "ma5": 47.67,
      "ma20": 46.55,
      "ma_gap": 2.4,
      "volume": 5612,
      "avg_vol5": 4179.5,
      "vol_ratio": 1.34,
      "buy_days": 0,
      "net_buy_ratio": 0.0,
      "foreign_buy_days": 7,
      "dif": 0.371,
      "score": 2,
      "criteria": {
        "s1": false,
        "s2": false,
        "s3": false,
        "s4": false,
        "s5": true,
        "s6": true
      },
      "updated": "2026-06-05"
    },
    {
      "code": "6508",
      "name": "惠光",
      "sector": "化學",
      "price": 24.05,
      "chg_pct": -0.41,
      "k": 63.3,
      "d": 46.9,
      "j": 96.2,
      "ma5": 23.69,
      "ma20": 23.74,
      "ma_gap": 0.2,
      "volume": 105,
      "avg_vol5": 114.9,
      "vol_ratio": 0.92,
      "buy_days": 0,
      "net_buy_ratio": 0.0,
      "foreign_buy_days": 3,
      "dif": -0.41,
      "score": 2,
      "criteria": {
        "s1": false,
        "s2": false,
        "s3": false,
        "s4": false,
        "s5": true,
        "s6": true
      },
      "updated": "2026-06-05"
    },
    {
      "code": "2371",
      "name": "大同",
      "sector": "電機機械",
      "price": 30.3,
      "chg_pct": -5.46,
      "k": 60.2,
      "d": 59.6,
      "j": 61.4,
      "ma5": 30.82,
      "ma20": 29.71,
      "ma_gap": 3.7,
      "volume": 29510,
      "avg_vol5": 41238.3,
      "vol_ratio": 0.72,
      "buy_days": 4,
      "net_buy_ratio": 0.35,
      "foreign_buy_days": 0,
      "dif": 0.0373,
      "score": 2,
      "criteria": {
        "s1": true,
        "s2": false,
        "s3": true,
        "s4": false,
        "s5": false,
        "s6": false
      },
      "updated": "2026-06-05"
    },
    {
      "code": "2014",
      "name": "中鴻",
      "sector": "鋼鐵",
      "price": 18.75,
      "chg_pct": 0.27,
      "k": 55.3,
      "d": 52.6,
      "j": 60.8,
      "ma5": 18.59,
      "ma20": 17.94,
      "ma_gap": 3.6,
      "volume": 6357,
      "avg_vol5": 10747.2,
      "vol_ratio": 0.59,
      "buy_days": 0,
      "net_buy_ratio": 0.0,
      "foreign_buy_days": 3,
      "dif": 0.2073,
      "score": 2,
      "criteria": {
        "s1": false,
        "s2": false,
        "s3": true,
        "s4": false,
        "s5": false,
        "s6": true
      },
      "updated": "2026-06-05"
    },
    {
      "code": "3044",
      "name": "健鼎",
      "sector": "電子零組件",
      "price": 498.0,
      "chg_pct": -2.73,
      "k": 43.0,
      "d": 52.3,
      "j": 24.5,
      "ma5": 509.2,
      "ma20": 497.5,
      "ma_gap": 2.4,
      "volume": 3630,
      "avg_vol5": 4396.3,
      "vol_ratio": 0.83,
      "buy_days": 1,
      "net_buy_ratio": 9.17,
      "foreign_buy_days": 0,
      "dif": 15.571,
      "score": 2,
      "criteria": {
        "s1": false,
        "s2": true,
        "s3": true,
        "s4": false,
        "s5": false,
        "s6": false
      },
      "updated": "2026-06-05"
    },
    {
      "code": "6271",
      "name": "同欣電",
      "sector": "電子零組件",
      "price": 236.5,
      "chg_pct": -2.87,
      "k": 49.4,
      "d": 65.2,
      "j": 17.6,
      "ma5": 245.4,
      "ma20": 218.7,
      "ma_gap": 12.2,
      "volume": 2111,
      "avg_vol5": 2600.9,
      "vol_ratio": 0.81,
      "buy_days": 0,
      "net_buy_ratio": 0.0,
      "foreign_buy_days": 4,
      "dif": 18.2532,
      "score": 2,
      "criteria": {
        "s1": false,
        "s2": false,
        "s3": true,
        "s4": false,
        "s5": false,
        "s6": true
      },
      "updated": "2026-06-05"
    },
    {
      "code": "3023",
      "name": "信邦",
      "sector": "電子零組件",
      "price": 329.0,
      "chg_pct": 5.28,
      "k": 73.9,
      "d": 70.7,
      "j": 80.5,
      "ma5": 318.1,
      "ma20": 308.02,
      "ma_gap": 3.3,
      "volume": 4295,
      "avg_vol5": 1890.6,
      "vol_ratio": 2.27,
      "buy_days": 2,
      "net_buy_ratio": 5.31,
      "foreign_buy_days": 1,
      "dif": 9.0623,
      "score": 2,
      "criteria": {
        "s1": false,
        "s2": true,
        "s3": false,
        "s4": true,
        "s5": false,
        "s6": false
      },
      "updated": "2026-06-05"
    },
    {
      "code": "6415",
      "name": "矽力-KY",
      "sector": "半導體",
      "price": 582.0,
      "chg_pct": 2.11,
      "k": 29.8,
      "d": 46.3,
      "j": -3.1,
      "ma5": 587.0,
      "ma20": 553.65,
      "ma_gap": 6.0,
      "volume": 4298,
      "avg_vol5": 5805.8,
      "vol_ratio": 0.74,
      "buy_days": 0,
      "net_buy_ratio": 0.0,
      "foreign_buy_days": 4,
      "dif": 48.5413,
      "score": 2,
      "criteria": {
        "s1": false,
        "s2": false,
        "s3": true,
        "s4": false,
        "s5": false,
        "s6": true
      },
      "updated": "2026-06-05"
    },
    {
      "code": "3532",
      "name": "台勝科",
      "sector": "半導體",
      "price": 290.0,
      "chg_pct": -0.34,
      "k": 50.6,
      "d": 66.3,
      "j": 19.1,
      "ma5": 312.3,
      "ma20": 269.2,
      "ma_gap": 16.0,
      "volume": 669,
      "avg_vol5": 1186.3,
      "vol_ratio": 0.56,
      "buy_days": 0,
      "net_buy_ratio": 0.0,
      "foreign_buy_days": 4,
      "dif": 27.7094,
      "score": 2,
      "criteria": {
        "s1": false,
        "s2": false,
        "s3": true,
        "s4": false,
        "s5": false,
        "s6": true
      },
      "updated": "2026-06-05"
    },
    {
      "code": "6239",
      "name": "力成",
      "sector": "半導體",
      "price": 338.0,
      "chg_pct": -4.52,
      "k": 53.8,
      "d": 70.2,
      "j": 21.1,
      "ma5": 349.6,
      "ma20": 294.55,
      "ma_gap": 18.7,
      "volume": 16700,
      "avg_vol5": 17508.3,
      "vol_ratio": 0.95,
      "buy_days": 0,
      "net_buy_ratio": 0.0,
      "foreign_buy_days": 4,
      "dif": 34.6897,
      "score": 2,
      "criteria": {
        "s1": false,
        "s2": false,
        "s3": true,
        "s4": false,
        "s5": false,
        "s6": true
      },
      "updated": "2026-06-05"
    },
    {
      "code": "6206",
      "name": "飛捷",
      "sector": "電腦週邊",
      "price": 141.5,
      "chg_pct": 1.07,
      "k": 57.9,
      "d": 62.4,
      "j": 49.0,
      "ma5": 141.3,
      "ma20": 137.4,
      "ma_gap": 2.8,
      "volume": 1904,
      "avg_vol5": 2117.0,
      "vol_ratio": 0.9,
      "buy_days": 0,
      "net_buy_ratio": 0.0,
      "foreign_buy_days": 2,
      "dif": 6.7804,
      "score": 2,
      "criteria": {
        "s1": false,
        "s2": false,
        "s3": true,
        "s4": false,
        "s5": true,
        "s6": false
      },
      "updated": "2026-06-05"
    },
    {
      "code": "4961",
      "name": "天鈺",
      "sector": "半導體",
      "price": 168.5,
      "chg_pct": 0.3,
      "k": 32.9,
      "d": 38.9,
      "j": 20.9,
      "ma5": 171.2,
      "ma20": 172.43,
      "ma_gap": 0.7,
      "volume": 795,
      "avg_vol5": 1101.1,
      "vol_ratio": 0.72,
      "buy_days": 7,
      "net_buy_ratio": 2.64,
      "foreign_buy_days": 1,
      "dif": 2.4491,
      "score": 2,
      "criteria": {
        "s1": true,
        "s2": false,
        "s3": true,
        "s4": false,
        "s5": false,
        "s6": false
      },
      "updated": "2026-06-05"
    },
    {
      "code": "8016",
      "name": "矽創",
      "sector": "半導體",
      "price": 303.5,
      "chg_pct": 0.0,
      "k": 75.7,
      "d": 79.3,
      "j": 68.6,
      "ma5": 304.4,
      "ma20": 290.95,
      "ma_gap": 4.6,
      "volume": 2132,
      "avg_vol5": 2740.8,
      "vol_ratio": 0.78,
      "buy_days": 5,
      "net_buy_ratio": 1.13,
      "foreign_buy_days": 3,
      "dif": 16.8638,
      "score": 2,
      "criteria": {
        "s1": true,
        "s2": false,
        "s3": false,
        "s4": false,
        "s5": false,
        "s6": true
      },
      "updated": "2026-06-05"
    },
    {
      "code": "4938",
      "name": "和碩",
      "sector": "電腦週邊",
      "price": 96.9,
      "chg_pct": -0.1,
      "k": 79.6,
      "d": 80.6,
      "j": 77.7,
      "ma5": 96.28,
      "ma20": 84.41,
      "ma_gap": 14.1,
      "volume": 37969,
      "avg_vol5": 48596.2,
      "vol_ratio": 0.78,
      "buy_days": 5,
      "net_buy_ratio": 38.27,
      "foreign_buy_days": 0,
      "dif": 4.2348,
      "score": 2,
      "criteria": {
        "s1": true,
        "s2": true,
        "s3": false,
        "s4": false,
        "s5": false,
        "s6": false
      },
      "updated": "2026-06-05"
    },
    {
      "code": "3702",
      "name": "大聯大",
      "sector": "電子通路",
      "price": 114.5,
      "chg_pct": -1.72,
      "k": 24.2,
      "d": 37.6,
      "j": -2.5,
      "ma5": 117.3,
      "ma20": 116.5,
      "ma_gap": 0.7,
      "volume": 16516,
      "avg_vol5": 13492.5,
      "vol_ratio": 1.22,
      "buy_days": 0,
      "net_buy_ratio": 0.0,
      "foreign_buy_days": 5,
      "dif": 3.8982,
      "score": 2,
      "criteria": {
        "s1": false,
        "s2": false,
        "s3": true,
        "s4": false,
        "s5": false,
        "s6": true
      },
      "updated": "2026-06-05"
    },
    {
      "code": "2404",
      "name": "漢唐",
      "sector": "其他電子",
      "price": 1205.0,
      "chg_pct": -2.03,
      "k": 39.5,
      "d": 45.5,
      "j": 27.5,
      "ma5": 1183.0,
      "ma20": 1119.15,
      "ma_gap": 5.7,
      "volume": 6169,
      "avg_vol5": 4270.8,
      "vol_ratio": 1.44,
      "buy_days": 0,
      "net_buy_ratio": 0.0,
      "foreign_buy_days": 4,
      "dif": 55.305,
      "score": 2,
      "criteria": {
        "s1": false,
        "s2": false,
        "s3": true,
        "s4": false,
        "s5": false,
        "s6": true
      },
      "updated": "2026-06-05"
    },
    {
      "code": "3533",
      "name": "嘉澤",
      "sector": "電子零組件",
      "price": 2365.0,
      "chg_pct": -1.46,
      "k": 35.7,
      "d": 49.2,
      "j": 8.7,
      "ma5": 2525.0,
      "ma20": 2536.0,
      "ma_gap": 0.4,
      "volume": 1740,
      "avg_vol5": 1408.8,
      "vol_ratio": 1.24,
      "buy_days": 0,
      "net_buy_ratio": 0.0,
      "foreign_buy_days": 9,
      "dif": 6.9497,
      "score": 2,
      "criteria": {
        "s1": false,
        "s2": false,
        "s3": true,
        "s4": false,
        "s5": false,
        "s6": true
      },
      "updated": "2026-06-05"
    },
    {
      "code": "3036",
      "name": "文曄",
      "sector": "電子通路",
      "price": 281.0,
      "chg_pct": -0.35,
      "k": 34.2,
      "d": 46.5,
      "j": 9.6,
      "ma5": 286.7,
      "ma20": 282.8,
      "ma_gap": 1.4,
      "volume": 15071,
      "avg_vol5": 13002.0,
      "vol_ratio": 1.16,
      "buy_days": 0,
      "net_buy_ratio": 0.0,
      "foreign_buy_days": 6,
      "dif": 13.4555,
      "score": 2,
      "criteria": {
        "s1": false,
        "s2": false,
        "s3": true,
        "s4": false,
        "s5": false,
        "s6": true
      },
      "updated": "2026-06-05"
    },
    {
      "code": "2633",
      "name": "台灣高鐵",
      "sector": "航運",
      "price": 25.5,
      "chg_pct": -0.2,
      "k": 57.1,
      "d": 42.0,
      "j": 87.4,
      "ma5": 25.44,
      "ma20": 25.64,
      "ma_gap": 0.8,
      "volume": 8674,
      "avg_vol5": 53378.7,
      "vol_ratio": 0.16,
      "buy_days": 4,
      "net_buy_ratio": 2.06,
      "foreign_buy_days": 1,
      "dif": -0.2634,
      "score": 2,
      "criteria": {
        "s1": true,
        "s2": false,
        "s3": false,
        "s4": false,
        "s5": true,
        "s6": false
      },
      "updated": "2026-06-05"
    },
    {
      "code": "2637",
      "name": "慧洋-KY",
      "sector": "航運",
      "price": 80.6,
      "chg_pct": 3.2,
      "k": 72.2,
      "d": 71.1,
      "j": 74.3,
      "ma5": 78.3,
      "ma20": 74.84,
      "ma_gap": 4.6,
      "volume": 15502,
      "avg_vol5": 5622.2,
      "vol_ratio": 2.76,
      "buy_days": 1,
      "net_buy_ratio": 0.97,
      "foreign_buy_days": 5,
      "dif": 1.564,
      "score": 2,
      "criteria": {
        "s1": false,
        "s2": false,
        "s3": false,
        "s4": true,
        "s5": false,
        "s6": true
      },
      "updated": "2026-06-05"
    },
    {
      "code": "2707",
      "name": "晶華",
      "sector": "觀光",
      "price": 181.0,
      "chg_pct": 0.56,
      "k": 81.6,
      "d": 66.5,
      "j": 111.7,
      "ma5": 177.1,
      "ma20": 173.97,
      "ma_gap": 1.8,
      "volume": 361,
      "avg_vol5": 320.0,
      "vol_ratio": 1.13,
      "buy_days": 0,
      "net_buy_ratio": 0.0,
      "foreign_buy_days": 5,
      "dif": 0.4016,
      "score": 2,
      "criteria": {
        "s1": false,
        "s2": false,
        "s3": false,
        "s4": false,
        "s5": true,
        "s6": true
      },
      "updated": "2026-06-05"
    },
    {
      "code": "9933",
      "name": "中鼎",
      "sector": "其他",
      "price": 43.45,
      "chg_pct": 3.08,
      "k": 78.6,
      "d": 70.0,
      "j": 95.9,
      "ma5": 41.46,
      "ma20": 39.13,
      "ma_gap": 6.0,
      "volume": 8685,
      "avg_vol5": 8670.1,
      "vol_ratio": 1.0,
      "buy_days": 4,
      "net_buy_ratio": 0.64,
      "foreign_buy_days": 3,
      "dif": 1.3838,
      "score": 2,
      "criteria": {
        "s1": true,
        "s2": false,
        "s3": false,
        "s4": false,
        "s5": false,
        "s6": true
      },
      "updated": "2026-06-05"
    },
    {
      "code": "9939",
      "name": "宏全",
      "sector": "其他",
      "price": 127.5,
      "chg_pct": 1.59,
      "k": 61.0,
      "d": 52.2,
      "j": 78.6,
      "ma5": 125.5,
      "ma20": 123.8,
      "ma_gap": 1.4,
      "volume": 1877,
      "avg_vol5": 1645.6,
      "vol_ratio": 1.14,
      "buy_days": 0,
      "net_buy_ratio": 0.0,
      "foreign_buy_days": 1,
      "dif": 2.2987,
      "score": 2,
      "criteria": {
        "s1": false,
        "s2": false,
        "s3": true,
        "s4": false,
        "s5": true,
        "s6": false
      },
      "updated": "2026-06-05"
    },
    {
      "code": "8932",
      "name": "智通",
      "sector": "資訊服務",
      "price": 102.0,
      "chg_pct": 2.0,
      "k": 42.3,
      "d": 43.5,
      "j": 39.9,
      "ma5": 101.54,
      "ma20": 99.71,
      "ma_gap": 1.8,
      "volume": 3338,
      "avg_vol5": 2829.6,
      "vol_ratio": 1.18,
      "buy_days": 0,
      "net_buy_ratio": 0.0,
      "foreign_buy_days": 2,
      "dif": 1.4215,
      "score": 2,
      "criteria": {
        "s1": false,
        "s2": false,
        "s3": true,
        "s4": false,
        "s5": true,
        "s6": false
      },
      "updated": "2026-06-05"
    },
    {
      "code": "6412",
      "name": "群電",
      "sector": "電子零組件",
      "price": 97.9,
      "chg_pct": -4.95,
      "k": 36.5,
      "d": 53.6,
      "j": 2.4,
      "ma5": 103.08,
      "ma20": 98.02,
      "ma_gap": 5.2,
      "volume": 5895,
      "avg_vol5": 5519.6,
      "vol_ratio": 1.07,
      "buy_days": 0,
      "net_buy_ratio": 0.0,
      "foreign_buy_days": 13,
      "dif": 4.5174,
      "score": 2,
      "criteria": {
        "s1": false,
        "s2": false,
        "s3": true,
        "s4": false,
        "s5": false,
        "s6": true
      },
      "updated": "2026-06-05"
    },
    {
      "code": "2308",
      "name": "台達電",
      "sector": "電子零組件",
      "price": 2300.0,
      "chg_pct": -5.15,
      "k": 48.4,
      "d": 62.9,
      "j": 19.4,
      "ma5": 2392.0,
      "ma20": 2238.25,
      "ma_gap": 6.9,
      "volume": 12284,
      "avg_vol5": 11930.0,
      "vol_ratio": 1.03,
      "buy_days": 0,
      "net_buy_ratio": 0.0,
      "foreign_buy_days": 0,
      "dif": 114.0035,
      "score": 1,
      "criteria": {
        "s1": false,
        "s2": false,
        "s3": true,
        "s4": false,
        "s5": false,
        "s6": false
      },
      "updated": "2026-06-05"
    },
    {
      "code": "2882",
      "name": "國泰金",
      "sector": "金融保險",
      "price": 100.0,
      "chg_pct": 5.93,
      "k": 94.4,
      "d": 91.1,
      "j": 101.1,
      "ma5": 92.72,
      "ma20": 83.09,
      "ma_gap": 11.6,
      "volume": 69269,
      "avg_vol5": 59695.3,
      "vol_ratio": 1.16,
      "buy_days": 0,
      "net_buy_ratio": 0.0,
      "foreign_buy_days": 15,
      "dif": 4.7746,
      "score": 1,
      "criteria": {
        "s1": false,
        "s2": false,
        "s3": false,
        "s4": false,
        "s5": false,
        "s6": true
      },
      "updated": "2026-06-05"
    },
    {
      "code": "2886",
      "name": "兆豐金",
      "sector": "金融保險",
      "price": 41.95,
      "chg_pct": -0.36,
      "k": 72.0,
      "d": 61.1,
      "j": 93.9,
      "ma5": 41.77,
      "ma20": 40.26,
      "ma_gap": 3.8,
      "volume": 31754,
      "avg_vol5": 67964.4,
      "vol_ratio": 0.47,
      "buy_days": 12,
      "net_buy_ratio": 0.53,
      "foreign_buy_days": 0,
      "dif": 0.5623,
      "score": 1,
      "criteria": {
        "s1": true,
        "s2": false,
        "s3": false,
        "s4": false,
        "s5": false,
        "s6": false
      },
      "updated": "2026-06-05"
    },
    {
      "code": "3711",
      "name": "日月光投控",
      "sector": "半導體",
      "price": 577.0,
      "chg_pct": -2.7,
      "k": 37.8,
      "d": 54.1,
      "j": 5.4,
      "ma5": 595.8,
      "ma20": 567.55,
      "ma_gap": 5.0,
      "volume": 21540,
      "avg_vol5": 29466.9,
      "vol_ratio": 0.73,
      "buy_days": 0,
      "net_buy_ratio": 0.0,
      "foreign_buy_days": 0,
      "dif": 32.1063,
      "score": 1,
      "criteria": {
        "s1": false,
        "s2": false,
        "s3": true,
        "s4": false,
        "s5": false,
        "s6": false
      },
      "updated": "2026-06-05"
    },
    {
      "code": "1301",
      "name": "台塑",
      "sector": "塑膠",
      "price": 48.9,
      "chg_pct": -3.74,
      "k": 67.7,
      "d": 66.6,
      "j": 70.1,
      "ma5": 50.52,
      "ma20": 47.2,
      "ma_gap": 7.0,
      "volume": 27308,
      "avg_vol5": 52917.3,
      "vol_ratio": 0.52,
      "buy_days": 0,
      "net_buy_ratio": 0.0,
      "foreign_buy_days": 0,
      "dif": 0.309,
      "score": 1,
      "criteria": {
        "s1": false,
        "s2": false,
        "s3": true,
        "s4": false,
        "s5": false,
        "s6": false
      },
      "updated": "2026-06-05"
    },
    {
      "code": "1303",
      "name": "南亞",
      "sector": "塑膠",
      "price": 104.5,
      "chg_pct": -5.86,
      "k": 72.4,
      "d": 76.7,
      "j": 63.9,
      "ma5": 109.7,
      "ma20": 93.45,
      "ma_gap": 17.4,
      "volume": 53708,
      "avg_vol5": 109395.3,
      "vol_ratio": 0.49,
      "buy_days": 8,
      "net_buy_ratio": 1.84,
      "foreign_buy_days": 1,
      "dif": 5.8525,
      "score": 1,
      "criteria": {
        "s1": true,
        "s2": false,
        "s3": false,
        "s4": false,
        "s5": false,
        "s6": false
      },
      "updated": "2026-06-05"
    },
    {
      "code": "2324",
      "name": "仁寶",
      "sector": "電腦週邊",
      "price": 41.4,
      "chg_pct": -2.24,
      "k": 74.8,
      "d": 80.7,
      "j": 63.1,
      "ma5": 43.1,
      "ma20": 34.19,
      "ma_gap": 26.1,
      "volume": 194674,
      "avg_vol5": 333011.2,
      "vol_ratio": 0.58,
      "buy_days": 3,
      "net_buy_ratio": 0.03,
      "foreign_buy_days": 0,
      "dif": 3.4234,
      "score": 1,
      "criteria": {
        "s1": true,
        "s2": false,
        "s3": false,
        "s4": false,
        "s5": false,
        "s6": false
      },
      "updated": "2026-06-05"
    },
    {
      "code": "3008",
      "name": "大立光",
      "sector": "光電",
      "price": 3680.0,
      "chg_pct": -3.79,
      "k": 55.5,
      "d": 66.0,
      "j": 34.6,
      "ma5": 3835.0,
      "ma20": 3437.75,
      "ma_gap": 11.6,
      "volume": 2296,
      "avg_vol5": 2105.2,
      "vol_ratio": 1.09,
      "buy_days": 0,
      "net_buy_ratio": 0.0,
      "foreign_buy_days": 1,
      "dif": 290.2684,
      "score": 1,
      "criteria": {
        "s1": false,
        "s2": false,
        "s3": true,
        "s4": false,
        "s5": false,
        "s6": false
      },
      "updated": "2026-06-05"
    },
    {
      "code": "2615",
      "name": "萬海",
      "sector": "航運",
      "price": 86.1,
      "chg_pct": 2.87,
      "k": 73.2,
      "d": 70.3,
      "j": 79.1,
      "ma5": 84.46,
      "ma20": 80.71,
      "ma_gap": 4.6,
      "volume": 26268,
      "avg_vol5": 11772.1,
      "vol_ratio": 2.23,
      "buy_days": 0,
      "net_buy_ratio": 0.0,
      "foreign_buy_days": 1,
      "dif": 2.0716,
      "score": 1,
      "criteria": {
        "s1": false,
        "s2": false,
        "s3": false,
        "s4": true,
        "s5": false,
        "s6": false
      },
      "updated": "2026-06-05"
    },
    {
      "code": "2337",
      "name": "旺宏",
      "sector": "半導體",
      "price": 150.0,
      "chg_pct": -4.15,
      "k": 46.5,
      "d": 56.0,
      "j": 27.5,
      "ma5": 162.3,
      "ma20": 157.7,
      "ma_gap": 2.9,
      "volume": 54587,
      "avg_vol5": 138913.5,
      "vol_ratio": 0.39,
      "buy_days": 0,
      "net_buy_ratio": 0.0,
      "foreign_buy_days": 0,
      "dif": 3.2458,
      "score": 1,
      "criteria": {
        "s1": false,
        "s2": false,
        "s3": true,
        "s4": false,
        "s5": false,
        "s6": false
      },
      "updated": "2026-06-05"
    },
    {
      "code": "2353",
      "name": "宏碁",
      "sector": "電腦週邊",
      "price": 38.4,
      "chg_pct": -1.79,
      "k": 72.9,
      "d": 79.2,
      "j": 60.3,
      "ma5": 40.43,
      "ma20": 32.34,
      "ma_gap": 25.0,
      "volume": 87069,
      "avg_vol5": 163967.7,
      "vol_ratio": 0.53,
      "buy_days": 3,
      "net_buy_ratio": 2.37,
      "foreign_buy_days": 1,
      "dif": 3.2097,
      "score": 1,
      "criteria": {
        "s1": true,
        "s2": false,
        "s3": false,
        "s4": false,
        "s5": false,
        "s6": false
      },
      "updated": "2026-06-05"
    },
    {
      "code": "2481",
      "name": "強茂",
      "sector": "半導體",
      "price": 165.0,
      "chg_pct": 3.45,
      "k": 76.2,
      "d": 76.5,
      "j": 75.6,
      "ma5": 157.3,
      "ma20": 138.35,
      "ma_gap": 13.7,
      "volume": 74311,
      "avg_vol5": 46528.0,
      "vol_ratio": 1.6,
      "buy_days": 0,
      "net_buy_ratio": 0.0,
      "foreign_buy_days": 1,
      "dif": 13.866,
      "score": 1,
      "criteria": {
        "s1": false,
        "s2": false,
        "s3": false,
        "s4": true,
        "s5": false,
        "s6": false
      },
      "updated": "2026-06-05"
    },
    {
      "code": "3034",
      "name": "聯詠",
      "sector": "半導體",
      "price": 492.0,
      "chg_pct": 0.61,
      "k": 57.4,
      "d": 64.5,
      "j": 43.4,
      "ma5": 497.5,
      "ma20": 486.1,
      "ma_gap": 2.3,
      "volume": 5463,
      "avg_vol5": 7165.6,
      "vol_ratio": 0.76,
      "buy_days": 0,
      "net_buy_ratio": 0.0,
      "foreign_buy_days": 1,
      "dif": 15.4562,
      "score": 1,
      "criteria": {
        "s1": false,
        "s2": false,
        "s3": true,
        "s4": false,
        "s5": false,
        "s6": false
      },
      "updated": "2026-06-05"
    },
    {
      "code": "3037",
      "name": "欣興",
      "sector": "電子零組件",
      "price": 933.0,
      "chg_pct": -3.91,
      "k": 33.1,
      "d": 49.9,
      "j": -0.3,
      "ma5": 985.8,
      "ma20": 941.3,
      "ma_gap": 4.7,
      "volume": 26077,
      "avg_vol5": 20574.0,
      "vol_ratio": 1.27,
      "buy_days": 0,
      "net_buy_ratio": 0.0,
      "foreign_buy_days": 0,
      "dif": 58.7913,
      "score": 1,
      "criteria": {
        "s1": false,
        "s2": false,
        "s3": true,
        "s4": false,
        "s5": false,
        "s6": false
      },
      "updated": "2026-06-05"
    },
    {
      "code": "3189",
      "name": "景碩",
      "sector": "電子零組件",
      "price": 712.0,
      "chg_pct": 2.89,
      "k": 63.8,
      "d": 74.2,
      "j": 43.0,
      "ma5": 732.0,
      "ma20": 616.23,
      "ma_gap": 18.8,
      "volume": 7602,
      "avg_vol5": 6227.0,
      "vol_ratio": 1.22,
      "buy_days": 0,
      "net_buy_ratio": 0.0,
      "foreign_buy_days": 1,
      "dif": 70.3254,
      "score": 1,
      "criteria": {
        "s1": false,
        "s2": false,
        "s3": true,
        "s4": false,
        "s5": false,
        "s6": false
      },
      "updated": "2026-06-05"
    },
    {
      "code": "2885",
      "name": "元大金",
      "sector": "金融保險",
      "price": 65.3,
      "chg_pct": 2.19,
      "k": 87.5,
      "d": 84.7,
      "j": 93.0,
      "ma5": 62.34,
      "ma20": 57.72,
      "ma_gap": 8.0,
      "volume": 40414,
      "avg_vol5": 46331.2,
      "vol_ratio": 0.87,
      "buy_days": 0,
      "net_buy_ratio": 0.0,
      "foreign_buy_days": 15,
      "dif": 2.93,
      "score": 1,
      "criteria": {
        "s1": false,
        "s2": false,
        "s3": false,
        "s4": false,
        "s5": false,
        "s6": true
      },
      "updated": "2026-06-05"
    },
    {
      "code": "1101",
      "name": "台泥",
      "sector": "水泥",
      "price": 24.4,
      "chg_pct": -0.2,
      "k": 58.2,
      "d": 57.2,
      "j": 60.1,
      "ma5": 24.58,
      "ma20": 24.37,
      "ma_gap": 0.9,
      "volume": 31313,
      "avg_vol5": 40170.8,
      "vol_ratio": 0.78,
      "buy_days": 4,
      "net_buy_ratio": 0.69,
      "foreign_buy_days": 0,
      "dif": -0.0194,
      "score": 1,
      "criteria": {
        "s1": true,
        "s2": false,
        "s3": false,
        "s4": false,
        "s5": false,
        "s6": false
      },
      "updated": "2026-06-05"
    },
    {
      "code": "1102",
      "name": "亞泥",
      "sector": "水泥",
      "price": 34.4,
      "chg_pct": 0.15,
      "k": 72.2,
      "d": 55.0,
      "j": 106.7,
      "ma5": 34.11,
      "ma20": 34.19,
      "ma_gap": 0.2,
      "volume": 14864,
      "avg_vol5": 55721.0,
      "vol_ratio": 0.27,
      "buy_days": 1,
      "net_buy_ratio": 0.71,
      "foreign_buy_days": 0,
      "dif": -0.2558,
      "score": 1,
      "criteria": {
        "s1": false,
        "s2": false,
        "s3": false,
        "s4": false,
        "s5": true,
        "s6": false
      },
      "updated": "2026-06-05"
    },
    {
      "code": "9904",
      "name": "寶成",
      "sector": "其他",
      "price": 26.45,
      "chg_pct": 0.19,
      "k": 74.9,
      "d": 58.8,
      "j": 107.1,
      "ma5": 26.25,
      "ma20": 25.89,
      "ma_gap": 1.4,
      "volume": 21051,
      "avg_vol5": 20825.1,
      "vol_ratio": 1.01,
      "buy_days": 0,
      "net_buy_ratio": 0.0,
      "foreign_buy_days": 0,
      "dif": -0.1319,
      "score": 1,
      "criteria": {
        "s1": false,
        "s2": false,
        "s3": false,
        "s4": false,
        "s5": true,
        "s6": false
      },
      "updated": "2026-06-05"
    },
    {
      "code": "9921",
      "name": "巨大",
      "sector": "其他",
      "price": 70.8,
      "chg_pct": 0.28,
      "k": 74.1,
      "d": 57.7,
      "j": 106.8,
      "ma5": 70.28,
      "ma20": 70.76,
      "ma_gap": 0.7,
      "volume": 1342,
      "avg_vol5": 2094.0,
      "vol_ratio": 0.64,
      "buy_days": 0,
      "net_buy_ratio": 0.0,
      "foreign_buy_days": 0,
      "dif": -0.1012,
      "score": 1,
      "criteria": {
        "s1": false,
        "s2": false,
        "s3": false,
        "s4": false,
        "s5": true,
        "s6": false
      },
      "updated": "2026-06-05"
    },
    {
      "code": "5904",
      "name": "寶雅",
      "sector": "貿易百貨",
      "price": 577.0,
      "chg_pct": -0.86,
      "k": 81.8,
      "d": 78.7,
      "j": 88.1,
      "ma5": 573.4,
      "ma20": 562.0,
      "ma_gap": 2.0,
      "volume": 409,
      "avg_vol5": 284.5,
      "vol_ratio": 1.44,
      "buy_days": 0,
      "net_buy_ratio": 0.0,
      "foreign_buy_days": 2,
      "dif": 8.2946,
      "score": 1,
      "criteria": {
        "s1": false,
        "s2": false,
        "s3": false,
        "s4": false,
        "s5": true,
        "s6": false
      },
      "updated": "2026-06-05"
    },
    {
      "code": "3481",
      "name": "群創",
      "sector": "光電",
      "price": 53.7,
      "chg_pct": -3.76,
      "k": 75.1,
      "d": 82.9,
      "j": 59.6,
      "ma5": 56.24,
      "ma20": 44.94,
      "ma_gap": 25.1,
      "volume": 177088,
      "avg_vol5": 736347.0,
      "vol_ratio": 0.24,
      "buy_days": 7,
      "net_buy_ratio": 0.01,
      "foreign_buy_days": 1,
      "dif": 6.9775,
      "score": 1,
      "criteria": {
        "s1": true,
        "s2": false,
        "s3": false,
        "s4": false,
        "s5": false,
        "s6": false
      },
      "updated": "2026-06-05"
    },
    {
      "code": "3017",
      "name": "奇鋐",
      "sector": "電腦週邊",
      "price": 2600.0,
      "chg_pct": -4.06,
      "k": 48.1,
      "d": 59.5,
      "j": 25.3,
      "ma5": 2730.0,
      "ma20": 2587.25,
      "ma_gap": 5.5,
      "volume": 4901,
      "avg_vol5": 6003.4,
      "vol_ratio": 0.82,
      "buy_days": 0,
      "net_buy_ratio": 0.0,
      "foreign_buy_days": 0,
      "dif": 65.5987,
      "score": 1,
      "criteria": {
        "s1": false,
        "s2": false,
        "s3": true,
        "s4": false,
        "s5": false,
        "s6": false
      },
      "updated": "2026-06-05"
    },
    {
      "code": "1717",
      "name": "長興",
      "sector": "化學",
      "price": 77.4,
      "chg_pct": 1.31,
      "k": 26.6,
      "d": 37.0,
      "j": 5.8,
      "ma5": 78.42,
      "ma20": 79.57,
      "ma_gap": 1.4,
      "volume": 22851,
      "avg_vol5": 22583.9,
      "vol_ratio": 1.01,
      "buy_days": 0,
      "net_buy_ratio": 0.0,
      "foreign_buy_days": 0,
      "dif": 0.5492,
      "score": 1,
      "criteria": {
        "s1": false,
        "s2": false,
        "s3": true,
        "s4": false,
        "s5": false,
        "s6": false
      },
      "updated": "2026-06-05"
    },
    {
      "code": "1504",
      "name": "東元",
      "sector": "電機機械",
      "price": 78.4,
      "chg_pct": -9.89,
      "k": 66.9,
      "d": 69.6,
      "j": 61.3,
      "ma5": 80.52,
      "ma20": 73.62,
      "ma_gap": 9.4,
      "volume": 102441,
      "avg_vol5": 110300.5,
      "vol_ratio": 0.93,
      "buy_days": 2,
      "net_buy_ratio": 0.02,
      "foreign_buy_days": 0,
      "dif": 3.5418,
      "score": 1,
      "criteria": {
        "s1": false,
        "s2": false,
        "s3": true,
        "s4": false,
        "s5": false,
        "s6": false
      },
      "updated": "2026-06-05"
    },
    {
      "code": "1513",
      "name": "中興電",
      "sector": "電機機械",
      "price": 170.5,
      "chg_pct": -8.82,
      "k": 56.1,
      "d": 66.7,
      "j": 35.0,
      "ma5": 175.7,
      "ma20": 161.82,
      "ma_gap": 8.6,
      "volume": 40328,
      "avg_vol5": 31345.2,
      "vol_ratio": 1.29,
      "buy_days": 0,
      "net_buy_ratio": 0.0,
      "foreign_buy_days": 1,
      "dif": 6.1632,
      "score": 1,
      "criteria": {
        "s1": false,
        "s2": false,
        "s3": true,
        "s4": false,
        "s5": false,
        "s6": false
      },
      "updated": "2026-06-05"
    },
    {
      "code": "1519",
      "name": "華城",
      "sector": "電機機械",
      "price": 851.0,
      "chg_pct": -6.48,
      "k": 46.1,
      "d": 55.6,
      "j": 27.1,
      "ma5": 883.2,
      "ma20": 855.05,
      "ma_gap": 3.3,
      "volume": 7359,
      "avg_vol5": 7464.5,
      "vol_ratio": 0.99,
      "buy_days": 0,
      "net_buy_ratio": 0.0,
      "foreign_buy_days": 0,
      "dif": 3.221,
      "score": 1,
      "criteria": {
        "s1": false,
        "s2": false,
        "s3": true,
        "s4": false,
        "s5": false,
        "s6": false
      },
      "updated": "2026-06-05"
    },
    {
      "code": "2027",
      "name": "大成鋼",
      "sector": "鋼鐵",
      "price": 43.8,
      "chg_pct": -0.68,
      "k": 72.9,
      "d": 68.6,
      "j": 81.3,
      "ma5": 43.72,
      "ma20": 41.59,
      "ma_gap": 5.1,
      "volume": 22945,
      "avg_vol5": 28167.4,
      "vol_ratio": 0.81,
      "buy_days": 0,
      "net_buy_ratio": 0.0,
      "foreign_buy_days": 8,
      "dif": 1.3941,
      "score": 1,
      "criteria": {
        "s1": false,
        "s2": false,
        "s3": false,
        "s4": false,
        "s5": false,
        "s6": true
      },
      "updated": "2026-06-05"
    },
    {
      "code": "2207",
      "name": "和泰車",
      "sector": "汽車",
      "price": 495.0,
      "chg_pct": 1.96,
      "k": 76.1,
      "d": 64.5,
      "j": 99.4,
      "ma5": 482.1,
      "ma20": 470.9,
      "ma_gap": 2.4,
      "volume": 1145,
      "avg_vol5": 1511.1,
      "vol_ratio": 0.76,
      "buy_days": 1,
      "net_buy_ratio": 0.09,
      "foreign_buy_days": 0,
      "dif": -0.4245,
      "score": 1,
      "criteria": {
        "s1": false,
        "s2": false,
        "s3": false,
        "s4": false,
        "s5": true,
        "s6": false
      },
      "updated": "2026-06-05"
    },
    {
      "code": "2313",
      "name": "華通",
      "sector": "電子零組件",
      "price": 259.0,
      "chg_pct": -2.45,
      "k": 26.6,
      "d": 38.5,
      "j": 2.8,
      "ma5": 268.7,
      "ma20": 263.9,
      "ma_gap": 1.8,
      "volume": 64235,
      "avg_vol5": 55595.4,
      "vol_ratio": 1.16,
      "buy_days": 1,
      "net_buy_ratio": 0.07,
      "foreign_buy_days": 0,
      "dif": 5.0616,
      "score": 1,
      "criteria": {
        "s1": false,
        "s2": false,
        "s3": true,
        "s4": false,
        "s5": false,
        "s6": false
      },
      "updated": "2026-06-05"
    },
    {
      "code": "2368",
      "name": "金像電",
      "sector": "電子零組件",
      "price": 1315.0,
      "chg_pct": -2.59,
      "k": 38.6,
      "d": 40.7,
      "j": 34.3,
      "ma5": 1330.0,
      "ma20": 1338.25,
      "ma_gap": 0.6,
      "volume": 5360,
      "avg_vol5": 6076.7,
      "vol_ratio": 0.88,
      "buy_days": 0,
      "net_buy_ratio": 0.0,
      "foreign_buy_days": 1,
      "dif": 19.1991,
      "score": 1,
      "criteria": {
        "s1": false,
        "s2": false,
        "s3": true,
        "s4": false,
        "s5": false,
        "s6": false
      },
      "updated": "2026-06-05"
    },
    {
      "code": "6213",
      "name": "聯茂",
      "sector": "電子零組件",
      "price": 254.5,
      "chg_pct": -2.3,
      "k": 35.5,
      "d": 47.2,
      "j": 12.2,
      "ma5": 270.6,
      "ma20": 265.57,
      "ma_gap": 1.9,
      "volume": 7795,
      "avg_vol5": 19572.2,
      "vol_ratio": 0.4,
      "buy_days": 0,
      "net_buy_ratio": 0.0,
      "foreign_buy_days": 1,
      "dif": 4.5875,
      "score": 1,
      "criteria": {
        "s1": false,
        "s2": false,
        "s3": true,
        "s4": false,
        "s5": false,
        "s6": false
      },
      "updated": "2026-06-05"
    },
    {
      "code": "2492",
      "name": "華新科",
      "sector": "被動元件",
      "price": 416.0,
      "chg_pct": 6.12,
      "k": 79.6,
      "d": 86.7,
      "j": 65.4,
      "ma5": 420.6,
      "ma20": 306.1,
      "ma_gap": 37.4,
      "volume": 4462,
      "avg_vol5": 4981.3,
      "vol_ratio": 0.9,
      "buy_days": 14,
      "net_buy_ratio": 0.87,
      "foreign_buy_days": 2,
      "dif": 68.4053,
      "score": 1,
      "criteria": {
        "s1": true,
        "s2": false,
        "s3": false,
        "s4": false,
        "s5": false,
        "s6": false
      },
      "updated": "2026-06-05"
    },
    {
      "code": "3661",
      "name": "世芯-KY",
      "sector": "半導體",
      "price": 4285.0,
      "chg_pct": -1.27,
      "k": 28.3,
      "d": 34.7,
      "j": 15.5,
      "ma5": 4530.0,
      "ma20": 4686.25,
      "ma_gap": 3.3,
      "volume": 1623,
      "avg_vol5": 1883.4,
      "vol_ratio": 0.86,
      "buy_days": 0,
      "net_buy_ratio": 0.0,
      "foreign_buy_days": 0,
      "dif": 74.733,
      "score": 1,
      "criteria": {
        "s1": false,
        "s2": false,
        "s3": true,
        "s4": false,
        "s5": false,
        "s6": false
      },
      "updated": "2026-06-05"
    },
    {
      "code": "3443",
      "name": "創意",
      "sector": "半導體",
      "price": 4410.0,
      "chg_pct": 0.23,
      "k": 24.9,
      "d": 31.7,
      "j": 11.2,
      "ma5": 4521.0,
      "ma20": 4906.25,
      "ma_gap": 7.9,
      "volume": 2409,
      "avg_vol5": 3273.0,
      "vol_ratio": 0.74,
      "buy_days": 0,
      "net_buy_ratio": 0.0,
      "foreign_buy_days": 2,
      "dif": 80.3285,
      "score": 1,
      "criteria": {
        "s1": false,
        "s2": false,
        "s3": true,
        "s4": false,
        "s5": false,
        "s6": false
      },
      "updated": "2026-06-05"
    },
    {
      "code": "5269",
      "name": "祥碩",
      "sector": "半導體",
      "price": 1525.0,
      "chg_pct": -2.87,
      "k": 56.0,
      "d": 61.7,
      "j": 44.8,
      "ma5": 1556.0,
      "ma20": 1478.5,
      "ma_gap": 5.2,
      "volume": 1332,
      "avg_vol5": 1984.0,
      "vol_ratio": 0.67,
      "buy_days": 0,
      "net_buy_ratio": 0.0,
      "foreign_buy_days": 0,
      "dif": 59.2359,
      "score": 1,
      "criteria": {
        "s1": false,
        "s2": false,
        "s3": true,
        "s4": false,
        "s5": false,
        "s6": false
      },
      "updated": "2026-06-05"
    },
    {
      "code": "8028",
      "name": "昇陽半導體",
      "sector": "半導體",
      "price": 337.5,
      "chg_pct": -1.03,
      "k": 67.0,
      "d": 73.1,
      "j": 54.9,
      "ma5": 342.9,
      "ma20": 296.32,
      "ma_gap": 15.7,
      "volume": 6896,
      "avg_vol5": 10921.2,
      "vol_ratio": 0.63,
      "buy_days": 2,
      "net_buy_ratio": 0.51,
      "foreign_buy_days": 0,
      "dif": 30.1418,
      "score": 1,
      "criteria": {
        "s1": false,
        "s2": false,
        "s3": true,
        "s4": false,
        "s5": false,
        "s6": false
      },
      "updated": "2026-06-05"
    },
    {
      "code": "6414",
      "name": "樺漢",
      "sector": "電腦週邊",
      "price": 384.0,
      "chg_pct": -1.41,
      "k": 84.1,
      "d": 82.9,
      "j": 86.5,
      "ma5": 383.4,
      "ma20": 356.52,
      "ma_gap": 7.5,
      "volume": 1803,
      "avg_vol5": 2004.7,
      "vol_ratio": 0.9,
      "buy_days": 0,
      "net_buy_ratio": 0.0,
      "foreign_buy_days": 15,
      "dif": 16.5284,
      "score": 1,
      "criteria": {
        "s1": false,
        "s2": false,
        "s3": false,
        "s4": false,
        "s5": false,
        "s6": true
      },
      "updated": "2026-06-05"
    },
    {
      "code": "3035",
      "name": "智原",
      "sector": "半導體",
      "price": 192.0,
      "chg_pct": 0.26,
      "k": 24.4,
      "d": 35.8,
      "j": 1.7,
      "ma5": 201.4,
      "ma20": 201.4,
      "ma_gap": 0.0,
      "volume": 8742,
      "avg_vol5": 12304.0,
      "vol_ratio": 0.71,
      "buy_days": 0,
      "net_buy_ratio": 0.0,
      "foreign_buy_days": 0,
      "dif": 5.8937,
      "score": 1,
      "criteria": {
        "s1": false,
        "s2": false,
        "s3": true,
        "s4": false,
        "s5": false,
        "s6": false
      },
      "updated": "2026-06-05"
    },
    {
      "code": "2458",
      "name": "義隆",
      "sector": "半導體",
      "price": 158.5,
      "chg_pct": -2.16,
      "k": 43.4,
      "d": 61.8,
      "j": 6.6,
      "ma5": 164.0,
      "ma20": 156.62,
      "ma_gap": 4.7,
      "volume": 2442,
      "avg_vol5": 3344.1,
      "vol_ratio": 0.73,
      "buy_days": 0,
      "net_buy_ratio": 0.0,
      "foreign_buy_days": 0,
      "dif": 6.0563,
      "score": 1,
      "criteria": {
        "s1": false,
        "s2": false,
        "s3": true,
        "s4": false,
        "s5": false,
        "s6": false
      },
      "updated": "2026-06-05"
    },
    {
      "code": "2377",
      "name": "微星",
      "sector": "電腦週邊",
      "price": 141.5,
      "chg_pct": 1.07,
      "k": 71.3,
      "d": 74.8,
      "j": 64.2,
      "ma5": 143.7,
      "ma20": 124.03,
      "ma_gap": 15.9,
      "volume": 30130,
      "avg_vol5": 58675.4,
      "vol_ratio": 0.51,
      "buy_days": 7,
      "net_buy_ratio": 0.07,
      "foreign_buy_days": 0,
      "dif": 11.1873,
      "score": 1,
      "criteria": {
        "s1": true,
        "s2": false,
        "s3": false,
        "s4": false,
        "s5": false,
        "s6": false
      },
      "updated": "2026-06-05"
    },
    {
      "code": "2474",
      "name": "可成",
      "sector": "其他電子",
      "price": 230.5,
      "chg_pct": -4.75,
      "k": 69.8,
      "d": 69.4,
      "j": 70.5,
      "ma5": 239.7,
      "ma20": 204.88,
      "ma_gap": 17.0,
      "volume": 18645,
      "avg_vol5": 30456.4,
      "vol_ratio": 0.61,
      "buy_days": 0,
      "net_buy_ratio": 0.0,
      "foreign_buy_days": 1,
      "dif": 9.4925,
      "score": 1,
      "criteria": {
        "s1": false,
        "s2": false,
        "s3": true,
        "s4": false,
        "s5": false,
        "s6": false
      },
      "updated": "2026-06-05"
    },
    {
      "code": "5434",
      "name": "崇越",
      "sector": "電子通路",
      "price": 458.5,
      "chg_pct": -1.29,
      "k": 47.3,
      "d": 57.7,
      "j": 26.6,
      "ma5": 463.0,
      "ma20": 440.05,
      "ma_gap": 5.2,
      "volume": 1357,
      "avg_vol5": 878.4,
      "vol_ratio": 1.54,
      "buy_days": 2,
      "net_buy_ratio": 0.45,
      "foreign_buy_days": 0,
      "dif": 16.7941,
      "score": 1,
      "criteria": {
        "s1": false,
        "s2": false,
        "s3": true,
        "s4": false,
        "s5": false,
        "s6": false
      },
      "updated": "2026-06-05"
    },
    {
      "code": "8464",
      "name": "億豐",
      "sector": "其他",
      "price": 328.5,
      "chg_pct": -0.9,
      "k": 81.3,
      "d": 70.2,
      "j": 103.5,
      "ma5": 326.0,
      "ma20": 321.0,
      "ma_gap": 1.6,
      "volume": 583,
      "avg_vol5": 1662.0,
      "vol_ratio": 0.35,
      "buy_days": 0,
      "net_buy_ratio": 0.0,
      "foreign_buy_days": 0,
      "dif": -5.3768,
      "score": 1,
      "criteria": {
        "s1": false,
        "s2": false,
        "s3": false,
        "s4": false,
        "s5": true,
        "s6": false
      },
      "updated": "2026-06-05"
    },
    {
      "code": "6285",
      "name": "啟碁",
      "sector": "通信網路",
      "price": 292.0,
      "chg_pct": -1.35,
      "k": 33.8,
      "d": 49.4,
      "j": 2.4,
      "ma5": 302.8,
      "ma20": 290.9,
      "ma_gap": 4.1,
      "volume": 12425,
      "avg_vol5": 15728.4,
      "vol_ratio": 0.79,
      "buy_days": 1,
      "net_buy_ratio": 0.41,
      "foreign_buy_days": 1,
      "dif": 16.9451,
      "score": 1,
      "criteria": {
        "s1": false,
        "s2": false,
        "s3": true,
        "s4": false,
        "s5": false,
        "s6": false
      },
      "updated": "2026-06-05"
    },
    {
      "code": "5388",
      "name": "中磊",
      "sector": "通信網路",
      "price": 89.6,
      "chg_pct": 0.79,
      "k": 67.7,
      "d": 73.5,
      "j": 56.2,
      "ma5": 90.8,
      "ma20": 84.84,
      "ma_gap": 7.0,
      "volume": 4060,
      "avg_vol5": 7640.4,
      "vol_ratio": 0.53,
      "buy_days": 0,
      "net_buy_ratio": 0.0,
      "foreign_buy_days": 1,
      "dif": 2.5623,
      "score": 1,
      "criteria": {
        "s1": false,
        "s2": false,
        "s3": true,
        "s4": false,
        "s5": false,
        "s6": false
      },
      "updated": "2026-06-05"
    },
    {
      "code": "3596",
      "name": "智易",
      "sector": "通信網路",
      "price": 190.5,
      "chg_pct": 1.33,
      "k": 59.5,
      "d": 64.8,
      "j": 49.0,
      "ma5": 190.8,
      "ma20": 186.07,
      "ma_gap": 2.5,
      "volume": 1858,
      "avg_vol5": 1782.6,
      "vol_ratio": 1.04,
      "buy_days": 0,
      "net_buy_ratio": 0.0,
      "foreign_buy_days": 1,
      "dif": 4.0565,
      "score": 1,
      "criteria": {
        "s1": false,
        "s2": false,
        "s3": true,
        "s4": false,
        "s5": false,
        "s6": false
      },
      "updated": "2026-06-05"
    },
    {
      "code": "2449",
      "name": "京元電子",
      "sector": "半導體",
      "price": 309.5,
      "chg_pct": -3.88,
      "k": 41.9,
      "d": 50.0,
      "j": 25.7,
      "ma5": 315.7,
      "ma20": 307.12,
      "ma_gap": 2.8,
      "volume": 28827,
      "avg_vol5": 51126.2,
      "vol_ratio": 0.56,
      "buy_days": 0,
      "net_buy_ratio": 0.0,
      "foreign_buy_days": 0,
      "dif": 5.2805,
      "score": 1,
      "criteria": {
        "s1": false,
        "s2": false,
        "s3": true,
        "s4": false,
        "s5": false,
        "s6": false
      },
      "updated": "2026-06-05"
    },
    {
      "code": "8150",
      "name": "南茂",
      "sector": "半導體",
      "price": 96.8,
      "chg_pct": -2.32,
      "k": 57.3,
      "d": 65.5,
      "j": 41.0,
      "ma5": 99.36,
      "ma20": 89.82,
      "ma_gap": 10.6,
      "volume": 34134,
      "avg_vol5": 62758.7,
      "vol_ratio": 0.54,
      "buy_days": 0,
      "net_buy_ratio": 0.0,
      "foreign_buy_days": 2,
      "dif": 6.5665,
      "score": 1,
      "criteria": {
        "s1": false,
        "s2": false,
        "s3": true,
        "s4": false,
        "s5": false,
        "s6": false
      },
      "updated": "2026-06-05"
    },
    {
      "code": "6443",
      "name": "元晶",
      "sector": "光電",
      "price": 39.9,
      "chg_pct": -3.86,
      "k": 29.9,
      "d": 38.9,
      "j": 11.9,
      "ma5": 41.79,
      "ma20": 41.01,
      "ma_gap": 1.9,
      "volume": 12428,
      "avg_vol5": 24737.5,
      "vol_ratio": 0.5,
      "buy_days": 0,
      "net_buy_ratio": 0.0,
      "foreign_buy_days": 0,
      "dif": 0.4714,
      "score": 1,
      "criteria": {
        "s1": false,
        "s2": false,
        "s3": true,
        "s4": false,
        "s5": false,
        "s6": false
      },
      "updated": "2026-06-05"
    },
    {
      "code": "3576",
      "name": "聯合再生",
      "sector": "光電",
      "price": 17.15,
      "chg_pct": -4.99,
      "k": 21.2,
      "d": 33.1,
      "j": -2.6,
      "ma5": 18.1,
      "ma20": 18.09,
      "ma_gap": 0.1,
      "volume": 17925,
      "avg_vol5": 20602.9,
      "vol_ratio": 0.87,
      "buy_days": 0,
      "net_buy_ratio": 0.0,
      "foreign_buy_days": 0,
      "dif": 0.1125,
      "score": 1,
      "criteria": {
        "s1": false,
        "s2": false,
        "s3": true,
        "s4": false,
        "s5": false,
        "s6": false
      },
      "updated": "2026-06-05"
    },
    {
      "code": "2406",
      "name": "國碩",
      "sector": "光電",
      "price": 34.65,
      "chg_pct": -10.0,
      "k": 55.9,
      "d": 66.0,
      "j": 35.7,
      "ma5": 36.57,
      "ma20": 33.78,
      "ma_gap": 8.3,
      "volume": 26787,
      "avg_vol5": 34309.9,
      "vol_ratio": 0.78,
      "buy_days": 0,
      "net_buy_ratio": 0.0,
      "foreign_buy_days": 0,
      "dif": 1.0932,
      "score": 1,
      "criteria": {
        "s1": false,
        "s2": false,
        "s3": true,
        "s4": false,
        "s5": false,
        "s6": false
      },
      "updated": "2026-06-05"
    },
    {
      "code": "2312",
      "name": "金寶",
      "sector": "電腦週邊",
      "price": 39.3,
      "chg_pct": -4.26,
      "k": 65.9,
      "d": 77.0,
      "j": 43.6,
      "ma5": 41.13,
      "ma20": 34.41,
      "ma_gap": 19.5,
      "volume": 67008,
      "avg_vol5": 127520.7,
      "vol_ratio": 0.53,
      "buy_days": 0,
      "net_buy_ratio": 0.0,
      "foreign_buy_days": 1,
      "dif": 3.7307,
      "score": 1,
      "criteria": {
        "s1": false,
        "s2": false,
        "s3": true,
        "s4": false,
        "s5": false,
        "s6": false
      },
      "updated": "2026-06-05"
    },
    {
      "code": "9907",
      "name": "統一實",
      "sector": "其他",
      "price": 16.65,
      "chg_pct": -0.89,
      "k": 80.2,
      "d": 64.5,
      "j": 111.6,
      "ma5": 16.55,
      "ma20": 16.24,
      "ma_gap": 1.9,
      "volume": 4765,
      "avg_vol5": 4402.6,
      "vol_ratio": 1.08,
      "buy_days": 0,
      "net_buy_ratio": 0.0,
      "foreign_buy_days": 0,
      "dif": -0.2098,
      "score": 1,
      "criteria": {
        "s1": false,
        "s2": false,
        "s3": false,
        "s4": false,
        "s5": true,
        "s6": false
      },
      "updated": "2026-06-05"
    },
    {
      "code": "4749",
      "name": "新應材",
      "sector": "半導體材料",
      "price": 1015.0,
      "chg_pct": -0.98,
      "k": 18.0,
      "d": 28.6,
      "j": -3.2,
      "ma5": 1045.0,
      "ma20": 1082.7,
      "ma_gap": 3.5,
      "volume": 1096,
      "avg_vol5": 1284.0,
      "vol_ratio": 0.85,
      "buy_days": 0,
      "net_buy_ratio": 0.0,
      "foreign_buy_days": 0,
      "dif": 10.8547,
      "score": 1,
      "criteria": {
        "s1": false,
        "s2": false,
        "s3": true,
        "s4": false,
        "s5": false,
        "s6": false
      },
      "updated": "2026-06-05"
    },
    {
      "code": "2881",
      "name": "富邦金",
      "sector": "金融保險",
      "price": 118.0,
      "chg_pct": 3.51,
      "k": 91.9,
      "d": 89.2,
      "j": 97.2,
      "ma5": 113.8,
      "ma20": 102.71,
      "ma_gap": 10.8,
      "volume": 61781,
      "avg_vol5": 90345.1,
      "vol_ratio": 0.68,
      "buy_days": 1,
      "net_buy_ratio": 3.17,
      "foreign_buy_days": 0,
      "dif": 6.1937,
      "score": 0,
      "criteria": {
        "s1": false,
        "s2": false,
        "s3": false,
        "s4": false,
        "s5": false,
        "s6": false
      },
      "updated": "2026-06-05"
    },
    {
      "code": "2891",
      "name": "中信金",
      "sector": "金融保險",
      "price": 66.6,
      "chg_pct": -2.06,
      "k": 82.5,
      "d": 85.0,
      "j": 77.5,
      "ma5": 66.26,
      "ma20": 59.08,
      "ma_gap": 12.2,
      "volume": 63845,
      "avg_vol5": 81784.6,
      "vol_ratio": 0.78,
      "buy_days": 0,
      "net_buy_ratio": 0.0,
      "foreign_buy_days": 0,
      "dif": 3.3076,
      "score": 0,
      "criteria": {
        "s1": false,
        "s2": false,
        "s3": false,
        "s4": false,
        "s5": false,
        "s6": false
      },
      "updated": "2026-06-05"
    },
    {
      "code": "2357",
      "name": "華碩",
      "sector": "電腦週邊",
      "price": 900.0,
      "chg_pct": 0.9,
      "k": 82.6,
      "d": 84.8,
      "j": 78.1,
      "ma5": 896.0,
      "ma20": 731.95,
      "ma_gap": 22.4,
      "volume": 7939,
      "avg_vol5": 10104.2,
      "vol_ratio": 0.79,
      "buy_days": 0,
      "net_buy_ratio": 0.0,
      "foreign_buy_days": 0,
      "dif": 73.9274,
      "score": 0,
      "criteria": {
        "s1": false,
        "s2": false,
        "s3": false,
        "s4": false,
        "s5": false,
        "s6": false
      },
      "updated": "2026-06-05"
    },
    {
      "code": "2880",
      "name": "華南金",
      "sector": "金融保險",
      "price": 34.8,
      "chg_pct": -7.69,
      "k": 70.0,
      "d": 59.3,
      "j": 91.3,
      "ma5": 35.16,
      "ma20": 32.51,
      "ma_gap": 8.2,
      "volume": 40543,
      "avg_vol5": 102600.1,
      "vol_ratio": 0.4,
      "buy_days": 0,
      "net_buy_ratio": 0.0,
      "foreign_buy_days": 0,
      "dif": 0.4303,
      "score": 0,
      "criteria": {
        "s1": false,
        "s2": false,
        "s3": false,
        "s4": false,
        "s5": false,
        "s6": false
      },
      "updated": "2026-06-05"
    },
    {
      "code": "2603",
      "name": "長榮",
      "sector": "航運",
      "price": 232.0,
      "chg_pct": -1.69,
      "k": 77.7,
      "d": 77.8,
      "j": 77.4,
      "ma5": 232.0,
      "ma20": 215.45,
      "ma_gap": 7.7,
      "volume": 23665,
      "avg_vol5": 34174.0,
      "vol_ratio": 0.69,
      "buy_days": 0,
      "net_buy_ratio": 0.0,
      "foreign_buy_days": 0,
      "dif": 6.9475,
      "score": 0,
      "criteria": {
        "s1": false,
        "s2": false,
        "s3": false,
        "s4": false,
        "s5": false,
        "s6": false
      },
      "updated": "2026-06-05"
    },
    {
      "code": "2605",
      "name": "新興",
      "sector": "航運",
      "price": 32.1,
      "chg_pct": -0.62,
      "k": 65.9,
      "d": 66.6,
      "j": 64.4,
      "ma5": 32.78,
      "ma20": 31.54,
      "ma_gap": 3.9,
      "volume": 8953,
      "avg_vol5": 10422.1,
      "vol_ratio": 0.86,
      "buy_days": 0,
      "net_buy_ratio": 0.0,
      "foreign_buy_days": 0,
      "dif": -0.468,
      "score": 0,
      "criteria": {
        "s1": false,
        "s2": false,
        "s3": false,
        "s4": false,
        "s5": false,
        "s6": false
      },
      "updated": "2026-06-05"
    },
    {
      "code": "2408",
      "name": "南亞科",
      "sector": "半導體",
      "price": 360.0,
      "chg_pct": -8.86,
      "k": 70.3,
      "d": 75.6,
      "j": 59.6,
      "ma5": 391.5,
      "ma20": 329.68,
      "ma_gap": 18.8,
      "volume": 121600,
      "avg_vol5": 141706.7,
      "vol_ratio": 0.86,
      "buy_days": 0,
      "net_buy_ratio": 0.0,
      "foreign_buy_days": 0,
      "dif": 33.4,
      "score": 0,
      "criteria": {
        "s1": false,
        "s2": false,
        "s3": false,
        "s4": false,
        "s5": false,
        "s6": false
      },
      "updated": "2026-06-05"
    },
    {
      "code": "2344",
      "name": "華邦電",
      "sector": "半導體",
      "price": 162.0,
      "chg_pct": -9.75,
      "k": 73.1,
      "d": 80.9,
      "j": 57.6,
      "ma5": 174.3,
      "ma20": 141.25,
      "ma_gap": 23.4,
      "volume": 228440,
      "avg_vol5": 274934.9,
      "vol_ratio": 0.83,
      "buy_days": 0,
      "net_buy_ratio": 0.0,
      "foreign_buy_days": 0,
      "dif": 17.7874,
      "score": 0,
      "criteria": {
        "s1": false,
        "s2": false,
        "s3": false,
        "s4": false,
        "s5": false,
        "s6": false
      },
      "updated": "2026-06-05"
    },
    {
      "code": "2376",
      "name": "技嘉",
      "sector": "電腦週邊",
      "price": 369.0,
      "chg_pct": -1.34,
      "k": 71.1,
      "d": 76.6,
      "j": 60.2,
      "ma5": 383.9,
      "ma20": 341.05,
      "ma_gap": 12.6,
      "volume": 17415,
      "avg_vol5": 28825.7,
      "vol_ratio": 0.6,
      "buy_days": 0,
      "net_buy_ratio": 0.0,
      "foreign_buy_days": 1,
      "dif": 24.6288,
      "score": 0,
      "criteria": {
        "s1": false,
        "s2": false,
        "s3": false,
        "s4": false,
        "s5": false,
        "s6": false
      },
      "updated": "2026-06-05"
    },
    {
      "code": "2352",
      "name": "佳世達",
      "sector": "電腦週邊",
      "price": 31.1,
      "chg_pct": -9.2,
      "k": 74.4,
      "d": 81.0,
      "j": 61.2,
      "ma5": 32.43,
      "ma20": 28.19,
      "ma_gap": 15.0,
      "volume": 26703,
      "avg_vol5": 27993.7,
      "vol_ratio": 0.95,
      "buy_days": 2,
      "net_buy_ratio": 0.31,
      "foreign_buy_days": 0,
      "dif": 1.9408,
      "score": 0,
      "criteria": {
        "s1": false,
        "s2": false,
        "s3": false,
        "s4": false,
        "s5": false,
        "s6": false
      },
      "updated": "2026-06-05"
    },
    {
      "code": "2618",
      "name": "長榮航",
      "sector": "航運",
      "price": 37.7,
      "chg_pct": -0.53,
      "k": 79.1,
      "d": 73.9,
      "j": 89.5,
      "ma5": 37.65,
      "ma20": 35.69,
      "ma_gap": 5.5,
      "volume": 39384,
      "avg_vol5": 86107.6,
      "vol_ratio": 0.46,
      "buy_days": 0,
      "net_buy_ratio": 0.0,
      "foreign_buy_days": 0,
      "dif": 0.7625,
      "score": 0,
      "criteria": {
        "s1": false,
        "s2": false,
        "s3": false,
        "s4": false,
        "s5": false,
        "s6": false
      },
      "updated": "2026-06-05"
    },
    {
      "code": "2610",
      "name": "華航",
      "sector": "航運",
      "price": 19.95,
      "chg_pct": 0.25,
      "k": 86.6,
      "d": 79.1,
      "j": 101.6,
      "ma5": 19.77,
      "ma20": 18.93,
      "ma_gap": 4.4,
      "volume": 49346,
      "avg_vol5": 107652.3,
      "vol_ratio": 0.46,
      "buy_days": 0,
      "net_buy_ratio": 0.0,
      "foreign_buy_days": 0,
      "dif": 0.3549,
      "score": 0,
      "criteria": {
        "s1": false,
        "s2": false,
        "s3": false,
        "s4": false,
        "s5": false,
        "s6": false
      },
      "updated": "2026-06-05"
    },
    {
      "code": "9945",
      "name": "潤泰新",
      "sector": "其他",
      "price": 25.15,
      "chg_pct": -0.2,
      "k": 79.4,
      "d": 65.1,
      "j": 108.2,
      "ma5": 24.5,
      "ma20": 23.66,
      "ma_gap": 3.6,
      "volume": 10439,
      "avg_vol5": 10505.5,
      "vol_ratio": 0.99,
      "buy_days": 0,
      "net_buy_ratio": 0.0,
      "foreign_buy_days": 1,
      "dif": 0.1015,
      "score": 0,
      "criteria": {
        "s1": false,
        "s2": false,
        "s3": false,
        "s4": false,
        "s5": false,
        "s6": false
      },
      "updated": "2026-06-05"
    },
    {
      "code": "2912",
      "name": "統一超",
      "sector": "貿易百貨",
      "price": 232.0,
      "chg_pct": -5.69,
      "k": 73.2,
      "d": 63.3,
      "j": 92.9,
      "ma5": 235.5,
      "ma20": 223.8,
      "ma_gap": 5.2,
      "volume": 5516,
      "avg_vol5": 15004.1,
      "vol_ratio": 0.37,
      "buy_days": 0,
      "net_buy_ratio": 0.0,
      "foreign_buy_days": 0,
      "dif": 1.9902,
      "score": 0,
      "criteria": {
        "s1": false,
        "s2": false,
        "s3": false,
        "s4": false,
        "s5": false,
        "s6": false
      },
      "updated": "2026-06-05"
    },
    {
      "code": "4904",
      "name": "遠傳",
      "sector": "通信網路",
      "price": 101.5,
      "chg_pct": -0.49,
      "k": 77.5,
      "d": 61.8,
      "j": 108.9,
      "ma5": 100.12,
      "ma20": 96.9,
      "ma_gap": 3.3,
      "volume": 8625,
      "avg_vol5": 12956.3,
      "vol_ratio": 0.67,
      "buy_days": 0,
      "net_buy_ratio": 0.0,
      "foreign_buy_days": 0,
      "dif": 1.2303,
      "score": 0,
      "criteria": {
        "s1": false,
        "s2": false,
        "s3": false,
        "s4": false,
        "s5": false,
        "s6": false
      },
      "updated": "2026-06-05"
    },
    {
      "code": "2409",
      "name": "友達",
      "sector": "光電",
      "price": 27.1,
      "chg_pct": -7.35,
      "k": 82.5,
      "d": 79.0,
      "j": 89.7,
      "ma5": 27.01,
      "ma20": 22.27,
      "ma_gap": 21.3,
      "volume": 607775,
      "avg_vol5": 670480.5,
      "vol_ratio": 0.91,
      "buy_days": 2,
      "net_buy_ratio": 0.0,
      "foreign_buy_days": 0,
      "dif": 2.3797,
      "score": 0,
      "criteria": {
        "s1": false,
        "s2": false,
        "s3": false,
        "s4": false,
        "s5": false,
        "s6": false
      },
      "updated": "2026-06-05"
    },
    {
      "code": "6669",
      "name": "緯穎",
      "sector": "電腦週邊",
      "price": 5660.0,
      "chg_pct": 1.62,
      "k": 70.0,
      "d": 60.6,
      "j": 88.9,
      "ma5": 5564.0,
      "ma20": 5360.0,
      "ma_gap": 3.8,
      "volume": 2033,
      "avg_vol5": 2181.9,
      "vol_ratio": 0.93,
      "buy_days": 2,
      "net_buy_ratio": 2.85,
      "foreign_buy_days": 0,
      "dif": 242.9763,
      "score": 0,
      "criteria": {
        "s1": false,
        "s2": false,
        "s3": false,
        "s4": false,
        "s5": false,
        "s6": false
      },
      "updated": "2026-06-05"
    },
    {
      "code": "1304",
      "name": "台聚",
      "sector": "塑膠",
      "price": 13.4,
      "chg_pct": -2.19,
      "k": 70.0,
      "d": 65.4,
      "j": 79.2,
      "ma5": 13.54,
      "ma20": 12.68,
      "ma_gap": 6.8,
      "volume": 5829,
      "avg_vol5": 11502.2,
      "vol_ratio": 0.51,
      "buy_days": 0,
      "net_buy_ratio": 0.0,
      "foreign_buy_days": 1,
      "dif": -0.0808,
      "score": 0,
      "criteria": {
        "s1": false,
        "s2": false,
        "s3": false,
        "s4": false,
        "s5": false,
        "s6": false
      },
      "updated": "2026-06-05"
    },
    {
      "code": "1308",
      "name": "亞聚",
      "sector": "塑膠",
      "price": 13.85,
      "chg_pct": -1.42,
      "k": 66.2,
      "d": 63.6,
      "j": 71.4,
      "ma5": 13.96,
      "ma20": 13.41,
      "ma_gap": 4.1,
      "volume": 2369,
      "avg_vol5": 4429.3,
      "vol_ratio": 0.53,
      "buy_days": 0,
      "net_buy_ratio": 0.0,
      "foreign_buy_days": 0,
      "dif": -0.1902,
      "score": 0,
      "criteria": {
        "s1": false,
        "s2": false,
        "s3": false,
        "s4": false,
        "s5": false,
        "s6": false
      },
      "updated": "2026-06-05"
    },
    {
      "code": "1326",
      "name": "台化",
      "sector": "塑膠",
      "price": 52.8,
      "chg_pct": -4.35,
      "k": 72.1,
      "d": 72.5,
      "j": 71.2,
      "ma5": 54.54,
      "ma20": 47.95,
      "ma_gap": 13.7,
      "volume": 32740,
      "avg_vol5": 72780.0,
      "vol_ratio": 0.45,
      "buy_days": 0,
      "net_buy_ratio": 0.0,
      "foreign_buy_days": 0,
      "dif": 1.6175,
      "score": 0,
      "criteria": {
        "s1": false,
        "s2": false,
        "s3": false,
        "s4": false,
        "s5": false,
        "s6": false
      },
      "updated": "2026-06-05"
    },
    {
      "code": "1503",
      "name": "士電",
      "sector": "電機機械",
      "price": 241.5,
      "chg_pct": -9.89,
      "k": 76.4,
      "d": 75.2,
      "j": 78.9,
      "ma5": 239.2,
      "ma20": 209.6,
      "ma_gap": 14.1,
      "volume": 27220,
      "avg_vol5": 7785.0,
      "vol_ratio": 3.5,
      "buy_days": 0,
      "net_buy_ratio": 0.0,
      "foreign_buy_days": 1,
      "dif": 12.755,
      "score": 0,
      "criteria": {
        "s1": false,
        "s2": false,
        "s3": false,
        "s4": false,
        "s5": false,
        "s6": false
      },
      "updated": "2026-06-05"
    },
    {
      "code": "2006",
      "name": "東和鋼鐵",
      "sector": "鋼鐵",
      "price": 67.0,
      "chg_pct": -0.59,
      "k": 70.7,
      "d": 66.8,
      "j": 78.4,
      "ma5": 67.04,
      "ma20": 66.24,
      "ma_gap": 1.2,
      "volume": 1612,
      "avg_vol5": 2721.3,
      "vol_ratio": 0.59,
      "buy_days": 0,
      "net_buy_ratio": 0.0,
      "foreign_buy_days": 0,
      "dif": -0.2643,
      "score": 0,
      "criteria": {
        "s1": false,
        "s2": false,
        "s3": false,
        "s4": false,
        "s5": false,
        "s6": false
      },
      "updated": "2026-06-05"
    },
    {
      "code": "2201",
      "name": "裕隆",
      "sector": "汽車",
      "price": 28.7,
      "chg_pct": -0.35,
      "k": 73.5,
      "d": 71.9,
      "j": 76.7,
      "ma5": 28.53,
      "ma20": 27.44,
      "ma_gap": 4.0,
      "volume": 3258,
      "avg_vol5": 5755.1,
      "vol_ratio": 0.57,
      "buy_days": 0,
      "net_buy_ratio": 0.0,
      "foreign_buy_days": 1,
      "dif": 0.3249,
      "score": 0,
      "criteria": {
        "s1": false,
        "s2": false,
        "s3": false,
        "s4": false,
        "s5": false,
        "s6": false
      },
      "updated": "2026-06-05"
    },
    {
      "code": "2204",
      "name": "中華",
      "sector": "汽車",
      "price": 56.6,
      "chg_pct": 0.89,
      "k": 89.1,
      "d": 81.7,
      "j": 104.1,
      "ma5": 55.04,
      "ma20": 53.41,
      "ma_gap": 3.1,
      "volume": 2067,
      "avg_vol5": 2425.3,
      "vol_ratio": 0.85,
      "buy_days": 0,
      "net_buy_ratio": 0.0,
      "foreign_buy_days": 0,
      "dif": 0.3744,
      "score": 0,
      "criteria": {
        "s1": false,
        "s2": false,
        "s3": false,
        "s4": false,
        "s5": false,
        "s6": false
      },
      "updated": "2026-06-05"
    },
    {
      "code": "2367",
      "name": "燿華",
      "sector": "電子零組件",
      "price": 63.1,
      "chg_pct": 1.77,
      "k": 21.8,
      "d": 32.5,
      "j": 0.4,
      "ma5": 64.7,
      "ma20": 64.96,
      "ma_gap": 0.4,
      "volume": 35580,
      "avg_vol5": 35870.3,
      "vol_ratio": 0.99,
      "buy_days": 0,
      "net_buy_ratio": 0.0,
      "foreign_buy_days": 0,
      "dif": -0.0593,
      "score": 0,
      "criteria": {
        "s1": false,
        "s2": false,
        "s3": false,
        "s4": false,
        "s5": false,
        "s6": false
      },
      "updated": "2026-06-05"
    },
    {
      "code": "2327",
      "name": "國巨",
      "sector": "被動元件",
      "price": 769.0,
      "chg_pct": 3.5,
      "k": 73.8,
      "d": 83.1,
      "j": 55.2,
      "ma5": 793.6,
      "ma20": 618.42,
      "ma_gap": 28.3,
      "volume": 29037,
      "avg_vol5": 25088.3,
      "vol_ratio": 1.16,
      "buy_days": 2,
      "net_buy_ratio": 1.16,
      "foreign_buy_days": 0,
      "dif": 112.9453,
      "score": 0,
      "criteria": {
        "s1": false,
        "s2": false,
        "s3": false,
        "s4": false,
        "s5": false,
        "s6": false
      },
      "updated": "2026-06-05"
    },
    {
      "code": "2356",
      "name": "英業達",
      "sector": "電腦週邊",
      "price": 76.8,
      "chg_pct": -1.29,
      "k": 72.5,
      "d": 79.8,
      "j": 57.9,
      "ma5": 79.56,
      "ma20": 62.38,
      "ma_gap": 27.5,
      "volume": 113333,
      "avg_vol5": 218839.0,
      "vol_ratio": 0.52,
      "buy_days": 0,
      "net_buy_ratio": 0.0,
      "foreign_buy_days": 1,
      "dif": 8.2217,
      "score": 0,
      "criteria": {
        "s1": false,
        "s2": false,
        "s3": false,
        "s4": false,
        "s5": false,
        "s6": false
      },
      "updated": "2026-06-05"
    },
    {
      "code": "3005",
      "name": "神基",
      "sector": "電腦週邊",
      "price": 109.0,
      "chg_pct": -0.91,
      "k": 73.9,
      "d": 74.4,
      "j": 72.9,
      "ma5": 109.0,
      "ma20": 103.22,
      "ma_gap": 5.6,
      "volume": 6464,
      "avg_vol5": 7540.2,
      "vol_ratio": 0.86,
      "buy_days": 0,
      "net_buy_ratio": 0.0,
      "foreign_buy_days": 2,
      "dif": 2.0273,
      "score": 0,
      "criteria": {
        "s1": false,
        "s2": false,
        "s3": false,
        "s4": false,
        "s5": false,
        "s6": false
      },
      "updated": "2026-06-05"
    },
    {
      "code": "2606",
      "name": "裕民",
      "sector": "航運",
      "price": 70.8,
      "chg_pct": 1.29,
      "k": 70.8,
      "d": 76.8,
      "j": 58.7,
      "ma5": 71.14,
      "ma20": 67.43,
      "ma_gap": 5.5,
      "volume": 8021,
      "avg_vol5": 5639.6,
      "vol_ratio": 1.42,
      "buy_days": 2,
      "net_buy_ratio": 4.45,
      "foreign_buy_days": 1,
      "dif": 2.2247,
      "score": 0,
      "criteria": {
        "s1": false,
        "s2": false,
        "s3": false,
        "s4": false,
        "s5": false,
        "s6": false
      },
      "updated": "2026-06-05"
    },
    {
      "code": "2634",
      "name": "漢翔",
      "sector": "航運",
      "price": 46.55,
      "chg_pct": 0.0,
      "k": 44.0,
      "d": 44.9,
      "j": 42.3,
      "ma5": 46.99,
      "ma20": 46.46,
      "ma_gap": 1.1,
      "volume": 4754,
      "avg_vol5": 5718.0,
      "vol_ratio": 0.83,
      "buy_days": 0,
      "net_buy_ratio": 0.0,
      "foreign_buy_days": 0,
      "dif": -0.3631,
      "score": 0,
      "criteria": {
        "s1": false,
        "s2": false,
        "s3": false,
        "s4": false,
        "s5": false,
        "s6": false
      },
      "updated": "2026-06-05"
    },
    {
      "code": "8112",
      "name": "至上",
      "sector": "電子通路",
      "price": 92.6,
      "chg_pct": -3.14,
      "k": 73.7,
      "d": 75.7,
      "j": 69.8,
      "ma5": 93.7,
      "ma20": 86.8,
      "ma_gap": 7.9,
      "volume": 43713,
      "avg_vol5": 52730.5,
      "vol_ratio": 0.83,
      "buy_days": 0,
      "net_buy_ratio": 0.0,
      "foreign_buy_days": 0,
      "dif": 2.5563,
      "score": 0,
      "criteria": {
        "s1": false,
        "s2": false,
        "s3": false,
        "s4": false,
        "s5": false,
        "s6": false
      },
      "updated": "2026-06-05"
    },
    {
      "code": "1476",
      "name": "儒鴻",
      "sector": "紡織",
      "price": 355.5,
      "chg_pct": -2.2,
      "k": 83.0,
      "d": 79.7,
      "j": 89.6,
      "ma5": 356.8,
      "ma20": 342.57,
      "ma_gap": 4.2,
      "volume": 1395,
      "avg_vol5": 2160.2,
      "vol_ratio": 0.65,
      "buy_days": 0,
      "net_buy_ratio": 0.0,
      "foreign_buy_days": 0,
      "dif": 4.0765,
      "score": 0,
      "criteria": {
        "s1": false,
        "s2": false,
        "s3": false,
        "s4": false,
        "s5": false,
        "s6": false
      },
      "updated": "2026-06-05"
    },
    {
      "code": "1477",
      "name": "聚陽",
      "sector": "紡織",
      "price": 228.0,
      "chg_pct": -0.87,
      "k": 79.8,
      "d": 73.4,
      "j": 92.5,
      "ma5": 227.4,
      "ma20": 220.18,
      "ma_gap": 3.3,
      "volume": 2479,
      "avg_vol5": 2751.2,
      "vol_ratio": 0.9,
      "buy_days": 0,
      "net_buy_ratio": 0.0,
      "foreign_buy_days": 0,
      "dif": 0.5999,
      "score": 0,
      "criteria": {
        "s1": false,
        "s2": false,
        "s3": false,
        "s4": false,
        "s5": false,
        "s6": false
      },
      "updated": "2026-06-05"
    }
  ]
}