{
  "updated": "2026-05-07",
  "total": 143,
  "scores": [
    {
      "code": "2357",
      "name": "華碩",
      "sector": "電腦週邊",
      "price": 639.0,
      "chg_pct": 1.59,
      "k": 56.1,
      "d": 41.4,
      "j": 85.5,
      "ma5": 606.0,
      "ma20": 593.3,
      "ma_gap": 2.1,
      "volume": 9859,
      "avg_vol5": 4170.8,
      "vol_ratio": 2.36,
      "buy_days": 2,
      "net_buy_ratio": 11.26,
      "foreign_buy_days": 0,
      "dif": 12.6634,
      "score": 3,
      "criteria": {
        "s1": false,
        "s2": true,
        "s3": false,
        "s4": true,
        "s5": true,
        "s6": false
      },
      "updated": "2026-05-07"
    },
    {
      "code": "2408",
      "name": "南亞科",
      "sector": "半導體",
      "price": 287.0,
      "chg_pct": 1.77,
      "k": 86.7,
      "d": 76.6,
      "j": 107.1,
      "ma5": 255.6,
      "ma20": 226.88,
      "ma_gap": 12.7,
      "volume": 197356,
      "avg_vol5": 145169.9,
      "vol_ratio": 1.36,
      "buy_days": 4,
      "net_buy_ratio": 5.34,
      "foreign_buy_days": 4,
      "dif": 9.111,
      "score": 3,
      "criteria": {
        "s1": true,
        "s2": true,
        "s3": false,
        "s4": false,
        "s5": false,
        "s6": true
      },
      "updated": "2026-05-07"
    },
    {
      "code": "2379",
      "name": "瑞昱",
      "sector": "半導體",
      "price": 539.0,
      "chg_pct": -0.92,
      "k": 33.7,
      "d": 37.7,
      "j": 25.5,
      "ma5": 536.2,
      "ma20": 537.5,
      "ma_gap": 0.2,
      "volume": 3702,
      "avg_vol5": 3551.6,
      "vol_ratio": 1.04,
      "buy_days": 3,
      "net_buy_ratio": 0.36,
      "foreign_buy_days": 0,
      "dif": 10.796,
      "score": 3,
      "criteria": {
        "s1": true,
        "s2": false,
        "s3": true,
        "s4": false,
        "s5": true,
        "s6": false
      },
      "updated": "2026-05-07"
    },
    {
      "code": "2344",
      "name": "華邦電",
      "sector": "半導體",
      "price": 114.0,
      "chg_pct": 5.07,
      "k": 85.1,
      "d": 74.5,
      "j": 106.1,
      "ma5": 101.3,
      "ma20": 93.6,
      "ma_gap": 8.2,
      "volume": 338650,
      "avg_vol5": 176661.0,
      "vol_ratio": 1.92,
      "buy_days": 4,
      "net_buy_ratio": 3.99,
      "foreign_buy_days": 4,
      "dif": 1.0632,
      "score": 3,
      "criteria": {
        "s1": true,
        "s2": false,
        "s3": false,
        "s4": true,
        "s5": false,
        "s6": true
      },
      "updated": "2026-05-07"
    },
    {
      "code": "2395",
      "name": "研華",
      "sector": "電腦週邊",
      "price": 444.0,
      "chg_pct": 8.42,
      "k": 85.1,
      "d": 75.5,
      "j": 104.3,
      "ma5": 400.9,
      "ma20": 367.48,
      "ma_gap": 9.1,
      "volume": 9166,
      "avg_vol5": 5219.3,
      "vol_ratio": 1.76,
      "buy_days": 3,
      "net_buy_ratio": 0.72,
      "foreign_buy_days": 14,
      "dif": 18.8375,
      "score": 3,
      "criteria": {
        "s1": true,
        "s2": false,
        "s3": false,
        "s4": true,
        "s5": false,
        "s6": true
      },
      "updated": "2026-05-07"
    },
    {
      "code": "2618",
      "name": "長榮航",
      "sector": "航運",
      "price": 35.4,
      "chg_pct": 4.27,
      "k": 53.8,
      "d": 37.2,
      "j": 87.0,
      "ma5": 34.13,
      "ma20": 34.48,
      "ma_gap": 1.0,
      "volume": 44125,
      "avg_vol5": 24179.8,
      "vol_ratio": 1.82,
      "buy_days": 3,
      "net_buy_ratio": 3.12,
      "foreign_buy_days": 1,
      "dif": -0.2545,
      "score": 3,
      "criteria": {
        "s1": true,
        "s2": false,
        "s3": false,
        "s4": true,
        "s5": true,
        "s6": false
      },
      "updated": "2026-05-07"
    },
    {
      "code": "2204",
      "name": "中華",
      "sector": "汽車",
      "price": 55.0,
      "chg_pct": 1.85,
      "k": 69.1,
      "d": 57.0,
      "j": 93.4,
      "ma5": 54.26,
      "ma20": 54.2,
      "ma_gap": 0.1,
      "volume": 1415,
      "avg_vol5": 1218.2,
      "vol_ratio": 1.16,
      "buy_days": 8,
      "net_buy_ratio": 17.96,
      "foreign_buy_days": 2,
      "dif": -0.2915,
      "score": 3,
      "criteria": {
        "s1": true,
        "s2": true,
        "s3": false,
        "s4": false,
        "s5": true,
        "s6": false
      },
      "updated": "2026-05-07"
    },
    {
      "code": "2458",
      "name": "義隆",
      "sector": "半導體",
      "price": 144.0,
      "chg_pct": 1.41,
      "k": 57.8,
      "d": 47.2,
      "j": 79.1,
      "ma5": 140.1,
      "ma20": 136.95,
      "ma_gap": 2.3,
      "volume": 5482,
      "avg_vol5": 2917.6,
      "vol_ratio": 1.88,
      "buy_days": 0,
      "net_buy_ratio": 0.0,
      "foreign_buy_days": 5,
      "dif": 2.5559,
      "score": 3,
      "criteria": {
        "s1": false,
        "s2": false,
        "s3": false,
        "s4": true,
        "s5": true,
        "s6": true
      },
      "updated": "2026-05-07"
    },
    {
      "code": "4961",
      "name": "天鈺",
      "sector": "半導體",
      "price": 161.0,
      "chg_pct": 2.88,
      "k": 36.7,
      "d": 30.5,
      "j": 49.0,
      "ma5": 156.9,
      "ma20": 156.45,
      "ma_gap": 0.3,
      "volume": 1423,
      "avg_vol5": 880.7,
      "vol_ratio": 1.62,
      "buy_days": 0,
      "net_buy_ratio": 0.0,
      "foreign_buy_days": 1,
      "dif": 2.3525,
      "score": 3,
      "criteria": {
        "s1": false,
        "s2": false,
        "s3": true,
        "s4": true,
        "s5": true,
        "s6": false
      },
      "updated": "2026-05-07"
    },
    {
      "code": "4938",
      "name": "和碩",
      "sector": "電腦週邊",
      "price": 84.3,
      "chg_pct": 0.84,
      "k": 47.9,
      "d": 41.4,
      "j": 61.0,
      "ma5": 82.6,
      "ma20": 81.98,
      "ma_gap": 0.8,
      "volume": 10411,
      "avg_vol5": 9529.3,
      "vol_ratio": 1.09,
      "buy_days": 0,
      "net_buy_ratio": 0.0,
      "foreign_buy_days": 3,
      "dif": 1.4859,
      "score": 3,
      "criteria": {
        "s1": false,
        "s2": false,
        "s3": true,
        "s4": false,
        "s5": true,
        "s6": true
      },
      "updated": "2026-05-07"
    },
    {
      "code": "2606",
      "name": "裕民",
      "sector": "航運",
      "price": 65.1,
      "chg_pct": 1.4,
      "k": 66.2,
      "d": 48.6,
      "j": 101.4,
      "ma5": 63.02,
      "ma20": 62.12,
      "ma_gap": 1.4,
      "volume": 7348,
      "avg_vol5": 3498.4,
      "vol_ratio": 2.1,
      "buy_days": 0,
      "net_buy_ratio": 0.0,
      "foreign_buy_days": 5,
      "dif": 0.5676,
      "score": 3,
      "criteria": {
        "s1": false,
        "s2": false,
        "s3": false,
        "s4": true,
        "s5": true,
        "s6": true
      },
      "updated": "2026-05-07"
    },
    {
      "code": "2637",
      "name": "慧洋-KY",
      "sector": "航運",
      "price": 76.8,
      "chg_pct": 1.05,
      "k": 68.1,
      "d": 54.5,
      "j": 95.3,
      "ma5": 74.32,
      "ma20": 72.96,
      "ma_gap": 1.9,
      "volume": 4478,
      "avg_vol5": 2328.5,
      "vol_ratio": 1.92,
      "buy_days": 0,
      "net_buy_ratio": 0.0,
      "foreign_buy_days": 8,
      "dif": 1.1119,
      "score": 3,
      "criteria": {
        "s1": false,
        "s2": false,
        "s3": false,
        "s4": true,
        "s5": true,
        "s6": true
      },
      "updated": "2026-05-07"
    },
    {
      "code": "6285",
      "name": "啟碁",
      "sector": "通信網路",
      "price": 256.0,
      "chg_pct": 9.87,
      "k": 69.5,
      "d": 50.0,
      "j": 108.5,
      "ma5": 232.9,
      "ma20": 233.65,
      "ma_gap": 0.3,
      "volume": 46404,
      "avg_vol5": 21672.2,
      "vol_ratio": 2.14,
      "buy_days": 1,
      "net_buy_ratio": 2.2,
      "foreign_buy_days": 3,
      "dif": 9.5662,
      "score": 3,
      "criteria": {
        "s1": false,
        "s2": false,
        "s3": false,
        "s4": true,
        "s5": true,
        "s6": true
      },
      "updated": "2026-05-07"
    },
    {
      "code": "8150",
      "name": "南茂",
      "sector": "半導體",
      "price": 98.1,
      "chg_pct": 9.98,
      "k": 81.9,
      "d": 66.8,
      "j": 112.2,
      "ma5": 83.54,
      "ma20": 71.97,
      "ma_gap": 16.1,
      "volume": 80750,
      "avg_vol5": 36250.9,
      "vol_ratio": 2.23,
      "buy_days": 3,
      "net_buy_ratio": 13.46,
      "foreign_buy_days": 0,
      "dif": 6.4251,
      "score": 3,
      "criteria": {
        "s1": true,
        "s2": true,
        "s3": false,
        "s4": true,
        "s5": false,
        "s6": false
      },
      "updated": "2026-05-07"
    },
    {
      "code": "6443",
      "name": "元晶",
      "sector": "光電",
      "price": 40.2,
      "chg_pct": 6.21,
      "k": 65.1,
      "d": 47.4,
      "j": 100.6,
      "ma5": 37.41,
      "ma20": 37.64,
      "ma_gap": 0.6,
      "volume": 4095,
      "avg_vol5": 2611.3,
      "vol_ratio": 1.57,
      "buy_days": 0,
      "net_buy_ratio": 0.0,
      "foreign_buy_days": 6,
      "dif": -1.2342,
      "score": 3,
      "criteria": {
        "s1": false,
        "s2": false,
        "s3": false,
        "s4": true,
        "s5": true,
        "s6": true
      },
      "updated": "2026-05-07"
    },
    {
      "code": "2406",
      "name": "國碩",
      "sector": "光電",
      "price": 34.9,
      "chg_pct": 7.22,
      "k": 70.3,
      "d": 54.8,
      "j": 101.4,
      "ma5": 32.67,
      "ma20": 31.97,
      "ma_gap": 2.2,
      "volume": 19752,
      "avg_vol5": 9310.6,
      "vol_ratio": 2.12,
      "buy_days": 0,
      "net_buy_ratio": 0.0,
      "foreign_buy_days": 9,
      "dif": -0.0871,
      "score": 3,
      "criteria": {
        "s1": false,
        "s2": false,
        "s3": false,
        "s4": true,
        "s5": true,
        "s6": true
      },
      "updated": "2026-05-07"
    },
    {
      "code": "1477",
      "name": "聚陽",
      "sector": "紡織",
      "price": 220.5,
      "chg_pct": 3.76,
      "k": 49.0,
      "d": 34.5,
      "j": 77.8,
      "ma5": 213.3,
      "ma20": 216.9,
      "ma_gap": 1.7,
      "volume": 3238,
      "avg_vol5": 2302.0,
      "vol_ratio": 1.41,
      "buy_days": 8,
      "net_buy_ratio": 11.52,
      "foreign_buy_days": 0,
      "dif": -10.0569,
      "score": 3,
      "criteria": {
        "s1": true,
        "s2": true,
        "s3": false,
        "s4": false,
        "s5": true,
        "s6": false
      },
      "updated": "2026-05-07"
    },
    {
      "code": "2317",
      "name": "鴻海",
      "sector": "其他電子",
      "price": 253.5,
      "chg_pct": 0.6,
      "k": 86.0,
      "d": 80.3,
      "j": 97.6,
      "ma5": 238.4,
      "ma20": 219.25,
      "ma_gap": 8.7,
      "volume": 128768,
      "avg_vol5": 115599.4,
      "vol_ratio": 1.11,
      "buy_days": 4,
      "net_buy_ratio": 1.29,
      "foreign_buy_days": 8,
      "dif": 9.7046,
      "score": 2,
      "criteria": {
        "s1": true,
        "s2": false,
        "s3": false,
        "s4": false,
        "s5": false,
        "s6": true
      },
      "updated": "2026-05-07"
    },
    {
      "code": "2308",
      "name": "台達電",
      "sector": "電子零組件",
      "price": 2280.0,
      "chg_pct": 3.17,
      "k": 77.7,
      "d": 79.8,
      "j": 73.5,
      "ma5": 2208.0,
      "ma20": 1983.75,
      "ma_gap": 11.3,
      "volume": 15656,
      "avg_vol5": 13018.4,
      "vol_ratio": 1.2,
      "buy_days": 7,
      "net_buy_ratio": 6.27,
      "foreign_buy_days": 2,
      "dif": 180.5855,
      "score": 2,
      "criteria": {
        "s1": true,
        "s2": true,
        "s3": false,
        "s4": false,
        "s5": false,
        "s6": false
      },
      "updated": "2026-05-07"
    },
    {
      "code": "2303",
      "name": "聯電",
      "sector": "半導體",
      "price": 96.5,
      "chg_pct": 5.58,
      "k": 87.2,
      "d": 80.4,
      "j": 100.7,
      "ma5": 85.9,
      "ma20": 73.84,
      "ma_gap": 16.3,
      "volume": 325904,
      "avg_vol5": 225079.0,
      "vol_ratio": 1.45,
      "buy_days": 3,
      "net_buy_ratio": 5.94,
      "foreign_buy_days": 0,
      "dif": 6.8512,
      "score": 2,
      "criteria": {
        "s1": true,
        "s2": true,
        "s3": false,
        "s4": false,
        "s5": false,
        "s6": false
      },
      "updated": "2026-05-07"
    },
    {
      "code": "2412",
      "name": "中華電",
      "sector": "通信網路",
      "price": 135.5,
      "chg_pct": -0.37,
      "k": 29.6,
      "d": 39.2,
      "j": 10.4,
      "ma5": 135.8,
      "ma20": 136.05,
      "ma_gap": 0.2,
      "volume": 14117,
      "avg_vol5": 9063.2,
      "vol_ratio": 1.56,
      "buy_days": 3,
      "net_buy_ratio": 2.44,
      "foreign_buy_days": 0,
      "dif": 0.2185,
      "score": 2,
      "criteria": {
        "s1": true,
        "s2": false,
        "s3": true,
        "s4": false,
        "s5": false,
        "s6": false
      },
      "updated": "2026-05-07"
    },
    {
      "code": "2891",
      "name": "中信金",
      "sector": "金融保險",
      "price": 56.2,
      "chg_pct": 2.74,
      "k": 65.8,
      "d": 47.0,
      "j": 103.4,
      "ma5": 53.92,
      "ma20": 53.42,
      "ma_gap": 0.9,
      "volume": 77424,
      "avg_vol5": 53711.0,
      "vol_ratio": 1.44,
      "buy_days": 0,
      "net_buy_ratio": 0.0,
      "foreign_buy_days": 4,
      "dif": 0.3683,
      "score": 2,
      "criteria": {
        "s1": false,
        "s2": false,
        "s3": false,
        "s4": false,
        "s5": true,
        "s6": true
      },
      "updated": "2026-05-07"
    },
    {
      "code": "2886",
      "name": "兆豐金",
      "sector": "金融保險",
      "price": 39.65,
      "chg_pct": 0.25,
      "k": 42.2,
      "d": 42.3,
      "j": 42.1,
      "ma5": 39.28,
      "ma20": 39.58,
      "ma_gap": 0.8,
      "volume": 20903,
      "avg_vol5": 20424.8,
      "vol_ratio": 1.02,
      "buy_days": 2,
      "net_buy_ratio": 1.63,
      "foreign_buy_days": 2,
      "dif": 0.0359,
      "score": 2,
      "criteria": {
        "s1": false,
        "s2": false,
        "s3": true,
        "s4": false,
        "s5": true,
        "s6": false
      },
      "updated": "2026-05-07"
    },
    {
      "code": "3711",
      "name": "日月光投控",
      "sector": "半導體",
      "price": 540.0,
      "chg_pct": 3.05,
      "k": 76.1,
      "d": 73.9,
      "j": 80.6,
      "ma5": 517.4,
      "ma20": 469.55,
      "ma_gap": 10.2,
      "volume": 24884,
      "avg_vol5": 31242.0,
      "vol_ratio": 0.8,
      "buy_days": 10,
      "net_buy_ratio": 14.99,
      "foreign_buy_days": 0,
      "dif": 39.7313,
      "score": 2,
      "criteria": {
        "s1": true,
        "s2": true,
        "s3": false,
        "s4": false,
        "s5": false,
        "s6": false
      },
      "updated": "2026-05-07"
    },
    {
      "code": "2884",
      "name": "玉山金",
      "sector": "金融保險",
      "price": 32.1,
      "chg_pct": 0.78,
      "k": 35.8,
      "d": 31.6,
      "j": 44.1,
      "ma5": 31.73,
      "ma20": 32.41,
      "ma_gap": 2.1,
      "volume": 42536,
      "avg_vol5": 43650.6,
      "vol_ratio": 0.97,
      "buy_days": 0,
      "net_buy_ratio": 0.0,
      "foreign_buy_days": 3,
      "dif": -0.219,
      "score": 2,
      "criteria": {
        "s1": false,
        "s2": false,
        "s3": false,
        "s4": false,
        "s5": true,
        "s6": true
      },
      "updated": "2026-05-07"
    },
    {
      "code": "2892",
      "name": "第一金",
      "sector": "金融保險",
      "price": 29.15,
      "chg_pct": 1.22,
      "k": 62.7,
      "d": 51.2,
      "j": 85.6,
      "ma5": 28.69,
      "ma20": 28.63,
      "ma_gap": 0.2,
      "volume": 54247,
      "avg_vol5": 42506.7,
      "vol_ratio": 1.28,
      "buy_days": 0,
      "net_buy_ratio": 0.0,
      "foreign_buy_days": 3,
      "dif": -0.0072,
      "score": 2,
      "criteria": {
        "s1": false,
        "s2": false,
        "s3": false,
        "s4": false,
        "s5": true,
        "s6": true
      },
      "updated": "2026-05-07"
    },
    {
      "code": "2324",
      "name": "仁寶",
      "sector": "電腦週邊",
      "price": 29.45,
      "chg_pct": 0.86,
      "k": 16.9,
      "d": 18.5,
      "j": 13.8,
      "ma5": 29.23,
      "ma20": 29.74,
      "ma_gap": 1.7,
      "volume": 49286,
      "avg_vol5": 25759.1,
      "vol_ratio": 1.91,
      "buy_days": 0,
      "net_buy_ratio": 0.0,
      "foreign_buy_days": 1,
      "dif": -0.2039,
      "score": 2,
      "criteria": {
        "s1": false,
        "s2": false,
        "s3": false,
        "s4": true,
        "s5": true,
        "s6": false
      },
      "updated": "2026-05-07"
    },
    {
      "code": "3008",
      "name": "大立光",
      "sector": "光電",
      "price": 2575.0,
      "chg_pct": 2.18,
      "k": 38.9,
      "d": 38.0,
      "j": 40.7,
      "ma5": 2546.0,
      "ma20": 2570.0,
      "ma_gap": 0.9,
      "volume": 1194,
      "avg_vol5": 1252.5,
      "vol_ratio": 0.95,
      "buy_days": 0,
      "net_buy_ratio": 0.0,
      "foreign_buy_days": 2,
      "dif": 46.0133,
      "score": 2,
      "criteria": {
        "s1": false,
        "s2": false,
        "s3": true,
        "s4": false,
        "s5": true,
        "s6": false
      },
      "updated": "2026-05-07"
    },
    {
      "code": "2603",
      "name": "長榮",
      "sector": "航運",
      "price": 213.5,
      "chg_pct": 0.71,
      "k": 81.5,
      "d": 71.1,
      "j": 102.2,
      "ma5": 208.3,
      "ma20": 202.72,
      "ma_gap": 2.8,
      "volume": 10470,
      "avg_vol5": 10322.8,
      "vol_ratio": 1.01,
      "buy_days": 0,
      "net_buy_ratio": 0.0,
      "foreign_buy_days": 8,
      "dif": 1.64,
      "score": 2,
      "criteria": {
        "s1": false,
        "s2": false,
        "s3": false,
        "s4": false,
        "s5": true,
        "s6": true
      },
      "updated": "2026-05-07"
    },
    {
      "code": "2615",
      "name": "萬海",
      "sector": "航運",
      "price": 78.2,
      "chg_pct": 0.51,
      "k": 78.8,
      "d": 58.7,
      "j": 119.1,
      "ma5": 76.64,
      "ma20": 75.83,
      "ma_gap": 1.1,
      "volume": 6669,
      "avg_vol5": 6137.9,
      "vol_ratio": 1.09,
      "buy_days": 0,
      "net_buy_ratio": 0.0,
      "foreign_buy_days": 4,
      "dif": -0.0423,
      "score": 2,
      "criteria": {
        "s1": false,
        "s2": false,
        "s3": false,
        "s4": false,
        "s5": true,
        "s6": true
      },
      "updated": "2026-05-07"
    },
    {
      "code": "2376",
      "name": "技嘉",
      "sector": "電腦週邊",
      "price": 309.0,
      "chg_pct": 2.66,
      "k": 64.3,
      "d": 52.5,
      "j": 87.7,
      "ma5": 288.3,
      "ma20": 278.43,
      "ma_gap": 3.5,
      "volume": 24537,
      "avg_vol5": 9621.1,
      "vol_ratio": 2.55,
      "buy_days": 1,
      "net_buy_ratio": 1.17,
      "foreign_buy_days": 5,
      "dif": 12.5242,
      "score": 2,
      "criteria": {
        "s1": false,
        "s2": false,
        "s3": false,
        "s4": true,
        "s5": false,
        "s6": true
      },
      "updated": "2026-05-07"
    },
    {
      "code": "2481",
      "name": "強茂",
      "sector": "半導體",
      "price": 103.5,
      "chg_pct": 1.97,
      "k": 46.1,
      "d": 35.2,
      "j": 68.0,
      "ma5": 101.54,
      "ma20": 103.09,
      "ma_gap": 1.5,
      "volume": 18298,
      "avg_vol5": 17127.9,
      "vol_ratio": 1.07,
      "buy_days": 0,
      "net_buy_ratio": 0.0,
      "foreign_buy_days": 1,
      "dif": 1.0138,
      "score": 2,
      "criteria": {
        "s1": false,
        "s2": false,
        "s3": true,
        "s4": false,
        "s5": true,
        "s6": false
      },
      "updated": "2026-05-07"
    },
    {
      "code": "3034",
      "name": "聯詠",
      "sector": "半導體",
      "price": 453.0,
      "chg_pct": 2.6,
      "k": 69.9,
      "d": 51.4,
      "j": 106.9,
      "ma5": 427.8,
      "ma20": 414.1,
      "ma_gap": 3.3,
      "volume": 6507,
      "avg_vol5": 4145.1,
      "vol_ratio": 1.57,
      "buy_days": 3,
      "net_buy_ratio": 0.37,
      "foreign_buy_days": 2,
      "dif": 11.1373,
      "score": 2,
      "criteria": {
        "s1": true,
        "s2": false,
        "s3": false,
        "s4": true,
        "s5": false,
        "s6": false
      },
      "updated": "2026-05-07"
    },
    {
      "code": "2610",
      "name": "華航",
      "sector": "航運",
      "price": 18.6,
      "chg_pct": 3.62,
      "k": 66.1,
      "d": 50.0,
      "j": 98.3,
      "ma5": 18.1,
      "ma20": 18.11,
      "ma_gap": 0.1,
      "volume": 51649,
      "avg_vol5": 18658.7,
      "vol_ratio": 2.77,
      "buy_days": 0,
      "net_buy_ratio": 0.0,
      "foreign_buy_days": 1,
      "dif": -0.1821,
      "score": 2,
      "criteria": {
        "s1": false,
        "s2": false,
        "s3": false,
        "s4": true,
        "s5": true,
        "s6": false
      },
      "updated": "2026-05-07"
    },
    {
      "code": "2887",
      "name": "台新金",
      "sector": "金融保險",
      "price": 24.0,
      "chg_pct": 0.21,
      "k": 35.5,
      "d": 28.2,
      "j": 50.3,
      "ma5": 23.79,
      "ma20": 24.13,
      "ma_gap": 1.4,
      "volume": 88192,
      "avg_vol5": 87694.6,
      "vol_ratio": 1.01,
      "buy_days": 0,
      "net_buy_ratio": 0.0,
      "foreign_buy_days": 5,
      "dif": -0.1098,
      "score": 2,
      "criteria": {
        "s1": false,
        "s2": false,
        "s3": false,
        "s4": false,
        "s5": true,
        "s6": true
      },
      "updated": "2026-05-07"
    },
    {
      "code": "2105",
      "name": "正新",
      "sector": "橡膠",
      "price": 32.0,
      "chg_pct": 3.06,
      "k": 33.6,
      "d": 24.1,
      "j": 52.5,
      "ma5": 31.22,
      "ma20": 32.0,
      "ma_gap": 2.4,
      "volume": 10173,
      "avg_vol5": 9087.1,
      "vol_ratio": 1.12,
      "buy_days": 0,
      "net_buy_ratio": 0.0,
      "foreign_buy_days": 1,
      "dif": 0.0601,
      "score": 2,
      "criteria": {
        "s1": false,
        "s2": false,
        "s3": true,
        "s4": false,
        "s5": true,
        "s6": false
      },
      "updated": "2026-05-07"
    },
    {
      "code": "9910",
      "name": "豐泰",
      "sector": "其他",
      "price": 70.1,
      "chg_pct": 1.89,
      "k": 15.1,
      "d": 12.1,
      "j": 21.3,
      "ma5": 69.8,
      "ma20": 74.33,
      "ma_gap": 6.1,
      "volume": 3182,
      "avg_vol5": 2264.8,
      "vol_ratio": 1.41,
      "buy_days": 13,
      "net_buy_ratio": 10.21,
      "foreign_buy_days": 1,
      "dif": -3.3556,
      "score": 2,
      "criteria": {
        "s1": true,
        "s2": true,
        "s3": false,
        "s4": false,
        "s5": false,
        "s6": false
      },
      "updated": "2026-05-07"
    },
    {
      "code": "2912",
      "name": "統一超",
      "sector": "貿易百貨",
      "price": 228.5,
      "chg_pct": 0.66,
      "k": 26.6,
      "d": 22.1,
      "j": 35.6,
      "ma5": 225.8,
      "ma20": 229.65,
      "ma_gap": 1.7,
      "volume": 2969,
      "avg_vol5": 2158.7,
      "vol_ratio": 1.38,
      "buy_days": 0,
      "net_buy_ratio": 0.0,
      "foreign_buy_days": 2,
      "dif": 0.4349,
      "score": 2,
      "criteria": {
        "s1": false,
        "s2": false,
        "s3": true,
        "s4": false,
        "s5": true,
        "s6": false
      },
      "updated": "2026-05-07"
    },
    {
      "code": "3045",
      "name": "台灣大",
      "sector": "通信網路",
      "price": 110.0,
      "chg_pct": 0.0,
      "k": 8.6,
      "d": 20.1,
      "j": -14.3,
      "ma5": 110.5,
      "ma20": 111.25,
      "ma_gap": 0.7,
      "volume": 6207,
      "avg_vol5": 8534.7,
      "vol_ratio": 0.73,
      "buy_days": 0,
      "net_buy_ratio": 0.0,
      "foreign_buy_days": 3,
      "dif": 0.3123,
      "score": 2,
      "criteria": {
        "s1": false,
        "s2": false,
        "s3": true,
        "s4": false,
        "s5": false,
        "s6": true
      },
      "updated": "2026-05-07"
    },
    {
      "code": "4904",
      "name": "遠傳",
      "sector": "通信網路",
      "price": 95.4,
      "chg_pct": 0.32,
      "k": 41.0,
      "d": 36.9,
      "j": 49.1,
      "ma5": 95.02,
      "ma20": 95.51,
      "ma_gap": 0.5,
      "volume": 5049,
      "avg_vol5": 5754.3,
      "vol_ratio": 0.88,
      "buy_days": 0,
      "net_buy_ratio": 0.0,
      "foreign_buy_days": 0,
      "dif": 0.4412,
      "score": 2,
      "criteria": {
        "s1": false,
        "s2": false,
        "s3": true,
        "s4": false,
        "s5": true,
        "s6": false
      },
      "updated": "2026-05-07"
    },
    {
      "code": "3481",
      "name": "群創",
      "sector": "光電",
      "price": 29.75,
      "chg_pct": 5.87,
      "k": 75.4,
      "d": 55.6,
      "j": 114.9,
      "ma5": 26.77,
      "ma20": 25.95,
      "ma_gap": 3.2,
      "volume": 860297,
      "avg_vol5": 344352.3,
      "vol_ratio": 2.5,
      "buy_days": 2,
      "net_buy_ratio": 0.02,
      "foreign_buy_days": 5,
      "dif": 0.3764,
      "score": 2,
      "criteria": {
        "s1": false,
        "s2": false,
        "s3": false,
        "s4": true,
        "s5": false,
        "s6": true
      },
      "updated": "2026-05-07"
    },
    {
      "code": "3231",
      "name": "緯創",
      "sector": "電腦週邊",
      "price": 146.0,
      "chg_pct": -0.34,
      "k": 72.2,
      "d": 65.5,
      "j": 85.6,
      "ma5": 142.4,
      "ma20": 139.38,
      "ma_gap": 2.2,
      "volume": 43322,
      "avg_vol5": 34094.1,
      "vol_ratio": 1.27,
      "buy_days": 2,
      "net_buy_ratio": 0.53,
      "foreign_buy_days": 4,
      "dif": 3.2878,
      "score": 2,
      "criteria": {
        "s1": false,
        "s2": false,
        "s3": false,
        "s4": false,
        "s5": true,
        "s6": true
      },
      "updated": "2026-05-07"
    },
    {
      "code": "6669",
      "name": "緯穎",
      "sector": "電腦週邊",
      "price": 4880.0,
      "chg_pct": -1.81,
      "k": 79.6,
      "d": 80.6,
      "j": 77.7,
      "ma5": 4828.0,
      "ma20": 4297.25,
      "ma_gap": 12.4,
      "volume": 2033,
      "avg_vol5": 2349.1,
      "vol_ratio": 0.87,
      "buy_days": 14,
      "net_buy_ratio": 8.95,
      "foreign_buy_days": 0,
      "dif": 312.3539,
      "score": 2,
      "criteria": {
        "s1": true,
        "s2": true,
        "s3": false,
        "s4": false,
        "s5": false,
        "s6": false
      },
      "updated": "2026-05-07"
    },
    {
      "code": "1717",
      "name": "長興",
      "sector": "化學",
      "price": 79.7,
      "chg_pct": 0.38,
      "k": 43.8,
      "d": 38.6,
      "j": 54.3,
      "ma5": 79.32,
      "ma20": 79.11,
      "ma_gap": 0.3,
      "volume": 48318,
      "avg_vol5": 46756.9,
      "vol_ratio": 1.03,
      "buy_days": 1,
      "net_buy_ratio": 0.02,
      "foreign_buy_days": 0,
      "dif": 3.0802,
      "score": 2,
      "criteria": {
        "s1": false,
        "s2": false,
        "s3": true,
        "s4": false,
        "s5": true,
        "s6": false
      },
      "updated": "2026-05-07"
    },
    {
      "code": "1503",
      "name": "士電",
      "sector": "電機機械",
      "price": 199.5,
      "chg_pct": 1.53,
      "k": 51.0,
      "d": 46.2,
      "j": 60.5,
      "ma5": 197.0,
      "ma20": 193.53,
      "ma_gap": 1.8,
      "volume": 2336,
      "avg_vol5": 2764.0,
      "vol_ratio": 0.85,
      "buy_days": 3,
      "net_buy_ratio": 3.21,
      "foreign_buy_days": 1,
      "dif": -0.0157,
      "score": 2,
      "criteria": {
        "s1": true,
        "s2": false,
        "s3": false,
        "s4": false,
        "s5": true,
        "s6": false
      },
      "updated": "2026-05-07"
    },
    {
      "code": "2014",
      "name": "中鴻",
      "sector": "鋼鐵",
      "price": 18.2,
      "chg_pct": 0.83,
      "k": 67.6,
      "d": 47.8,
      "j": 107.4,
      "ma5": 17.75,
      "ma20": 18.07,
      "ma_gap": 1.8,
      "volume": 6890,
      "avg_vol5": 4681.3,
      "vol_ratio": 1.47,
      "buy_days": 0,
      "net_buy_ratio": 0.0,
      "foreign_buy_days": 8,
      "dif": -0.1224,
      "score": 2,
      "criteria": {
        "s1": false,
        "s2": false,
        "s3": false,
        "s4": false,
        "s5": true,
        "s6": true
      },
      "updated": "2026-05-07"
    },
    {
      "code": "2027",
      "name": "大成鋼",
      "sector": "鋼鐵",
      "price": 39.1,
      "chg_pct": 1.69,
      "k": 77.5,
      "d": 63.6,
      "j": 105.1,
      "ma5": 38.14,
      "ma20": 37.61,
      "ma_gap": 1.4,
      "volume": 30542,
      "avg_vol5": 21974.4,
      "vol_ratio": 1.39,
      "buy_days": 1,
      "net_buy_ratio": 0.82,
      "foreign_buy_days": 7,
      "dif": 0.2421,
      "score": 2,
      "criteria": {
        "s1": false,
        "s2": false,
        "s3": false,
        "s4": false,
        "s5": true,
        "s6": true
      },
      "updated": "2026-05-07"
    },
    {
      "code": "2201",
      "name": "裕隆",
      "sector": "汽車",
      "price": 27.7,
      "chg_pct": 2.03,
      "k": 44.0,
      "d": 30.0,
      "j": 72.2,
      "ma5": 27.16,
      "ma20": 27.12,
      "ma_gap": 0.1,
      "volume": 4106,
      "avg_vol5": 2193.5,
      "vol_ratio": 1.87,
      "buy_days": 1,
      "net_buy_ratio": 0.07,
      "foreign_buy_days": 1,
      "dif": -0.1681,
      "score": 2,
      "criteria": {
        "s1": false,
        "s2": false,
        "s3": false,
        "s4": true,
        "s5": true,
        "s6": false
      },
      "updated": "2026-05-07"
    },
    {
      "code": "2492",
      "name": "華新科",
      "sector": "被動元件",
      "price": 160.0,
      "chg_pct": 8.84,
      "k": 74.8,
      "d": 60.2,
      "j": 104.2,
      "ma5": 145.1,
      "ma20": 140.18,
      "ma_gap": 3.5,
      "volume": 41249,
      "avg_vol5": 14077.4,
      "vol_ratio": 2.93,
      "buy_days": 0,
      "net_buy_ratio": 0.0,
      "foreign_buy_days": 4,
      "dif": 4.1545,
      "score": 2,
      "criteria": {
        "s1": false,
        "s2": false,
        "s3": false,
        "s4": true,
        "s5": false,
        "s6": true
      },
      "updated": "2026-05-07"
    },
    {
      "code": "3443",
      "name": "創意",
      "sector": "半導體",
      "price": 5450.0,
      "chg_pct": 9.99,
      "k": 96.0,
      "d": 92.4,
      "j": 103.2,
      "ma5": 4837.0,
      "ma20": 3810.0,
      "ma_gap": 27.0,
      "volume": 2180,
      "avg_vol5": 2466.0,
      "vol_ratio": 0.88,
      "buy_days": 5,
      "net_buy_ratio": 16.62,
      "foreign_buy_days": 0,
      "dif": 613.0547,
      "score": 2,
      "criteria": {
        "s1": true,
        "s2": true,
        "s3": false,
        "s4": false,
        "s5": false,
        "s6": false
      },
      "updated": "2026-05-07"
    },
    {
      "code": "6206",
      "name": "飛捷",
      "sector": "電腦週邊",
      "price": 117.0,
      "chg_pct": 5.88,
      "k": 71.7,
      "d": 60.8,
      "j": 93.5,
      "ma5": 111.4,
      "ma20": 107.2,
      "ma_gap": 3.9,
      "volume": 3886,
      "avg_vol5": 889.9,
      "vol_ratio": 4.37,
      "buy_days": 0,
      "net_buy_ratio": 0.0,
      "foreign_buy_days": 6,
      "dif": 2.9845,
      "score": 2,
      "criteria": {
        "s1": false,
        "s2": false,
        "s3": false,
        "s4": true,
        "s5": false,
        "s6": true
      },
      "updated": "2026-05-07"
    },
    {
      "code": "3035",
      "name": "智原",
      "sector": "半導體",
      "price": 181.0,
      "chg_pct": -0.28,
      "k": 41.0,
      "d": 43.1,
      "j": 36.9,
      "ma5": 175.3,
      "ma20": 168.18,
      "ma_gap": 4.2,
      "volume": 13577,
      "avg_vol5": 12287.2,
      "vol_ratio": 1.1,
      "buy_days": 0,
      "net_buy_ratio": 0.0,
      "foreign_buy_days": 3,
      "dif": 6.0981,
      "score": 2,
      "criteria": {
        "s1": false,
        "s2": false,
        "s3": true,
        "s4": false,
        "s5": false,
        "s6": true
      },
      "updated": "2026-05-07"
    },
    {
      "code": "8016",
      "name": "矽創",
      "sector": "半導體",
      "price": 265.5,
      "chg_pct": 9.94,
      "k": 74.2,
      "d": 62.6,
      "j": 97.4,
      "ma5": 241.0,
      "ma20": 222.8,
      "ma_gap": 8.2,
      "volume": 5281,
      "avg_vol5": 1315.5,
      "vol_ratio": 4.01,
      "buy_days": 0,
      "net_buy_ratio": 0.0,
      "foreign_buy_days": 5,
      "dif": 11.7169,
      "score": 2,
      "criteria": {
        "s1": false,
        "s2": false,
        "s3": false,
        "s4": true,
        "s5": false,
        "s6": true
      },
      "updated": "2026-05-07"
    },
    {
      "code": "2356",
      "name": "英業達",
      "sector": "電腦週邊",
      "price": 49.95,
      "chg_pct": 1.52,
      "k": 61.7,
      "d": 50.2,
      "j": 84.7,
      "ma5": 47.7,
      "ma20": 46.32,
      "ma_gap": 3.0,
      "volume": 42154,
      "avg_vol5": 20426.8,
      "vol_ratio": 2.06,
      "buy_days": 0,
      "net_buy_ratio": 0.0,
      "foreign_buy_days": 7,
      "dif": 1.2611,
      "score": 2,
      "criteria": {
        "s1": false,
        "s2": false,
        "s3": false,
        "s4": true,
        "s5": false,
        "s6": true
      },
      "updated": "2026-05-07"
    },
    {
      "code": "3533",
      "name": "嘉澤",
      "sector": "電子零組件",
      "price": 2850.0,
      "chg_pct": 4.2,
      "k": 68.6,
      "d": 65.0,
      "j": 75.9,
      "ma5": 2660.0,
      "ma20": 2532.5,
      "ma_gap": 5.0,
      "volume": 2272,
      "avg_vol5": 1587.2,
      "vol_ratio": 1.43,
      "buy_days": 2,
      "net_buy_ratio": 9.96,
      "foreign_buy_days": 11,
      "dif": 165.9001,
      "score": 2,
      "criteria": {
        "s1": false,
        "s2": true,
        "s3": false,
        "s4": false,
        "s5": false,
        "s6": true
      },
      "updated": "2026-05-07"
    },
    {
      "code": "5434",
      "name": "崇越",
      "sector": "電子通路",
      "price": 418.5,
      "chg_pct": -1.53,
      "k": 43.2,
      "d": 37.8,
      "j": 54.2,
      "ma5": 415.4,
      "ma20": 411.95,
      "ma_gap": 0.8,
      "volume": 785,
      "avg_vol5": 565.3,
      "vol_ratio": 1.39,
      "buy_days": 0,
      "net_buy_ratio": 0.0,
      "foreign_buy_days": 0,
      "dif": 16.5245,
      "score": 2,
      "criteria": {
        "s1": false,
        "s2": false,
        "s3": true,
        "s4": false,
        "s5": true,
        "s6": false
      },
      "updated": "2026-05-07"
    },
    {
      "code": "3036",
      "name": "文曄",
      "sector": "電子通路",
      "price": 219.0,
      "chg_pct": 2.34,
      "k": 60.6,
      "d": 44.9,
      "j": 92.0,
      "ma5": 211.3,
      "ma20": 216.0,
      "ma_gap": 2.2,
      "volume": 19017,
      "avg_vol5": 8113.0,
      "vol_ratio": 2.34,
      "buy_days": 0,
      "net_buy_ratio": 0.0,
      "foreign_buy_days": 0,
      "dif": -2.6073,
      "score": 2,
      "criteria": {
        "s1": false,
        "s2": false,
        "s3": false,
        "s4": true,
        "s5": true,
        "s6": false
      },
      "updated": "2026-05-07"
    },
    {
      "code": "9933",
      "name": "中鼎",
      "sector": "其他",
      "price": 37.3,
      "chg_pct": 1.36,
      "k": 56.3,
      "d": 48.3,
      "j": 72.2,
      "ma5": 36.87,
      "ma20": 36.73,
      "ma_gap": 0.4,
      "volume": 4755,
      "avg_vol5": 2936.8,
      "vol_ratio": 1.62,
      "buy_days": 1,
      "net_buy_ratio": 0.02,
      "foreign_buy_days": 2,
      "dif": 0.5026,
      "score": 2,
      "criteria": {
        "s1": false,
        "s2": false,
        "s3": false,
        "s4": true,
        "s5": true,
        "s6": false
      },
      "updated": "2026-05-07"
    },
    {
      "code": "8112",
      "name": "至上",
      "sector": "電子通路",
      "price": 86.9,
      "chg_pct": 0.12,
      "k": 48.3,
      "d": 43.4,
      "j": 58.0,
      "ma5": 84.54,
      "ma20": 84.64,
      "ma_gap": 0.1,
      "volume": 12653,
      "avg_vol5": 15600.5,
      "vol_ratio": 0.81,
      "buy_days": 0,
      "net_buy_ratio": 0.0,
      "foreign_buy_days": 0,
      "dif": 1.1545,
      "score": 2,
      "criteria": {
        "s1": false,
        "s2": false,
        "s3": true,
        "s4": false,
        "s5": true,
        "s6": false
      },
      "updated": "2026-05-07"
    },
    {
      "code": "9907",
      "name": "統一實",
      "sector": "其他",
      "price": 17.25,
      "chg_pct": -0.29,
      "k": 17.8,
      "d": 19.1,
      "j": 15.2,
      "ma5": 17.47,
      "ma20": 17.84,
      "ma_gap": 2.1,
      "volume": 4901,
      "avg_vol5": 4551.8,
      "vol_ratio": 1.08,
      "buy_days": 5,
      "net_buy_ratio": 9.96,
      "foreign_buy_days": 0,
      "dif": -0.2186,
      "score": 2,
      "criteria": {
        "s1": true,
        "s2": true,
        "s3": false,
        "s4": false,
        "s5": false,
        "s6": false
      },
      "updated": "2026-05-07"
    },
    {
      "code": "2330",
      "name": "台積電",
      "sector": "半導體",
      "price": 2310.0,
      "chg_pct": 2.67,
      "k": 74.0,
      "d": 69.3,
      "j": 83.4,
      "ma5": 2244.0,
      "ma20": 2123.25,
      "ma_gap": 5.7,
      "volume": 41966,
      "avg_vol5": 43572.4,
      "vol_ratio": 0.96,
      "buy_days": 10,
      "net_buy_ratio": 3.42,
      "foreign_buy_days": 1,
      "dif": 94.3527,
      "score": 1,
      "criteria": {
        "s1": true,
        "s2": false,
        "s3": false,
        "s4": false,
        "s5": false,
        "s6": false
      },
      "updated": "2026-05-07"
    },
    {
      "code": "2881",
      "name": "富邦金",
      "sector": "金融保險",
      "price": 94.5,
      "chg_pct": 1.83,
      "k": 80.3,
      "d": 71.5,
      "j": 97.7,
      "ma5": 92.1,
      "ma20": 89.07,
      "ma_gap": 3.4,
      "volume": 35428,
      "avg_vol5": 33634.9,
      "vol_ratio": 1.05,
      "buy_days": 0,
      "net_buy_ratio": 0.0,
      "foreign_buy_days": 8,
      "dif": 1.0653,
      "score": 1,
      "criteria": {
        "s1": false,
        "s2": false,
        "s3": false,
        "s4": false,
        "s5": false,
        "s6": true
      },
      "updated": "2026-05-07"
    },
    {
      "code": "2382",
      "name": "廣達",
      "sector": "電腦週邊",
      "price": 344.0,
      "chg_pct": -0.72,
      "k": 58.5,
      "d": 44.8,
      "j": 86.0,
      "ma5": 328.4,
      "ma20": 324.3,
      "ma_gap": 1.3,
      "volume": 23383,
      "avg_vol5": 21135.5,
      "vol_ratio": 1.11,
      "buy_days": 1,
      "net_buy_ratio": 0.62,
      "foreign_buy_days": 0,
      "dif": 9.1159,
      "score": 1,
      "criteria": {
        "s1": false,
        "s2": false,
        "s3": false,
        "s4": false,
        "s5": true,
        "s6": false
      },
      "updated": "2026-05-07"
    },
    {
      "code": "5880",
      "name": "合庫金",
      "sector": "金融保險",
      "price": 23.0,
      "chg_pct": 0.22,
      "k": 28.8,
      "d": 20.4,
      "j": 45.7,
      "ma5": 22.94,
      "ma20": 23.39,
      "ma_gap": 1.9,
      "volume": 22627,
      "avg_vol5": 15403.5,
      "vol_ratio": 1.47,
      "buy_days": 2,
      "net_buy_ratio": 0.89,
      "foreign_buy_days": 1,
      "dif": -0.1663,
      "score": 1,
      "criteria": {
        "s1": false,
        "s2": false,
        "s3": false,
        "s4": false,
        "s5": true,
        "s6": false
      },
      "updated": "2026-05-07"
    },
    {
      "code": "1301",
      "name": "台塑",
      "sector": "塑膠",
      "price": 49.55,
      "chg_pct": -2.27,
      "k": 34.3,
      "d": 39.3,
      "j": 24.5,
      "ma5": 50.77,
      "ma20": 51.2,
      "ma_gap": 0.8,
      "volume": 27679,
      "avg_vol5": 18303.6,
      "vol_ratio": 1.51,
      "buy_days": 0,
      "net_buy_ratio": 0.0,
      "foreign_buy_days": 0,
      "dif": 0.4968,
      "score": 1,
      "criteria": {
        "s1": false,
        "s2": false,
        "s3": true,
        "s4": false,
        "s5": false,
        "s6": false
      },
      "updated": "2026-05-07"
    },
    {
      "code": "1216",
      "name": "統一",
      "sector": "食品",
      "price": 69.4,
      "chg_pct": 1.02,
      "k": 12.2,
      "d": 11.7,
      "j": 13.2,
      "ma5": 69.22,
      "ma20": 71.23,
      "ma_gap": 2.8,
      "volume": 19155,
      "avg_vol5": 13889.8,
      "vol_ratio": 1.38,
      "buy_days": 0,
      "net_buy_ratio": 0.0,
      "foreign_buy_days": 1,
      "dif": -0.7158,
      "score": 1,
      "criteria": {
        "s1": false,
        "s2": false,
        "s3": false,
        "s4": false,
        "s5": true,
        "s6": false
      },
      "updated": "2026-05-07"
    },
    {
      "code": "2880",
      "name": "華南金",
      "sector": "金融保險",
      "price": 33.3,
      "chg_pct": 1.83,
      "k": 25.3,
      "d": 21.7,
      "j": 32.4,
      "ma5": 32.55,
      "ma20": 34.32,
      "ma_gap": 5.2,
      "volume": 25270,
      "avg_vol5": 23167.4,
      "vol_ratio": 1.09,
      "buy_days": 0,
      "net_buy_ratio": 0.0,
      "foreign_buy_days": 3,
      "dif": -0.4407,
      "score": 1,
      "criteria": {
        "s1": false,
        "s2": false,
        "s3": false,
        "s4": false,
        "s5": false,
        "s6": true
      },
      "updated": "2026-05-07"
    },
    {
      "code": "2609",
      "name": "陽明",
      "sector": "航運",
      "price": 50.7,
      "chg_pct": 0.2,
      "k": 50.8,
      "d": 32.2,
      "j": 88.0,
      "ma5": 50.1,
      "ma20": 50.35,
      "ma_gap": 0.5,
      "volume": 15115,
      "avg_vol5": 14857.7,
      "vol_ratio": 1.02,
      "buy_days": 1,
      "net_buy_ratio": 0.21,
      "foreign_buy_days": 2,
      "dif": -0.9297,
      "score": 1,
      "criteria": {
        "s1": false,
        "s2": false,
        "s3": false,
        "s4": false,
        "s5": true,
        "s6": false
      },
      "updated": "2026-05-07"
    },
    {
      "code": "2605",
      "name": "新興",
      "sector": "航運",
      "price": 34.4,
      "chg_pct": -3.1,
      "k": 61.3,
      "d": 53.0,
      "j": 78.0,
      "ma5": 34.9,
      "ma20": 35.26,
      "ma_gap": 1.0,
      "volume": 8250,
      "avg_vol5": 5360.5,
      "vol_ratio": 1.54,
      "buy_days": 0,
      "net_buy_ratio": 0.0,
      "foreign_buy_days": 4,
      "dif": -0.8653,
      "score": 1,
      "criteria": {
        "s1": false,
        "s2": false,
        "s3": false,
        "s4": false,
        "s5": false,
        "s6": true
      },
      "updated": "2026-05-07"
    },
    {
      "code": "2353",
      "name": "宏碁",
      "sector": "電腦週邊",
      "price": 28.1,
      "chg_pct": 0.0,
      "k": 56.0,
      "d": 41.8,
      "j": 84.5,
      "ma5": 27.92,
      "ma20": 27.75,
      "ma_gap": 0.6,
      "volume": 22041,
      "avg_vol5": 19553.1,
      "vol_ratio": 1.13,
      "buy_days": 0,
      "net_buy_ratio": 0.0,
      "foreign_buy_days": 2,
      "dif": 0.1514,
      "score": 1,
      "criteria": {
        "s1": false,
        "s2": false,
        "s3": false,
        "s4": false,
        "s5": true,
        "s6": false
      },
      "updated": "2026-05-07"
    },
    {
      "code": "2352",
      "name": "佳世達",
      "sector": "電腦週邊",
      "price": 25.2,
      "chg_pct": -2.51,
      "k": 54.0,
      "d": 43.2,
      "j": 75.5,
      "ma5": 24.86,
      "ma20": 24.8,
      "ma_gap": 0.2,
      "volume": 8711,
      "avg_vol5": 5263.4,
      "vol_ratio": 1.65,
      "buy_days": 0,
      "net_buy_ratio": 0.0,
      "foreign_buy_days": 0,
      "dif": 0.1903,
      "score": 1,
      "criteria": {
        "s1": false,
        "s2": false,
        "s3": false,
        "s4": false,
        "s5": true,
        "s6": false
      },
      "updated": "2026-05-07"
    },
    {
      "code": "8046",
      "name": "南電",
      "sector": "電子零組件",
      "price": 947.0,
      "chg_pct": 0.74,
      "k": 71.7,
      "d": 80.2,
      "j": 54.6,
      "ma5": 975.0,
      "ma20": 821.55,
      "ma_gap": 18.7,
      "volume": 11915,
      "avg_vol5": 19177.1,
      "vol_ratio": 0.62,
      "buy_days": 1,
      "net_buy_ratio": 0.64,
      "foreign_buy_days": 3,
      "dif": 102.9076,
      "score": 1,
      "criteria": {
        "s1": false,
        "s2": false,
        "s3": false,
        "s4": false,
        "s5": false,
        "s6": true
      },
      "updated": "2026-05-07"
    },
    {
      "code": "3189",
      "name": "景碩",
      "sector": "電子零組件",
      "price": 492.5,
      "chg_pct": 2.07,
      "k": 47.6,
      "d": 64.6,
      "j": 13.6,
      "ma5": 512.2,
      "ma20": 458.32,
      "ma_gap": 11.8,
      "volume": 21100,
      "avg_vol5": 29379.1,
      "vol_ratio": 0.72,
      "buy_days": 0,
      "net_buy_ratio": 0.0,
      "foreign_buy_days": 1,
      "dif": 42.4107,
      "score": 1,
      "criteria": {
        "s1": false,
        "s2": false,
        "s3": true,
        "s4": false,
        "s5": false,
        "s6": false
      },
      "updated": "2026-05-07"
    },
    {
      "code": "2883",
      "name": "開發金",
      "sector": "金融保險",
      "price": 22.45,
      "chg_pct": 1.13,
      "k": 87.4,
      "d": 79.4,
      "j": 103.6,
      "ma5": 21.87,
      "ma20": 21.14,
      "ma_gap": 3.5,
      "volume": 74881,
      "avg_vol5": 65207.7,
      "vol_ratio": 1.15,
      "buy_days": 1,
      "net_buy_ratio": 0.47,
      "foreign_buy_days": 9,
      "dif": 0.4582,
      "score": 1,
      "criteria": {
        "s1": false,
        "s2": false,
        "s3": false,
        "s4": false,
        "s5": false,
        "s6": true
      },
      "updated": "2026-05-07"
    },
    {
      "code": "2890",
      "name": "永豐金",
      "sector": "金融保險",
      "price": 30.9,
      "chg_pct": -0.32,
      "k": 29.0,
      "d": 22.2,
      "j": 42.5,
      "ma5": 30.81,
      "ma20": 31.97,
      "ma_gap": 3.6,
      "volume": 32907,
      "avg_vol5": 29676.2,
      "vol_ratio": 1.11,
      "buy_days": 2,
      "net_buy_ratio": 2.19,
      "foreign_buy_days": 3,
      "dif": -0.267,
      "score": 1,
      "criteria": {
        "s1": false,
        "s2": false,
        "s3": false,
        "s4": false,
        "s5": false,
        "s6": true
      },
      "updated": "2026-05-07"
    },
    {
      "code": "5871",
      "name": "中租-KY",
      "sector": "其他",
      "price": 114.5,
      "chg_pct": -1.29,
      "k": 20.7,
      "d": 30.7,
      "j": 0.8,
      "ma5": 115.2,
      "ma20": 115.95,
      "ma_gap": 0.6,
      "volume": 5844,
      "avg_vol5": 5354.3,
      "vol_ratio": 1.09,
      "buy_days": 0,
      "net_buy_ratio": 0.0,
      "foreign_buy_days": 0,
      "dif": 1.7064,
      "score": 1,
      "criteria": {
        "s1": false,
        "s2": false,
        "s3": true,
        "s4": false,
        "s5": false,
        "s6": false
      },
      "updated": "2026-05-07"
    },
    {
      "code": "5876",
      "name": "上海商銀",
      "sector": "金融保險",
      "price": 38.8,
      "chg_pct": 1.04,
      "k": 23.0,
      "d": 26.6,
      "j": 15.9,
      "ma5": 38.65,
      "ma20": 39.37,
      "ma_gap": 1.8,
      "volume": 6751,
      "avg_vol5": 8110.5,
      "vol_ratio": 0.83,
      "buy_days": 0,
      "net_buy_ratio": 0.0,
      "foreign_buy_days": 1,
      "dif": -0.226,
      "score": 1,
      "criteria": {
        "s1": false,
        "s2": false,
        "s3": false,
        "s4": false,
        "s5": true,
        "s6": false
      },
      "updated": "2026-05-07"
    },
    {
      "code": "1101",
      "name": "台泥",
      "sector": "水泥",
      "price": 25.5,
      "chg_pct": 1.8,
      "k": 56.0,
      "d": 39.7,
      "j": 88.7,
      "ma5": 24.72,
      "ma20": 24.78,
      "ma_gap": 0.2,
      "volume": 37444,
      "avg_vol5": 29743.1,
      "vol_ratio": 1.26,
      "buy_days": 0,
      "net_buy_ratio": 0.0,
      "foreign_buy_days": 2,
      "dif": 0.0907,
      "score": 1,
      "criteria": {
        "s1": false,
        "s2": false,
        "s3": false,
        "s4": false,
        "s5": true,
        "s6": false
      },
      "updated": "2026-05-07"
    },
    {
      "code": "1402",
      "name": "遠東新",
      "sector": "紡織",
      "price": 26.0,
      "chg_pct": -0.38,
      "k": 53.2,
      "d": 40.1,
      "j": 79.4,
      "ma5": 25.8,
      "ma20": 26.16,
      "ma_gap": 1.4,
      "volume": 12458,
      "avg_vol5": 11096.3,
      "vol_ratio": 1.12,
      "buy_days": 0,
      "net_buy_ratio": 0.0,
      "foreign_buy_days": 0,
      "dif": -0.2709,
      "score": 1,
      "criteria": {
        "s1": false,
        "s2": false,
        "s3": false,
        "s4": false,
        "s5": true,
        "s6": false
      },
      "updated": "2026-05-07"
    },
    {
      "code": "9945",
      "name": "潤泰新",
      "sector": "其他",
      "price": 23.6,
      "chg_pct": 0.64,
      "k": 19.6,
      "d": 13.1,
      "j": 32.7,
      "ma5": 23.46,
      "ma20": 24.41,
      "ma_gap": 3.9,
      "volume": 7937,
      "avg_vol5": 6219.3,
      "vol_ratio": 1.28,
      "buy_days": 0,
      "net_buy_ratio": 0.0,
      "foreign_buy_days": 3,
      "dif": -0.7033,
      "score": 1,
      "criteria": {
        "s1": false,
        "s2": false,
        "s3": false,
        "s4": false,
        "s5": false,
        "s6": true
      },
      "updated": "2026-05-07"
    },
    {
      "code": "6176",
      "name": "瑞儀",
      "sector": "光電",
      "price": 102.0,
      "chg_pct": -0.49,
      "k": 38.2,
      "d": 43.0,
      "j": 28.6,
      "ma5": 101.54,
      "ma20": 96.69,
      "ma_gap": 5.0,
      "volume": 6271,
      "avg_vol5": 8940.6,
      "vol_ratio": 0.7,
      "buy_days": 0,
      "net_buy_ratio": 0.0,
      "foreign_buy_days": 0,
      "dif": 1.4609,
      "score": 1,
      "criteria": {
        "s1": false,
        "s2": false,
        "s3": true,
        "s4": false,
        "s5": false,
        "s6": false
      },
      "updated": "2026-05-07"
    },
    {
      "code": "3017",
      "name": "奇鋐",
      "sector": "電腦週邊",
      "price": 2415.0,
      "chg_pct": -0.82,
      "k": 28.5,
      "d": 50.1,
      "j": -14.7,
      "ma5": 2655.0,
      "ma20": 2563.75,
      "ma_gap": 3.6,
      "volume": 11314,
      "avg_vol5": 6232.6,
      "vol_ratio": 1.82,
      "buy_days": 0,
      "net_buy_ratio": 0.0,
      "foreign_buy_days": 0,
      "dif": 143.216,
      "score": 1,
      "criteria": {
        "s1": false,
        "s2": false,
        "s3": true,
        "s4": false,
        "s5": false,
        "s6": false
      },
      "updated": "2026-05-07"
    },
    {
      "code": "1308",
      "name": "亞聚",
      "sector": "塑膠",
      "price": 13.75,
      "chg_pct": 0.36,
      "k": 10.0,
      "d": 10.9,
      "j": 8.2,
      "ma5": 14.16,
      "ma20": 15.33,
      "ma_gap": 7.6,
      "volume": 3750,
      "avg_vol5": 4299.2,
      "vol_ratio": 0.87,
      "buy_days": 0,
      "net_buy_ratio": 0.0,
      "foreign_buy_days": 3,
      "dif": -0.614,
      "score": 1,
      "criteria": {
        "s1": false,
        "s2": false,
        "s3": false,
        "s4": false,
        "s5": false,
        "s6": true
      },
      "updated": "2026-05-07"
    },
    {
      "code": "1326",
      "name": "台化",
      "sector": "塑膠",
      "price": 49.45,
      "chg_pct": -3.04,
      "k": 42.6,
      "d": 50.6,
      "j": 26.5,
      "ma5": 51.07,
      "ma20": 50.45,
      "ma_gap": 1.2,
      "volume": 28788,
      "avg_vol5": 28713.6,
      "vol_ratio": 1.0,
      "buy_days": 0,
      "net_buy_ratio": 0.0,
      "foreign_buy_days": 0,
      "dif": 1.1961,
      "score": 1,
      "criteria": {
        "s1": false,
        "s2": false,
        "s3": true,
        "s4": false,
        "s5": false,
        "s6": false
      },
      "updated": "2026-05-07"
    },
    {
      "code": "1722",
      "name": "台肥",
      "sector": "化學",
      "price": 46.8,
      "chg_pct": -0.11,
      "k": 40.8,
      "d": 42.0,
      "j": 38.3,
      "ma5": 47.92,
      "ma20": 46.23,
      "ma_gap": 3.7,
      "volume": 4965,
      "avg_vol5": 16826.0,
      "vol_ratio": 0.3,
      "buy_days": 2,
      "net_buy_ratio": 0.58,
      "foreign_buy_days": 0,
      "dif": 0.3237,
      "score": 1,
      "criteria": {
        "s1": false,
        "s2": false,
        "s3": true,
        "s4": false,
        "s5": false,
        "s6": false
      },
      "updated": "2026-05-07"
    },
    {
      "code": "1504",
      "name": "東元",
      "sector": "電機機械",
      "price": 74.0,
      "chg_pct": 9.96,
      "k": 75.5,
      "d": 63.5,
      "j": 99.7,
      "ma5": 68.16,
      "ma20": 63.28,
      "ma_gap": 7.7,
      "volume": 43630,
      "avg_vol5": 26652.8,
      "vol_ratio": 1.64,
      "buy_days": 0,
      "net_buy_ratio": 0.0,
      "foreign_buy_days": 1,
      "dif": 0.6959,
      "score": 1,
      "criteria": {
        "s1": false,
        "s2": false,
        "s3": false,
        "s4": true,
        "s5": false,
        "s6": false
      },
      "updated": "2026-05-07"
    },
    {
      "code": "1513",
      "name": "中興電",
      "sector": "電機機械",
      "price": 156.5,
      "chg_pct": 0.64,
      "k": 64.0,
      "d": 49.9,
      "j": 92.1,
      "ma5": 154.0,
      "ma20": 152.25,
      "ma_gap": 1.1,
      "volume": 5841,
      "avg_vol5": 7933.8,
      "vol_ratio": 0.74,
      "buy_days": 0,
      "net_buy_ratio": 0.0,
      "foreign_buy_days": 0,
      "dif": -0.1754,
      "score": 1,
      "criteria": {
        "s1": false,
        "s2": false,
        "s3": false,
        "s4": false,
        "s5": true,
        "s6": false
      },
      "updated": "2026-05-07"
    },
    {
      "code": "1519",
      "name": "華城",
      "sector": "電機機械",
      "price": 891.0,
      "chg_pct": 0.45,
      "k": 40.0,
      "d": 44.0,
      "j": 32.0,
      "ma5": 895.6,
      "ma20": 874.4,
      "ma_gap": 2.4,
      "volume": 2257,
      "avg_vol5": 3213.7,
      "vol_ratio": 0.7,
      "buy_days": 0,
      "net_buy_ratio": 0.0,
      "foreign_buy_days": 0,
      "dif": 3.3556,
      "score": 1,
      "criteria": {
        "s1": false,
        "s2": false,
        "s3": true,
        "s4": false,
        "s5": false,
        "s6": false
      },
      "updated": "2026-05-07"
    },
    {
      "code": "2371",
      "name": "大同",
      "sector": "電機機械",
      "price": 30.85,
      "chg_pct": 1.48,
      "k": 37.3,
      "d": 29.2,
      "j": 53.6,
      "ma5": 30.53,
      "ma20": 31.27,
      "ma_gap": 2.4,
      "volume": 17001,
      "avg_vol5": 13635.3,
      "vol_ratio": 1.25,
      "buy_days": 2,
      "net_buy_ratio": 0.3,
      "foreign_buy_days": 1,
      "dif": -0.5179,
      "score": 1,
      "criteria": {
        "s1": false,
        "s2": false,
        "s3": false,
        "s4": false,
        "s5": true,
        "s6": false
      },
      "updated": "2026-05-07"
    },
    {
      "code": "2367",
      "name": "燿華",
      "sector": "電子零組件",
      "price": 61.4,
      "chg_pct": 0.82,
      "k": 52.5,
      "d": 33.9,
      "j": 89.8,
      "ma5": 60.06,
      "ma20": 65.45,
      "ma_gap": 8.2,
      "volume": 32406,
      "avg_vol5": 42258.2,
      "vol_ratio": 0.77,
      "buy_days": 0,
      "net_buy_ratio": 0.0,
      "foreign_buy_days": 3,
      "dif": -2.8067,
      "score": 1,
      "criteria": {
        "s1": false,
        "s2": false,
        "s3": false,
        "s4": false,
        "s5": false,
        "s6": true
      },
      "updated": "2026-05-07"
    },
    {
      "code": "3044",
      "name": "健鼎",
      "sector": "電子零組件",
      "price": 500.0,
      "chg_pct": 2.46,
      "k": 65.0,
      "d": 60.8,
      "j": 73.4,
      "ma5": 477.3,
      "ma20": 438.52,
      "ma_gap": 8.8,
      "volume": 4740,
      "avg_vol5": 4822.6,
      "vol_ratio": 0.98,
      "buy_days": 4,
      "net_buy_ratio": 3.63,
      "foreign_buy_days": 1,
      "dif": 28.9387,
      "score": 1,
      "criteria": {
        "s1": true,
        "s2": false,
        "s3": false,
        "s4": false,
        "s5": false,
        "s6": false
      },
      "updated": "2026-05-07"
    },
    {
      "code": "6213",
      "name": "聯茂",
      "sector": "電子零組件",
      "price": 299.5,
      "chg_pct": 5.09,
      "k": 68.6,
      "d": 57.9,
      "j": 89.9,
      "ma5": 285.7,
      "ma20": 261.32,
      "ma_gap": 9.3,
      "volume": 9973,
      "avg_vol5": 6534.5,
      "vol_ratio": 1.53,
      "buy_days": 0,
      "net_buy_ratio": 0.0,
      "foreign_buy_days": 0,
      "dif": 28.8981,
      "score": 1,
      "criteria": {
        "s1": false,
        "s2": false,
        "s3": false,
        "s4": true,
        "s5": false,
        "s6": false
      },
      "updated": "2026-05-07"
    },
    {
      "code": "6271",
      "name": "同欣電",
      "sector": "電子零組件",
      "price": 180.0,
      "chg_pct": 0.28,
      "k": 52.0,
      "d": 40.3,
      "j": 75.2,
      "ma5": 177.6,
      "ma20": 178.45,
      "ma_gap": 0.5,
      "volume": 6450,
      "avg_vol5": 5573.2,
      "vol_ratio": 1.16,
      "buy_days": 0,
      "net_buy_ratio": 0.0,
      "foreign_buy_days": 2,
      "dif": 4.2381,
      "score": 1,
      "criteria": {
        "s1": false,
        "s2": false,
        "s3": false,
        "s4": false,
        "s5": true,
        "s6": false
      },
      "updated": "2026-05-07"
    },
    {
      "code": "2327",
      "name": "國巨",
      "sector": "被動元件",
      "price": 371.5,
      "chg_pct": 9.91,
      "k": 82.3,
      "d": 73.2,
      "j": 100.5,
      "ma5": 343.5,
      "ma20": 318.32,
      "ma_gap": 7.9,
      "volume": 52951,
      "avg_vol5": 40506.6,
      "vol_ratio": 1.31,
      "buy_days": 4,
      "net_buy_ratio": 4.12,
      "foreign_buy_days": 1,
      "dif": 18.5297,
      "score": 1,
      "criteria": {
        "s1": true,
        "s2": false,
        "s3": false,
        "s4": false,
        "s5": false,
        "s6": false
      },
      "updated": "2026-05-07"
    },
    {
      "code": "3023",
      "name": "信邦",
      "sector": "電子零組件",
      "price": 310.0,
      "chg_pct": 1.47,
      "k": 76.3,
      "d": 64.7,
      "j": 99.4,
      "ma5": 295.3,
      "ma20": 282.07,
      "ma_gap": 4.7,
      "volume": 3490,
      "avg_vol5": 2961.1,
      "vol_ratio": 1.18,
      "buy_days": 0,
      "net_buy_ratio": 0.0,
      "foreign_buy_days": 14,
      "dif": 10.5892,
      "score": 1,
      "criteria": {
        "s1": false,
        "s2": false,
        "s3": false,
        "s4": false,
        "s5": false,
        "s6": true
      },
      "updated": "2026-05-07"
    },
    {
      "code": "3661",
      "name": "世芯-KY",
      "sector": "半導體",
      "price": 4795.0,
      "chg_pct": 5.04,
      "k": 82.7,
      "d": 77.3,
      "j": 93.3,
      "ma5": 4379.0,
      "ma20": 3817.0,
      "ma_gap": 14.7,
      "volume": 3080,
      "avg_vol5": 2512.1,
      "vol_ratio": 1.23,
      "buy_days": 2,
      "net_buy_ratio": 8.28,
      "foreign_buy_days": 0,
      "dif": 349.1117,
      "score": 1,
      "criteria": {
        "s1": false,
        "s2": true,
        "s3": false,
        "s4": false,
        "s5": false,
        "s6": false
      },
      "updated": "2026-05-07"
    },
    {
      "code": "6415",
      "name": "矽力-KY",
      "sector": "半導體",
      "price": 424.5,
      "chg_pct": 0.12,
      "k": 63.0,
      "d": 71.9,
      "j": 45.3,
      "ma5": 429.3,
      "ma20": 370.0,
      "ma_gap": 16.0,
      "volume": 2237,
      "avg_vol5": 2989.8,
      "vol_ratio": 0.75,
      "buy_days": 2,
      "net_buy_ratio": 0.49,
      "foreign_buy_days": 5,
      "dif": 37.3701,
      "score": 1,
      "criteria": {
        "s1": false,
        "s2": false,
        "s3": false,
        "s4": false,
        "s5": false,
        "s6": true
      },
      "updated": "2026-05-07"
    },
    {
      "code": "3532",
      "name": "台勝科",
      "sector": "半導體",
      "price": 263.0,
      "chg_pct": 4.99,
      "k": 87.4,
      "d": 76.5,
      "j": 109.0,
      "ma5": 227.6,
      "ma20": 191.6,
      "ma_gap": 18.8,
      "volume": 16975,
      "avg_vol5": 7730.8,
      "vol_ratio": 2.2,
      "buy_days": 2,
      "net_buy_ratio": 0.18,
      "foreign_buy_days": 0,
      "dif": 22.2577,
      "score": 1,
      "criteria": {
        "s1": false,
        "s2": false,
        "s3": false,
        "s4": true,
        "s5": false,
        "s6": false
      },
      "updated": "2026-05-07"
    },
    {
      "code": "8028",
      "name": "昇陽半導體",
      "sector": "半導體",
      "price": 229.0,
      "chg_pct": -3.17,
      "k": 55.8,
      "d": 68.1,
      "j": 31.2,
      "ma5": 239.2,
      "ma20": 217.85,
      "ma_gap": 9.8,
      "volume": 10198,
      "avg_vol5": 15515.3,
      "vol_ratio": 0.66,
      "buy_days": 3,
      "net_buy_ratio": 4.41,
      "foreign_buy_days": 0,
      "dif": 13.8413,
      "score": 1,
      "criteria": {
        "s1": true,
        "s2": false,
        "s3": false,
        "s4": false,
        "s5": false,
        "s6": false
      },
      "updated": "2026-05-07"
    },
    {
      "code": "6414",
      "name": "樺漢",
      "sector": "電腦週邊",
      "price": 351.5,
      "chg_pct": 0.86,
      "k": 90.9,
      "d": 87.5,
      "j": 97.5,
      "ma5": 340.2,
      "ma20": 313.27,
      "ma_gap": 8.6,
      "volume": 2110,
      "avg_vol5": 1716.9,
      "vol_ratio": 1.23,
      "buy_days": 0,
      "net_buy_ratio": 0.0,
      "foreign_buy_days": 14,
      "dif": 16.4202,
      "score": 1,
      "criteria": {
        "s1": false,
        "s2": false,
        "s3": false,
        "s4": false,
        "s5": false,
        "s6": true
      },
      "updated": "2026-05-07"
    },
    {
      "code": "3702",
      "name": "大聯大",
      "sector": "電子通路",
      "price": 103.5,
      "chg_pct": -0.48,
      "k": 83.2,
      "d": 77.5,
      "j": 94.7,
      "ma5": 103.1,
      "ma20": 99.03,
      "ma_gap": 4.1,
      "volume": 6236,
      "avg_vol5": 8601.8,
      "vol_ratio": 0.72,
      "buy_days": 0,
      "net_buy_ratio": 0.0,
      "foreign_buy_days": 14,
      "dif": 4.1286,
      "score": 1,
      "criteria": {
        "s1": false,
        "s2": false,
        "s3": false,
        "s4": false,
        "s5": false,
        "s6": true
      },
      "updated": "2026-05-07"
    },
    {
      "code": "2404",
      "name": "漢唐",
      "sector": "其他電子",
      "price": 997.0,
      "chg_pct": 1.32,
      "k": 50.4,
      "d": 43.1,
      "j": 65.2,
      "ma5": 977.2,
      "ma20": 966.1,
      "ma_gap": 1.1,
      "volume": 3370,
      "avg_vol5": 3138.8,
      "vol_ratio": 1.07,
      "buy_days": 0,
      "net_buy_ratio": 0.0,
      "foreign_buy_days": 2,
      "dif": 12.1723,
      "score": 1,
      "criteria": {
        "s1": false,
        "s2": false,
        "s3": false,
        "s4": false,
        "s5": true,
        "s6": false
      },
      "updated": "2026-05-07"
    },
    {
      "code": "2474",
      "name": "可成",
      "sector": "其他電子",
      "price": 206.0,
      "chg_pct": -1.67,
      "k": 17.5,
      "d": 30.6,
      "j": -8.6,
      "ma5": 209.3,
      "ma20": 209.47,
      "ma_gap": 0.1,
      "volume": 4206,
      "avg_vol5": 5625.7,
      "vol_ratio": 0.75,
      "buy_days": 0,
      "net_buy_ratio": 0.0,
      "foreign_buy_days": 0,
      "dif": 4.5482,
      "score": 1,
      "criteria": {
        "s1": false,
        "s2": false,
        "s3": true,
        "s4": false,
        "s5": false,
        "s6": false
      },
      "updated": "2026-05-07"
    },
    {
      "code": "3005",
      "name": "神基",
      "sector": "電腦週邊",
      "price": 99.1,
      "chg_pct": 1.64,
      "k": 53.7,
      "d": 40.7,
      "j": 79.7,
      "ma5": 98.16,
      "ma20": 98.67,
      "ma_gap": 0.5,
      "volume": 2988,
      "avg_vol5": 2740.6,
      "vol_ratio": 1.09,
      "buy_days": 0,
      "net_buy_ratio": 0.0,
      "foreign_buy_days": 1,
      "dif": -3.0881,
      "score": 1,
      "criteria": {
        "s1": false,
        "s2": false,
        "s3": false,
        "s4": false,
        "s5": true,
        "s6": false
      },
      "updated": "2026-05-07"
    },
    {
      "code": "2634",
      "name": "漢翔",
      "sector": "航運",
      "price": 49.5,
      "chg_pct": 1.12,
      "k": 55.8,
      "d": 43.7,
      "j": 80.0,
      "ma5": 48.87,
      "ma20": 48.54,
      "ma_gap": 0.7,
      "volume": 3977,
      "avg_vol5": 4623.0,
      "vol_ratio": 0.86,
      "buy_days": 0,
      "net_buy_ratio": 0.0,
      "foreign_buy_days": 1,
      "dif": -0.1502,
      "score": 1,
      "criteria": {
        "s1": false,
        "s2": false,
        "s3": false,
        "s4": false,
        "s5": true,
        "s6": false
      },
      "updated": "2026-05-07"
    },
    {
      "code": "8932",
      "name": "智通",
      "sector": "資訊服務",
      "price": 91.5,
      "chg_pct": -0.54,
      "k": 31.1,
      "d": 28.9,
      "j": 35.3,
      "ma5": 90.86,
      "ma20": 90.26,
      "ma_gap": 0.7,
      "volume": 1813,
      "avg_vol5": 3137.4,
      "vol_ratio": 0.58,
      "buy_days": 0,
      "net_buy_ratio": 0.0,
      "foreign_buy_days": 0,
      "dif": -3.2693,
      "score": 1,
      "criteria": {
        "s1": false,
        "s2": false,
        "s3": false,
        "s4": false,
        "s5": true,
        "s6": false
      },
      "updated": "2026-05-07"
    },
    {
      "code": "5388",
      "name": "中磊",
      "sector": "通信網路",
      "price": 80.3,
      "chg_pct": 2.42,
      "k": 31.5,
      "d": 23.2,
      "j": 48.1,
      "ma5": 78.42,
      "ma20": 80.99,
      "ma_gap": 3.2,
      "volume": 12668,
      "avg_vol5": 2813.0,
      "vol_ratio": 4.5,
      "buy_days": 0,
      "net_buy_ratio": 0.0,
      "foreign_buy_days": 1,
      "dif": -0.5144,
      "score": 1,
      "criteria": {
        "s1": false,
        "s2": false,
        "s3": false,
        "s4": true,
        "s5": false,
        "s6": false
      },
      "updated": "2026-05-07"
    },
    {
      "code": "3596",
      "name": "智易",
      "sector": "通信網路",
      "price": 167.5,
      "chg_pct": -0.89,
      "k": 47.1,
      "d": 32.8,
      "j": 75.7,
      "ma5": 165.0,
      "ma20": 169.32,
      "ma_gap": 2.6,
      "volume": 1362,
      "avg_vol5": 831.0,
      "vol_ratio": 1.64,
      "buy_days": 0,
      "net_buy_ratio": 0.0,
      "foreign_buy_days": 0,
      "dif": -3.5816,
      "score": 1,
      "criteria": {
        "s1": false,
        "s2": false,
        "s3": false,
        "s4": false,
        "s5": true,
        "s6": false
      },
      "updated": "2026-05-07"
    },
    {
      "code": "2449",
      "name": "京元電子",
      "sector": "半導體",
      "price": 339.0,
      "chg_pct": 3.2,
      "k": 71.3,
      "d": 66.2,
      "j": 81.4,
      "ma5": 331.3,
      "ma20": 295.4,
      "ma_gap": 12.2,
      "volume": 30226,
      "avg_vol5": 50587.4,
      "vol_ratio": 0.6,
      "buy_days": 3,
      "net_buy_ratio": 0.98,
      "foreign_buy_days": 0,
      "dif": 11.7026,
      "score": 1,
      "criteria": {
        "s1": true,
        "s2": false,
        "s3": false,
        "s4": false,
        "s5": false,
        "s6": false
      },
      "updated": "2026-05-07"
    },
    {
      "code": "3576",
      "name": "聯合再生",
      "sector": "光電",
      "price": 17.2,
      "chg_pct": 9.9,
      "k": 60.4,
      "d": 41.2,
      "j": 98.7,
      "ma5": 15.95,
      "ma20": 16.56,
      "ma_gap": 3.7,
      "volume": 34206,
      "avg_vol5": 20923.3,
      "vol_ratio": 1.63,
      "buy_days": 0,
      "net_buy_ratio": 0.0,
      "foreign_buy_days": 1,
      "dif": -1.0888,
      "score": 1,
      "criteria": {
        "s1": false,
        "s2": false,
        "s3": false,
        "s4": true,
        "s5": false,
        "s6": false
      },
      "updated": "2026-05-07"
    },
    {
      "code": "2312",
      "name": "金寶",
      "sector": "電腦週邊",
      "price": 28.55,
      "chg_pct": 1.96,
      "k": 52.3,
      "d": 51.7,
      "j": 53.6,
      "ma5": 28.03,
      "ma20": 26.24,
      "ma_gap": 6.8,
      "volume": 44192,
      "avg_vol5": 57975.6,
      "vol_ratio": 0.76,
      "buy_days": 0,
      "net_buy_ratio": 0.0,
      "foreign_buy_days": 3,
      "dif": 1.2947,
      "score": 1,
      "criteria": {
        "s1": false,
        "s2": false,
        "s3": false,
        "s4": false,
        "s5": false,
        "s6": true
      },
      "updated": "2026-05-07"
    },
    {
      "code": "4749",
      "name": "新應材",
      "sector": "半導體材料",
      "price": 987.0,
      "chg_pct": -2.28,
      "k": 43.1,
      "d": 50.8,
      "j": 27.8,
      "ma5": 1002.6,
      "ma20": 963.6,
      "ma_gap": 4.0,
      "volume": 3245,
      "avg_vol5": 3530.6,
      "vol_ratio": 0.92,
      "buy_days": 0,
      "net_buy_ratio": 0.0,
      "foreign_buy_days": 0,
      "dif": 29.9144,
      "score": 1,
      "criteria": {
        "s1": false,
        "s2": false,
        "s3": true,
        "s4": false,
        "s5": false,
        "s6": false
      },
      "updated": "2026-05-07"
    },
    {
      "code": "2454",
      "name": "聯發科",
      "sector": "半導體",
      "price": 3420.0,
      "chg_pct": -0.29,
      "k": 95.9,
      "d": 94.5,
      "j": 98.7,
      "ma5": 3097.0,
      "ma20": 2307.25,
      "ma_gap": 34.2,
      "volume": 8465,
      "avg_vol5": 16887.8,
      "vol_ratio": 0.5,
      "buy_days": 0,
      "net_buy_ratio": 0.0,
      "foreign_buy_days": 0,
      "dif": 399.7836,
      "score": 0,
      "criteria": {
        "s1": false,
        "s2": false,
        "s3": false,
        "s4": false,
        "s5": false,
        "s6": false
      },
      "updated": "2026-05-07"
    },
    {
      "code": "2882",
      "name": "國泰金",
      "sector": "金融保險",
      "price": 79.0,
      "chg_pct": 0.38,
      "k": 76.6,
      "d": 70.6,
      "j": 88.7,
      "ma5": 77.66,
      "ma20": 75.25,
      "ma_gap": 3.2,
      "volume": 24209,
      "avg_vol5": 39243.7,
      "vol_ratio": 0.62,
      "buy_days": 1,
      "net_buy_ratio": 0.72,
      "foreign_buy_days": 0,
      "dif": 1.3293,
      "score": 0,
      "criteria": {
        "s1": false,
        "s2": false,
        "s3": false,
        "s4": false,
        "s5": false,
        "s6": false
      },
      "updated": "2026-05-07"
    },
    {
      "code": "2002",
      "name": "中鋼",
      "sector": "鋼鐵",
      "price": 18.85,
      "chg_pct": 0.27,
      "k": 30.2,
      "d": 18.4,
      "j": 53.9,
      "ma5": 18.72,
      "ma20": 19.43,
      "ma_gap": 3.7,
      "volume": 50917,
      "avg_vol5": 45163.3,
      "vol_ratio": 1.13,
      "buy_days": 1,
      "net_buy_ratio": 0.02,
      "foreign_buy_days": 1,
      "dif": -0.2661,
      "score": 0,
      "criteria": {
        "s1": false,
        "s2": false,
        "s3": false,
        "s4": false,
        "s5": false,
        "s6": false
      },
      "updated": "2026-05-07"
    },
    {
      "code": "1303",
      "name": "南亞",
      "sector": "塑膠",
      "price": 90.3,
      "chg_pct": -3.73,
      "k": 58.6,
      "d": 64.0,
      "j": 47.8,
      "ma5": 91.22,
      "ma20": 88.39,
      "ma_gap": 3.2,
      "volume": 74376,
      "avg_vol5": 105602.9,
      "vol_ratio": 0.7,
      "buy_days": 0,
      "net_buy_ratio": 0.0,
      "foreign_buy_days": 0,
      "dif": 2.5339,
      "score": 0,
      "criteria": {
        "s1": false,
        "s2": false,
        "s3": false,
        "s4": false,
        "s5": false,
        "s6": false
      },
      "updated": "2026-05-07"
    },
    {
      "code": "2337",
      "name": "旺宏",
      "sector": "半導體",
      "price": 164.5,
      "chg_pct": -4.36,
      "k": 75.6,
      "d": 69.4,
      "j": 88.0,
      "ma5": 161.1,
      "ma20": 146.28,
      "ma_gap": 10.1,
      "volume": 235421,
      "avg_vol5": 260691.8,
      "vol_ratio": 0.9,
      "buy_days": 0,
      "net_buy_ratio": 0.0,
      "foreign_buy_days": 0,
      "dif": 9.5355,
      "score": 0,
      "criteria": {
        "s1": false,
        "s2": false,
        "s3": false,
        "s4": false,
        "s5": false,
        "s6": false
      },
      "updated": "2026-05-07"
    },
    {
      "code": "2301",
      "name": "光寶科",
      "sector": "電腦週邊",
      "price": 203.5,
      "chg_pct": 10.0,
      "k": 76.6,
      "d": 64.6,
      "j": 100.8,
      "ma5": 179.4,
      "ma20": 168.47,
      "ma_gap": 6.5,
      "volume": 53993,
      "avg_vol5": 44669.3,
      "vol_ratio": 1.21,
      "buy_days": 0,
      "net_buy_ratio": 0.0,
      "foreign_buy_days": 2,
      "dif": 6.7441,
      "score": 0,
      "criteria": {
        "s1": false,
        "s2": false,
        "s3": false,
        "s4": false,
        "s5": false,
        "s6": false
      },
      "updated": "2026-05-07"
    },
    {
      "code": "3037",
      "name": "欣興",
      "sector": "電子零組件",
      "price": 896.0,
      "chg_pct": 4.43,
      "k": 78.7,
      "d": 83.6,
      "j": 68.8,
      "ma5": 890.2,
      "ma20": 746.6,
      "ma_gap": 19.2,
      "volume": 26519,
      "avg_vol5": 36904.7,
      "vol_ratio": 0.72,
      "buy_days": 1,
      "net_buy_ratio": 1.68,
      "foreign_buy_days": 1,
      "dif": 93.1569,
      "score": 0,
      "criteria": {
        "s1": false,
        "s2": false,
        "s3": false,
        "s4": false,
        "s5": false,
        "s6": false
      },
      "updated": "2026-05-07"
    },
    {
      "code": "2885",
      "name": "元大金",
      "sector": "金融保險",
      "price": 56.1,
      "chg_pct": -0.18,
      "k": 85.9,
      "d": 83.1,
      "j": 91.5,
      "ma5": 54.6,
      "ma20": 51.23,
      "ma_gap": 6.6,
      "volume": 30560,
      "avg_vol5": 28619.1,
      "vol_ratio": 1.07,
      "buy_days": 2,
      "net_buy_ratio": 0.55,
      "foreign_buy_days": 0,
      "dif": 2.2598,
      "score": 0,
      "criteria": {
        "s1": false,
        "s2": false,
        "s3": false,
        "s4": false,
        "s5": false,
        "s6": false
      },
      "updated": "2026-05-07"
    },
    {
      "code": "1102",
      "name": "亞泥",
      "sector": "水泥",
      "price": 34.95,
      "chg_pct": -0.71,
      "k": 27.1,
      "d": 30.5,
      "j": 20.3,
      "ma5": 35.01,
      "ma20": 35.4,
      "ma_gap": 1.1,
      "volume": 7386,
      "avg_vol5": 7742.9,
      "vol_ratio": 0.95,
      "buy_days": 0,
      "net_buy_ratio": 0.0,
      "foreign_buy_days": 0,
      "dif": -0.0214,
      "score": 0,
      "criteria": {
        "s1": false,
        "s2": false,
        "s3": false,
        "s4": false,
        "s5": false,
        "s6": false
      },
      "updated": "2026-05-07"
    },
    {
      "code": "9904",
      "name": "寶成",
      "sector": "其他",
      "price": 25.95,
      "chg_pct": 1.37,
      "k": 18.6,
      "d": 10.0,
      "j": 35.8,
      "ma5": 25.7,
      "ma20": 26.9,
      "ma_gap": 4.5,
      "volume": 14714,
      "avg_vol5": 11441.0,
      "vol_ratio": 1.29,
      "buy_days": 0,
      "net_buy_ratio": 0.0,
      "foreign_buy_days": 0,
      "dif": -0.8346,
      "score": 0,
      "criteria": {
        "s1": false,
        "s2": false,
        "s3": false,
        "s4": false,
        "s5": false,
        "s6": false
      },
      "updated": "2026-05-07"
    },
    {
      "code": "9921",
      "name": "巨大",
      "sector": "其他",
      "price": 67.8,
      "chg_pct": -1.45,
      "k": 48.6,
      "d": 44.1,
      "j": 57.5,
      "ma5": 68.44,
      "ma20": 68.36,
      "ma_gap": 0.1,
      "volume": 2062,
      "avg_vol5": 2099.9,
      "vol_ratio": 0.98,
      "buy_days": 0,
      "net_buy_ratio": 0.0,
      "foreign_buy_days": 0,
      "dif": -1.2776,
      "score": 0,
      "criteria": {
        "s1": false,
        "s2": false,
        "s3": false,
        "s4": false,
        "s5": false,
        "s6": false
      },
      "updated": "2026-05-07"
    },
    {
      "code": "5904",
      "name": "寶雅",
      "sector": "貿易百貨",
      "price": 587.0,
      "chg_pct": -1.84,
      "k": 83.0,
      "d": 80.7,
      "j": 87.5,
      "ma5": 580.8,
      "ma20": 537.05,
      "ma_gap": 8.1,
      "volume": 337,
      "avg_vol5": 638.5,
      "vol_ratio": 0.53,
      "buy_days": 0,
      "net_buy_ratio": 0.0,
      "foreign_buy_days": 0,
      "dif": 21.9985,
      "score": 0,
      "criteria": {
        "s1": false,
        "s2": false,
        "s3": false,
        "s4": false,
        "s5": false,
        "s6": false
      },
      "updated": "2026-05-07"
    },
    {
      "code": "2345",
      "name": "智邦",
      "sector": "通信網路",
      "price": 2560.0,
      "chg_pct": 3.02,
      "k": 85.7,
      "d": 84.0,
      "j": 89.0,
      "ma5": 2465.0,
      "ma20": 2146.5,
      "ma_gap": 14.8,
      "volume": 3820,
      "avg_vol5": 4496.1,
      "vol_ratio": 0.85,
      "buy_days": 1,
      "net_buy_ratio": 0.9,
      "foreign_buy_days": 2,
      "dif": 219.96,
      "score": 0,
      "criteria": {
        "s1": false,
        "s2": false,
        "s3": false,
        "s4": false,
        "s5": false,
        "s6": false
      },
      "updated": "2026-05-07"
    },
    {
      "code": "2409",
      "name": "友達",
      "sector": "光電",
      "price": 18.35,
      "chg_pct": 1.66,
      "k": 53.1,
      "d": 36.6,
      "j": 86.0,
      "ma5": 17.68,
      "ma20": 18.36,
      "ma_gap": 3.7,
      "volume": 263749,
      "avg_vol5": 189732.8,
      "vol_ratio": 1.39,
      "buy_days": 2,
      "net_buy_ratio": 0.02,
      "foreign_buy_days": 2,
      "dif": 0.2699,
      "score": 0,
      "criteria": {
        "s1": false,
        "s2": false,
        "s3": false,
        "s4": false,
        "s5": false,
        "s6": false
      },
      "updated": "2026-05-07"
    },
    {
      "code": "1304",
      "name": "台聚",
      "sector": "塑膠",
      "price": 13.0,
      "chg_pct": -1.52,
      "k": 13.3,
      "d": 14.5,
      "j": 10.7,
      "ma5": 13.58,
      "ma20": 14.61,
      "ma_gap": 7.0,
      "volume": 10937,
      "avg_vol5": 8702.6,
      "vol_ratio": 1.26,
      "buy_days": 0,
      "net_buy_ratio": 0.0,
      "foreign_buy_days": 1,
      "dif": -0.448,
      "score": 0,
      "criteria": {
        "s1": false,
        "s2": false,
        "s3": false,
        "s4": false,
        "s5": false,
        "s6": false
      },
      "updated": "2026-05-07"
    },
    {
      "code": "6505",
      "name": "台塑化",
      "sector": "油電燃氣",
      "price": 52.3,
      "chg_pct": -4.56,
      "k": 53.1,
      "d": 55.4,
      "j": 48.3,
      "ma5": 54.58,
      "ma20": 53.75,
      "ma_gap": 1.5,
      "volume": 16435,
      "avg_vol5": 11504.9,
      "vol_ratio": 1.43,
      "buy_days": 0,
      "net_buy_ratio": 0.0,
      "foreign_buy_days": 0,
      "dif": -0.3223,
      "score": 0,
      "criteria": {
        "s1": false,
        "s2": false,
        "s3": false,
        "s4": false,
        "s5": false,
        "s6": false
      },
      "updated": "2026-05-07"
    },
    {
      "code": "6508",
      "name": "惠光",
      "sector": "化學",
      "price": 24.55,
      "chg_pct": -1.8,
      "k": 24.4,
      "d": 27.0,
      "j": 19.3,
      "ma5": 25.28,
      "ma20": 26.01,
      "ma_gap": 2.8,
      "volume": 115,
      "avg_vol5": 54.6,
      "vol_ratio": 2.11,
      "buy_days": 0,
      "net_buy_ratio": 0.0,
      "foreign_buy_days": 1,
      "dif": -0.4633,
      "score": 0,
      "criteria": {
        "s1": false,
        "s2": false,
        "s3": false,
        "s4": false,
        "s5": false,
        "s6": false
      },
      "updated": "2026-05-07"
    },
    {
      "code": "2006",
      "name": "東和鋼鐵",
      "sector": "鋼鐵",
      "price": 67.6,
      "chg_pct": 1.35,
      "k": 39.5,
      "d": 30.1,
      "j": 58.4,
      "ma5": 66.58,
      "ma20": 68.87,
      "ma_gap": 3.3,
      "volume": 2230,
      "avg_vol5": 2457.2,
      "vol_ratio": 0.91,
      "buy_days": 0,
      "net_buy_ratio": 0.0,
      "foreign_buy_days": 1,
      "dif": -1.4249,
      "score": 0,
      "criteria": {
        "s1": false,
        "s2": false,
        "s3": false,
        "s4": false,
        "s5": false,
        "s6": false
      },
      "updated": "2026-05-07"
    },
    {
      "code": "2207",
      "name": "和泰車",
      "sector": "汽車",
      "price": 487.0,
      "chg_pct": 2.74,
      "k": 23.5,
      "d": 17.5,
      "j": 35.3,
      "ma5": 477.7,
      "ma20": 496.9,
      "ma_gap": 3.9,
      "volume": 539,
      "avg_vol5": 395.8,
      "vol_ratio": 1.36,
      "buy_days": 0,
      "net_buy_ratio": 0.0,
      "foreign_buy_days": 1,
      "dif": -7.4428,
      "score": 0,
      "criteria": {
        "s1": false,
        "s2": false,
        "s3": false,
        "s4": false,
        "s5": false,
        "s6": false
      },
      "updated": "2026-05-07"
    },
    {
      "code": "2313",
      "name": "華通",
      "sector": "電子零組件",
      "price": 249.5,
      "chg_pct": -0.2,
      "k": 62.9,
      "d": 59.5,
      "j": 69.6,
      "ma5": 257.4,
      "ma20": 253.47,
      "ma_gap": 1.6,
      "volume": 65354,
      "avg_vol5": 87416.2,
      "vol_ratio": 0.75,
      "buy_days": 0,
      "net_buy_ratio": 0.0,
      "foreign_buy_days": 1,
      "dif": 3.2029,
      "score": 0,
      "criteria": {
        "s1": false,
        "s2": false,
        "s3": false,
        "s4": false,
        "s5": false,
        "s6": false
      },
      "updated": "2026-05-07"
    },
    {
      "code": "2368",
      "name": "金像電",
      "sector": "電子零組件",
      "price": 1450.0,
      "chg_pct": 0.35,
      "k": 77.2,
      "d": 80.4,
      "j": 70.9,
      "ma5": 1441.0,
      "ma20": 1280.5,
      "ma_gap": 12.5,
      "volume": 4093,
      "avg_vol5": 5036.6,
      "vol_ratio": 0.81,
      "buy_days": 1,
      "net_buy_ratio": 2.62,
      "foreign_buy_days": 0,
      "dif": 127.6196,
      "score": 0,
      "criteria": {
        "s1": false,
        "s2": false,
        "s3": false,
        "s4": false,
        "s5": false,
        "s6": false
      },
      "updated": "2026-05-07"
    },
    {
      "code": "5269",
      "name": "祥碩",
      "sector": "半導體",
      "price": 1370.0,
      "chg_pct": 2.24,
      "k": 56.4,
      "d": 55.3,
      "j": 58.6,
      "ma5": 1363.0,
      "ma20": 1270.0,
      "ma_gap": 7.3,
      "volume": 1425,
      "avg_vol5": 1960.4,
      "vol_ratio": 0.73,
      "buy_days": 2,
      "net_buy_ratio": 0.25,
      "foreign_buy_days": 0,
      "dif": 45.4103,
      "score": 0,
      "criteria": {
        "s1": false,
        "s2": false,
        "s3": false,
        "s4": false,
        "s5": false,
        "s6": false
      },
      "updated": "2026-05-07"
    },
    {
      "code": "6239",
      "name": "力成",
      "sector": "半導體",
      "price": 230.5,
      "chg_pct": -1.71,
      "k": 60.3,
      "d": 53.4,
      "j": 74.1,
      "ma5": 223.7,
      "ma20": 215.25,
      "ma_gap": 3.9,
      "volume": 22862,
      "avg_vol5": 34304.4,
      "vol_ratio": 0.67,
      "buy_days": 1,
      "net_buy_ratio": 0.32,
      "foreign_buy_days": 0,
      "dif": 3.876,
      "score": 0,
      "criteria": {
        "s1": false,
        "s2": false,
        "s3": false,
        "s4": false,
        "s5": false,
        "s6": false
      },
      "updated": "2026-05-07"
    },
    {
      "code": "2377",
      "name": "微星",
      "sector": "電腦週邊",
      "price": 101.0,
      "chg_pct": 1.0,
      "k": 56.6,
      "d": 49.4,
      "j": 70.9,
      "ma5": 97.9,
      "ma20": 94.44,
      "ma_gap": 3.7,
      "volume": 17013,
      "avg_vol5": 14089.3,
      "vol_ratio": 1.21,
      "buy_days": 1,
      "net_buy_ratio": 0.08,
      "foreign_buy_days": 0,
      "dif": 1.9713,
      "score": 0,
      "criteria": {
        "s1": false,
        "s2": false,
        "s3": false,
        "s4": false,
        "s5": false,
        "s6": false
      },
      "updated": "2026-05-07"
    },
    {
      "code": "2633",
      "name": "台灣高鐵",
      "sector": "航運",
      "price": 26.35,
      "chg_pct": -0.19,
      "k": 29.8,
      "d": 33.7,
      "j": 22.1,
      "ma5": 26.41,
      "ma20": 26.65,
      "ma_gap": 0.9,
      "volume": 7624,
      "avg_vol5": 4914.8,
      "vol_ratio": 1.55,
      "buy_days": 0,
      "net_buy_ratio": 0.0,
      "foreign_buy_days": 0,
      "dif": -0.0587,
      "score": 0,
      "criteria": {
        "s1": false,
        "s2": false,
        "s3": false,
        "s4": false,
        "s5": false,
        "s6": false
      },
      "updated": "2026-05-07"
    },
    {
      "code": "2707",
      "name": "晶華",
      "sector": "觀光",
      "price": 170.0,
      "chg_pct": 0.0,
      "k": 27.5,
      "d": 20.3,
      "j": 41.9,
      "ma5": 170.0,
      "ma20": 178.35,
      "ma_gap": 4.7,
      "volume": 145,
      "avg_vol5": 331.7,
      "vol_ratio": 0.44,
      "buy_days": 0,
      "net_buy_ratio": 0.0,
      "foreign_buy_days": 0,
      "dif": -4.4173,
      "score": 0,
      "criteria": {
        "s1": false,
        "s2": false,
        "s3": false,
        "s4": false,
        "s5": false,
        "s6": false
      },
      "updated": "2026-05-07"
    },
    {
      "code": "9939",
      "name": "宏全",
      "sector": "其他",
      "price": 110.5,
      "chg_pct": -0.45,
      "k": 10.5,
      "d": 16.9,
      "j": -2.3,
      "ma5": 111.4,
      "ma20": 113.35,
      "ma_gap": 1.7,
      "volume": 1484,
      "avg_vol5": 924.5,
      "vol_ratio": 1.61,
      "buy_days": 0,
      "net_buy_ratio": 0.0,
      "foreign_buy_days": 0,
      "dif": -1.6479,
      "score": 0,
      "criteria": {
        "s1": false,
        "s2": false,
        "s3": false,
        "s4": false,
        "s5": false,
        "s6": false
      },
      "updated": "2026-05-07"
    },
    {
      "code": "8464",
      "name": "億豐",
      "sector": "其他",
      "price": 327.0,
      "chg_pct": -3.82,
      "k": 15.4,
      "d": 19.8,
      "j": 6.6,
      "ma5": 341.3,
      "ma20": 357.73,
      "ma_gap": 4.6,
      "volume": 1712,
      "avg_vol5": 824.4,
      "vol_ratio": 2.08,
      "buy_days": 0,
      "net_buy_ratio": 0.0,
      "foreign_buy_days": 0,
      "dif": -7.9157,
      "score": 0,
      "criteria": {
        "s1": false,
        "s2": false,
        "s3": false,
        "s4": false,
        "s5": false,
        "s6": false
      },
      "updated": "2026-05-07"
    },
    {
      "code": "2360",
      "name": "致茂",
      "sector": "其他電子",
      "price": 2325.0,
      "chg_pct": -0.85,
      "k": 74.7,
      "d": 70.2,
      "j": 83.6,
      "ma5": 2267.0,
      "ma20": 2050.75,
      "ma_gap": 10.5,
      "volume": 4128,
      "avg_vol5": 4824.1,
      "vol_ratio": 0.86,
      "buy_days": 0,
      "net_buy_ratio": 0.0,
      "foreign_buy_days": 0,
      "dif": 171.1071,
      "score": 0,
      "criteria": {
        "s1": false,
        "s2": false,
        "s3": false,
        "s4": false,
        "s5": false,
        "s6": false
      },
      "updated": "2026-05-07"
    },
    {
      "code": "6412",
      "name": "群電",
      "sector": "電子零組件",
      "price": 87.1,
      "chg_pct": -0.11,
      "k": 61.2,
      "d": 57.4,
      "j": 68.8,
      "ma5": 86.96,
      "ma20": 80.63,
      "ma_gap": 7.9,
      "volume": 1774,
      "avg_vol5": 5784.4,
      "vol_ratio": 0.31,
      "buy_days": 0,
      "net_buy_ratio": 0.0,
      "foreign_buy_days": 1,
      "dif": 1.8688,
      "score": 0,
      "criteria": {
        "s1": false,
        "s2": false,
        "s3": false,
        "s4": false,
        "s5": false,
        "s6": false
      },
      "updated": "2026-05-07"
    },
    {
      "code": "1476",
      "name": "儒鴻",
      "sector": "紡織",
      "price": 335.0,
      "chg_pct": 0.6,
      "k": 51.8,
      "d": 47.2,
      "j": 61.0,
      "ma5": 335.5,
      "ma20": 337.3,
      "ma_gap": 0.5,
      "volume": 992,
      "avg_vol5": 881.0,
      "vol_ratio": 1.13,
      "buy_days": 1,
      "net_buy_ratio": 0.18,
      "foreign_buy_days": 0,
      "dif": -5.2908,
      "score": 0,
      "criteria": {
        "s1": false,
        "s2": false,
        "s3": false,
        "s4": false,
        "s5": false,
        "s6": false
      },
      "updated": "2026-05-07"
    }
  ]
}