{
  "updated_at": "2026-03-24T03:35:22.952554+00:00",
  "updated_at_tw": "11:35",
  "prices": [
    {
      "id": "2605",
      "name": "新興",
      "price": 41.3,
      "prev_close": 39.85,
      "change_pct": 3.64,
      "high": 42.5,
      "low": 39.55,
      "vol": 34960,
      "is_realtime": false
    },
    {
      "id": "2481",
      "name": "強茂",
      "price": 97.6,
      "prev_close": 92.0,
      "change_pct": 6.09,
      "high": 100.5,
      "low": 94.4,
      "vol": 25191,
      "is_realtime": false
    },
    {
      "id": "6213",
      "name": "聯茂",
      "price": 133.0,
      "prev_close": 136.0,
      "change_pct": -2.21,
      "high": 139.5,
      "low": 130.0,
      "vol": 5056,
      "is_realtime": false
    },
    {
      "id": "8932",
      "name": "智通*",
      "price": 82.5,
      "prev_close": 81.7,
      "change_pct": 0.98,
      "high": 85.0,
      "low": 81.6,
      "vol": 1023,
      "is_realtime": false
    },
    {
      "id": "2317",
      "name": "鴻海",
      "price": 196.0,
      "prev_close": 196.0,
      "change_pct": 0.0,
      "high": 199.5,
      "low": 194.0,
      "vol": 36608,
      "is_realtime": false
    },
    {
      "id": "2313",
      "name": "華通",
      "price": 215.0,
      "prev_close": 216.0,
      "change_pct": -0.46,
      "high": 227.5,
      "low": 205.0,
      "vol": 59916,
      "is_realtime": false
    },
    {
      "id": "2303",
      "name": "聯電",
      "price": 56.6,
      "prev_close": 56.7,
      "change_pct": -0.18,
      "high": 57.5,
      "low": 55.7,
      "vol": 30057,
      "is_realtime": false
    },
    {
      "id": "2618",
      "name": "長榮航",
      "price": 35.4,
      "prev_close": 34.85,
      "change_pct": 1.58,
      "high": 36.1,
      "low": 35.25,
      "vol": 21563,
      "is_realtime": false
    }
  ]
}